Workbook

Sheet Cover
B2: Microsoft Corporation
B3: MSFT
B4: 12/04/2025

Sheet Summary
B2: Microsoft Corporation
B3: Ticker | C3: MSFT
B4: Current Stock Price | C4: 477.73 | D4: As of 12/04/2025
B5: Weighted Implied Stock Price | C5: =(C9*D9)+(C10*D10) -> 433.58149
B6: Implied Upside/Downside | C6: =(C4/C5-1) -> 0.10182286
B8: Method | C8: Weight | D8: Price Target
B9: DCF | C9: 0.5 | D9: =(C13*D13)+(C14*D14)+(C15*D15) -> 163.13436
B10: Relative Valuation | C10: 0.5 | D10: =(C18*D18)+(C19*D19)+(C20*D20)+(C21*D21) -> 704.02863
B12: DCF Case | C12: Weight | D12: Price Target
B13: Base | C13: 0.6 | D13: ='DCF Base'!K48 -> 274.60786
B14: Bear | C14: 0.2 | D14: ='DCF Bear'!K48 -> -4.0661202
B15: Bull | C15: 0.2 | D15: ='DCF Bull'!K48 -> -4.0856751
B17: Relative Method | C17: Weight | D17: Price Target
B18: EV/Sales | C18: =RV!J5 -> 0.25 | D18: =RV!D13 -> 376.30211
B19: Price/Sales | C19: =RV!J6 -> 0.25 | D19: =RV!E13 -> 375.29697
B20: Price/Earnings | C20: =RV!J7 -> 0.25 | D20: =RV!F13 -> 959.41996
B21: Price/Book Value | C21: =RV!J8 -> 0.25 | D21: =RV!G13 -> 1105.0955

Sheet DCF Base
B2: Microsoft Corporation DCF Analysis
B4: WACC | E4: 0.1 | G4: Other Assumptions
B5: Beta | E5: =Beta!C5 -> 1.1566004 | G5: Fiscal Year End | J5: 46022
B6: Market Risk Premium | E6: 0.0433 | G6: LTGR | J6: 0.025
B7: Risk Free Rate | E7: 0.0406 | G7: Cash & Equivalents | J7: 30242
B8: Cost of Equity | E8: =E7+(E5*E6) -> 0.090680798 | G8: Shares Outstanding | J8: 7465
B9: Weight of Equity | E9: =J10/SUM(J10:J11) -> 0.98322387 | G9: Current Price | J9: 477.73
B10: Cost of Debt | E10: ='3 Statement'!O9 -> 0.05 | G10: Mkt Cap | J10: 3550971.8
B11: After Tax CoD | E11: =E10*(1-E13) -> 0.048 | G11: BV Debt | J11: 60588
B12: Weight of Debt | E12: =1-E9 -> 0.016776131 | G12: Financial Units | J12: USD in millions
B13: Tax Rate | E13: ='3 Statement'!O8 -> 0.04
B14: WACC | E14: =(E9*E8)+(E12*E10*(1-E13)) -> 0.08996478
B16: Free Cash Flow | D16: 2023 A | E16: 2024 A | F16: 2025 A | G16: 2026 E | H16: 2027 E | I16: 2028 E | J16: Year"E" | K16: Year"E"
B17: Revenue | D17: ='3 Statement'!D5 -> 211915 | E17: ='3 Statement'!E5 -> 245122 | F17: ='3 Statement'!F5 -> 281724 | G17: ='3 Statement'!G5 -> 284541.24 | H17: ='3 Statement'!H5 -> 287386.65 | I17: ='3 Statement'!I5 -> 290260.52 | J17: ='3 Statement'!J5 -> 293163.12 | K17: ='3 Statement'!K5 -> 296094.76
B18: Revenue Growth (%) | E18: =E17/D17-1 -> 0.15669962 | F18: =F17/E17-1 -> 0.14932156 | G18: =((1+'3 Statement'!O5)-1)*100 -> 1 | H18: =((1+'3 Statement'!P5)-1)*100 -> 1 | I18: =((1+'3 Statement'!Q5)-1)*100 -> 1 | J18: =((1+'3 Statement'!R5)-1)*100 -> 1 | K18: =((1+'3 Statement'!S5)-1)*100 -> 1
B19: (-) COGS | D19: ='3 Statement'!D6 -> 65863 | E19: ='3 Statement'!E6 -> 74114 | F19: ='3 Statement'!F6 -> 87831 | G19: ='3 Statement'!G6 -> 83018.485 | H19: ='3 Statement'!H6 -> 78100.937 | I19: ='3 Statement'!I6 -> 73076.736 | J19: ='3 Statement'!J6 -> 67944.241 | K19: ='3 Statement'!K6 -> 62701.788
B20: GP | D20: =D17-D19 -> 146052 | E20: =E17-E19 -> 171008 | F20: =F17-F19 -> 193893 | G20: =G17-G19 -> 201522.75 | H20: =H17-H19 -> 209285.72 | I20: =I17-I19 -> 217183.78 | J20: =J17-J19 -> 225218.88 | K20: =K17-K19 -> 233392.97
B21: GP Margin (%) | E21: =E20/D20-1 -> 0.17087065 | F21: =F20/E20-1 -> 0.13382415 | G21: ='3 Statement'!G8 -> 0.70823742 | H21: ='3 Statement'!H8 -> 0.72823742 | I21: ='3 Statement'!I8 -> 0.74823742 | J21: ='3 Statement'!J8 -> 0.76823742 | K21: ='3 Statement'!K8 -> 0.78823742
B23: (-) Op Ex | D23: =SUM('3 Statement'!D9:D11) -> 242768 | E23: =SUM('3 Statement'!E9:E11) -> 269063 | F23: =SUM('3 Statement'!F9:F11) -> 303417 | G23: =SUM('3 Statement'!G9:G11) -> 149133.53 | H23: =SUM('3 Statement'!H9:H11) -> 65680.536 | I23: =SUM('3 Statement'!I9:I11) -> 25960.519 | J23: =SUM('3 Statement'!J9:J11) -> 9217.4147 | K23: =SUM('3 Statement'!K9:K11) -> 2940.7392
B24: EBIT | D24: =D20+D23 -> 388820 | E24: =E20+E23 -> 440071 | F24: =F20+F23 -> 497310 | G24: ='3 Statement'!G12 -> 138349.52 | H24: ='3 Statement'!H12 -> 148354.61 | I24: ='3 Statement'!I12 -> 158545.97 | J24: ='3 Statement'!J12 -> 168926.33 | K24: ='3 Statement'!K12 -> 179498.43
B25: EBIT Margin (%) | D25: =D24/D17 -> 1.8347923 | E25: =E24/E17 -> 1.7953142 | F25: =F24/F17 -> 1.7652383 | G25: ='3 Statement'!G13 -> 0.48621956 | H25: ='3 Statement'!H13 -> 0.51621956 | I25: ='3 Statement'!I13 -> 0.54621956 | J25: ='3 Statement'!J13 -> 0.57621956 | K25: ='3 Statement'!K13 -> 0.60621956
B27: NOPAT | D27: =D24*(1-$E$13) -> 373267.2 | E27: =E24*(1-$E$13) -> 422468.16 | F27: =F24*(1-$E$13) -> 477417.6 | G27: =G24*(1-$E$13) -> 132815.54 | H27: =H24*(1-$E$13) -> 142420.43 | I27: =I24*(1-$E$13) -> 152204.13 | J27: =J24*(1-$E$13) -> 162169.27 | K27: =K24*(1-$E$13) -> 172318.5
B28: (+) D&A | D28: ='3 Statement'!D71 -> 13861 | E28: ='3 Statement'!E71 -> 22287 | F28: ='3 Statement'!F71 -> 34153 | G28: ='3 Statement'!G71 -> 13787.34 | H28: ='3 Statement'!H71 -> 14971.128 | I28: ='3 Statement'!I71 -> 15028.524 | J28: ='3 Statement'!J71 -> 15086.494 | K28: ='3 Statement'!K71 -> 15145.044
B29: (-) CapEx | D29: ='3 Statement'!D78 -> -28107 | E29: ='3 Statement'!E78 -> -44477 | F29: ='3 Statement'!F78 -> -64551 | G29: ='3 Statement'!G78 -> -9 | H29: ='3 Statement'!H78 -> -9 | I29: ='3 Statement'!I78 -> -9 | J29: ='3 Statement'!J78 -> -9 | K29: ='3 Statement'!K78 -> -9
B30: (-) Changes in WC | D30: ='3 Statement'!D74 -> -2388 | E30: ='3 Statement'!E74 -> 1824 | F30: ='3 Statement'!F74 -> -5350 | G30: ='3 Statement'!G74 -> -18932.527 | H30: ='3 Statement'!H74 -> -151.34527 | I30: ='3 Statement'!I74 -> -152.85872 | J30: ='3 Statement'!J74 -> -154.38731 | K30: ='3 Statement'!K74 -> -155.93118
B31: Unlevered Free Cash Flow | D31: =D27+D28+D29+D30 -> 356633.2 | E31: =E27+E28+E29+E30 -> 402102.16 | F31: =F27+F28+F29+F30 -> 441669.6 | G31: =G27+G28+G29+G30 -> 127661.35 | H31: =H27+H28+H29+H30 -> 157231.21 | I31: =I27+I28+I29+I30 -> 167070.8 | J31: =J27+J28+J29+J30 -> 177092.38 | K31: =K27+K28+K29+K30 -> 187298.61
B33: DCF | G33: 2026 E | H33: 2027 E | I33: 2028 E | J33: Year"E" | K33: Year"E"
B34: Discount Period | G34: =YEARFRAC(TODAY(),$J$5) -> 0.075 | H34: =G34+1 -> 1.075 | I34: =H34+1 -> 2.075 | J34: =I34+1 -> 3.075 | K34: =J34+1 -> 4.075
B35: Discount Factor | G35: =(1/(1+$E$14))^G34 -> 0.99355992 | H35: =(1/(1+$E$14))^H34 -> 0.91155232 | I35: =(1/(1+$E$14))^I34 -> 0.83631355 | J35: =(1/(1+$E$14))^J34 -> 0.76728493 | K35: =(1/(1+$E$14))^K34 -> 0.70395388
B37: PV of UFCF | G37: =G31*G35 -> 126839.2 | H37: =H31*H35 -> 143324.47 | I37: =I31*I35 -> 139723.57 | J37: =J31*J35 -> 135880.32 | K37: =K31*K35 -> 131849.58
B38: Total PV of UFCF | K38: =SUM(G37:K37) -> 677617.15
B40: Terminal Value | K40: =(K31*(1+J6))/(E14-J6) -> 2955156.2
B41: PV of TV | K41: =K40*K35 -> 2080293.7
B43: Enterprise Value | K43: =K41+K38 -> 2757910.8
B44: (-) Net Debt | K44: =J11-J7 -> 30346
B45: Equity Value | K45: =K41-K44 -> 2049947.7
B47: (/) Shares Outstanding | K47: =J8 -> 7465
B48: Per Share Price Target | K48: =K45/K47 -> 274.60786
B49: Implied Upside/Downside | K49: =(K48/J9-1) -> -0.42518188
B51: Sensitivity Analysis
B52: WACC Step | C52: 0.02
B53: Terminal Step | C53: 0.0025 | E53: =K48 -> 274.60786 | F53: =G53-C53 -> 0.02 | G53: =H53-C53 -> 0.0225 | H53: =J6 -> 0.025 | I53: =H53+C53 -> 0.0275 | J53: =I53+C53 -> 0.03
E54: =E55-C52 -> 0.04996478 | F54: =( $G$31/(1+$E$54)^$G$34 +$H$31/(1+$E$54)^$H$34 +$I$31/(1+$E$54)^$I$34 +$J$31/(1+$E$54)^$J$34 +$K$31/(1+$E$54)^$K$34 +(($K$31*(1+F$53))/($E54-F$53))/(1+$E54)^$K$34 -$K$44 )/$K$47 -> 794.35242 | G54: =( $G$31/(1+$E$54)^$G$34 +$H$31/(1+$E$54)^$H$34 +$I$31/(1+$E$54)^$I$34 +$J$31/(1+$E$54)^$J$34 +$K$31/(1+$E$54)^$K$34 +(($K$31*(1+G$53))/($E54-G$53))/(1+$E54)^$K$34 -$K$44 )/$K$47 -> 859.95867 | H54: =( $G$31/(1+$E$54)^$G$34 +$H$31/(1+$E$54)^$H$34 +$I$31/(1+$E$54)^$I$34 +$J$31/(1+$E$54)^$J$34 +$K$31/(1+$E$54)^$K$34 +(($K$31*(1+H$53))/($E54-H$53))/(1+$E54)^$K$34 -$K$44 )/$K$47 -> 938.70469 | I54: =( $G$31/(1+$E$54)^$G$34 +$H$31/(1+$E$54)^$H$34 +$I$31/(1+$E$54)^$I$34 +$J$31/(1+$E$54)^$J$34 +$K$31/(1+$E$54)^$K$34 +(($K$31*(1+I$53))/($E54-I$53))/(1+$E54)^$K$34 -$K$44 )/$K$47 -> 1034.9773 | J54: =( $G$31/(1+$E$54)^$G$34 +$H$31/(1+$E$54)^$H$34 +$I$31/(1+$E$54)^$I$34 +$J$31/(1+$E$54)^$J$34 +$K$31/(1+$E$54)^$K$34 +(($K$31*(1+J$53))/($E54-J$53))/(1+$E54)^$K$34 -$K$44 )/$K$47 -> 1155.3604
E55: =E56-C52 -> 0.06996478 | F55: =( $G$31/(1+$E$55)^$G$34 +$H$31/(1+$E$55)^$H$34 +$I$31/(1+$E$55)^$I$34 +$J$31/(1+$E$55)^$J$34 +$K$31/(1+$E$55)^$K$34 +(($K$31*(1+F$53))/($E55-F$53))/(1+$E$55)^$K$34 -$K$44 )/$K$47 -> 479.13207 | G55: =( $G$31/(1+$E$55)^$G$34 +$H$31/(1+$E$55)^$H$34 +$I$31/(1+$E$55)^$I$34 +$J$31/(1+$E$55)^$J$34 +$K$31/(1+$E$55)^$K$34 +(($K$31*(1+G$53))/($E55-G$53))/(1+$E$55)^$K$34 -$K$44 )/$K$47 -> 500.61523 | H55: =( $G$31/(1+$E$55)^$G$34 +$H$31/(1+$E$55)^$H$34 +$I$31/(1+$E$55)^$I$34 +$J$31/(1+$E$55)^$J$34 +$K$31/(1+$E$55)^$K$34 +(($K$31*(1+H$53))/($E55-H$53))/(1+$E$55)^$K$34 -$K$44 )/$K$47 -> 524.48727 | I55: =( $G$31/(1+$E$55)^$G$34 +$H$31/(1+$E$55)^$H$34 +$I$31/(1+$E$55)^$I$34 +$J$31/(1+$E$55)^$J$34 +$K$31/(1+$E$55)^$K$34 +(($K$31*(1+I$53))/($E55-I$53))/(1+$E$55)^$K$34 -$K$44 )/$K$47 -> 551.17012 | J55: =( $G$31/(1+$E$55)^$G$34 +$H$31/(1+$E$55)^$H$34 +$I$31/(1+$E$55)^$I$34 +$J$31/(1+$E$55)^$J$34 +$K$31/(1+$E$55)^$K$34 +(($K$31*(1+J$53))/($E55-J$53))/(1+$E$55)^$K$34 -$K$44 )/$K$47 -> 581.19127
E56: =E14 -> 0.08996478 | F56: =( $G$31/(1+$E$56)^$G$34 +$H$31/(1+$E$56)^$H$34 +$I$31/(1+$E$56)^$I$34 +$J$31/(1+$E$56)^$J$34 +$K$31/(1+$E$56)^$K$34 +(($K$31*(1+F$53))/($E$56-F$53))/(1+$E$56)^$K$34 -$K$44 )/$K$47 -> 344.20296 | G56: =( $G$31/(1+$E$56)^$G$34 +$H$31/(1+$E$56)^$H$34 +$I$31/(1+$E$56)^$I$34 +$J$31/(1+$E$56)^$J$34 +$K$31/(1+$E$56)^$K$34 +(($K$31*(1+G$53))/($E$56-G$53))/(1+$E$56)^$K$34 -$K$44 )/$K$47 -> 354.39931 | H56: =( $G$31/(1+$E$56)^$G$34 +$H$31/(1+$E$56)^$H$34 +$I$31/(1+$E$56)^$I$34 +$J$31/(1+$E$56)^$J$34 +$K$31/(1+$E$56)^$K$34 +(($K$31*(1+H$53))/($E$56-H$53))/(1+$E$56)^$K$34 -$K$44 )/$K$47 -> 365.38042 | I56: =( $G$31/(1+$E$56)^$G$34 +$H$31/(1+$E$56)^$H$34 +$I$31/(1+$E$56)^$I$34 +$J$31/(1+$E$56)^$J$34 +$K$31/(1+$E$56)^$K$34 +(($K$31*(1+I$53))/($E$56-I$53))/(1+$E$56)^$K$34 -$K$44 )/$K$47 -> 377.24052 | J56: =( $G$31/(1+$E$56)^$G$34 +$H$31/(1+$E$56)^$H$34 +$I$31/(1+$E$56)^$I$34 +$J$31/(1+$E$56)^$J$34 +$K$31/(1+$E$56)^$K$34 +(($K$31*(1+J$53))/($E$56-J$53))/(1+$E$56)^$K$34 -$K$44 )/$K$47 -> 390.08954
E57: =E56+C52 -> 0.10996478 | F57: =( $G$31/(1+$E$57)^$G$34 +$H$31/(1+$E$57)^$H$34 +$I$31/(1+$E$57)^$I$34 +$J$31/(1+$E$57)^$J$34 +$K$31/(1+$E$57)^$K$34 +(($K$31*(1+F$53))/($E$57-F$53))/(1+$E$57)^$K$34 -$K$44 )/$K$47 -> 269.31895 | G57: =( $G$31/(1+$E$57)^$G$34 +$H$31/(1+$E$57)^$H$34 +$I$31/(1+$E$57)^$I$34 +$J$31/(1+$E$57)^$J$34 +$K$31/(1+$E$57)^$K$34 +(($K$31*(1+G$53))/($E$57-G$53))/(1+$E$57)^$K$34 -$K$44 )/$K$47 -> 275.10275 | H57: =( $G$31/(1+$E$57)^$G$34 +$H$31/(1+$E$57)^$H$34 +$I$31/(1+$E$57)^$I$34 +$J$31/(1+$E$57)^$J$34 +$K$31/(1+$E$57)^$K$34 +(($K$31*(1+H$53))/($E$57-H$53))/(1+$E$57)^$K$34 -$K$44 )/$K$47 -> 281.22691 | I57: =( $G$31/(1+$E$57)^$G$34 +$H$31/(1+$E$57)^$H$34 +$I$31/(1+$E$57)^$I$34 +$J$31/(1+$E$57)^$J$34 +$K$31/(1+$E$57)^$K$34 +(($K$31*(1+I$53))/($E$57-I$53))/(1+$E$57)^$K$34 -$K$44 )/$K$47 -> 287.7224 | J57: =( $G$31/(1+$E$57)^$G$34 +$H$31/(1+$E$57)^$H$34 +$I$31/(1+$E$57)^$I$34 +$J$31/(1+$E$57)^$J$34 +$K$31/(1+$E$57)^$K$34 +(($K$31*(1+J$53))/($E$57-J$53))/(1+$E$57)^$K$34 -$K$44 )/$K$47 -> 294.62403
E58: =E57+C52 -> 0.12996478 | F58: =( $G$31/(1+$E$58)^$G$34 +$H$31/(1+$E$58)^$H$34 +$I$31/(1+$E$58)^$I$34 +$J$31/(1+$E$58)^$J$34 +$K$31/(1+$E$58)^$K$34 +(($K$31*(1+F$53))/($E$58-F$53))/(1+$E$58)^$K$34 -$K$44 )/$K$47 -> 221.71406 | G58: =( $G$31/(1+$E$58)^$G$34 +$H$31/(1+$E$58)^$H$34 +$I$31/(1+$E$58)^$I$34 +$J$31/(1+$E$58)^$J$34 +$K$31/(1+$E$58)^$K$34 +(($K$31*(1+G$53))/($E$58-G$53))/(1+$E$58)^$K$34 -$K$44 )/$K$47 -> 225.35951 | H58: =( $G$31/(1+$E$58)^$G$34 +$H$31/(1+$E$58)^$H$34 +$I$31/(1+$E$58)^$I$34 +$J$31/(1+$E$58)^$J$34 +$K$31/(1+$E$58)^$K$34 +(($K$31*(1+H$53))/($E$58-H$53))/(1+$E$58)^$K$34 -$K$44 )/$K$47 -> 229.1786 | I58: =( $G$31/(1+$E$58)^$G$34 +$H$31/(1+$E$58)^$H$34 +$I$31/(1+$E$58)^$I$34 +$J$31/(1+$E$58)^$J$34 +$K$31/(1+$E$58)^$K$34 +(($K$31*(1+I$53))/($E$58-I$53))/(1+$E$58)^$K$34 -$K$44 )/$K$47 -> 233.18406 | J58: =( $G$31/(1+$E$58)^$G$34 +$H$31/(1+$E$58)^$H$34 +$I$31/(1+$E$58)^$I$34 +$J$31/(1+$E$58)^$J$34 +$K$31/(1+$E$58)^$K$34 +(($K$31*(1+J$53))/($E$58-J$53))/(1+$E$58)^$K$34 -$K$44 )/$K$47 -> 237.38985

Sheet DCF Bear
B2: Microsoft Corporation DCF Analysis
B4: WACC | E4: 0.1 | G4: Other Assumptions
B5: Beta | E5: 1.2 | G5: Fiscal Year End | J5: 46022
B6: Market Risk Premium | E6: 0.0433 | G6: LTGR | J6: 0.025
B7: Risk Free Rate | E7: 0.0406 | G7: Cash & Equivalents | J7: ='DCF Base'!J7 -> 30242
B8: Cost of Equity | E8: =E7+(E5*E6) -> 0.09256 | G8: Diluted S/O | J8: ='DCF Base'!J8 -> 7465
B9: Weight of Equity | E9: =J10/SUM(J10:J11) -> 0.98329456 | G9: Current Price | J9: ='DCF Base'!J9 -> 477.73
B10: Cost of Debt | E10: ='3 Statement'!O9 -> 0.05 | G10: Mkt Cap | J10: =J8*J9 -> 3566254.5
B11: After Tax CoD | E11: =E10*(1-E13) -> 0.048 | G11: BV Debt | J11: ='DCF Base'!J11 -> 60588
B12: Weight of Debt | E12: =1-E9 -> 0.01670544 | G12: Financial Units | J12: USD in millions
B13: Tax Rate | E13: ='3 Statement'!O8 -> 0.04
B14: WACC | E14: =(E9*E8)+(E12*E10*(1-E13)) -> 0.091815606
B16: Free Cash Flow | D16: 2023 A | E16: 2024 A | F16: 2025 A | G16: 2026 E | H16: 2027 E | I16: 2028 E | J16: Year"E" | K16: Year"E"
B17: Revenue | D17: ='3 Statement'!D5 -> 211915 | E17: ='3 Statement'!E5 -> 245122 | F17: ='3 Statement'!F5 -> 281724 | G17: =F17*G18 -> 33806.88 | H17: =G17*H18 -> 4056.8256 | I17: =H17*I18 -> 486.81907 | J17: =I17*J18 -> 58.418289 | K17: =J17*K18 -> 7.0101946
B18: Revenue Growth (%) | E18: =E17/D17-1 -> 0.15669962 | F18: =F17/E17-1 -> 0.14932156 | G18: =0.12 -> 0.12 | H18: =0.12 -> 0.12 | I18: =0.12 -> 0.12 | J18: =0.12 -> 0.12 | K18: =0.12 -> 0.12
B19: (-) COGS | D19: ='3 Statement'!D6 -> 65863 | E19: ='3 Statement'!E6 -> 74114 | F19: ='3 Statement'!F6 -> 87831 | G19: =G17*G21 -> 4394.8944 | H19: =H17*H21 -> 527.38733 | I19: =I17*I21 -> 63.286479 | J19: =J17*J21 -> 7.5943775 | K19: =K17*K21 -> 0.9113253
B20: GP | D20: =D17-D19 -> 146052 | E20: =E17-E19 -> 171008 | F20: =F17-F19 -> 193893 | G20: =G17-G19 -> 29411.986 | H20: =H17-H19 -> 3529.4383 | I20: =I17-I19 -> 423.53259 | J20: =J17-J19 -> 50.823911 | K20: =K17-K19 -> 6.0988693
B21: GP Margin (%) | E21: =E20/D20-1 -> 0.17087065 | F21: =F20/E20-1 -> 0.13382415 | G21: =0.13 -> 0.13 | H21: =0.13 -> 0.13 | I21: =0.13 -> 0.13 | J21: =0.13 -> 0.13 | K21: =0.13 -> 0.13
B23: (-) Op Ex | D23: =SUM('3 Statement'!D9:D11) -> 242768 | E23: =SUM('3 Statement'!E9:E11) -> 269063 | F23: =SUM('3 Statement'!F9:F11) -> 303417 | G23: =G17*G25 -> 4732.9632 | H23: =H17*H25 -> 567.95558 | I23: =I17*I25 -> 68.15467 | J23: =J17*J25 -> 8.1785604 | K23: =K17*K25 -> 0.98142725
B24: EBIT | D24: =D20+D23 -> 388820 | E24: =E20+E23 -> 440071 | F24: =F20+F23 -> 497310 | G24: =G21-G23 -> -4732.8332 | H24: =H21-H23 -> -567.82558 | I24: =I21-I23 -> -68.02467 | J24: =J21-J23 -> -8.0485604 | K24: =K21-K23 -> -0.85142725
B25: EBIT Margin (%) | D25: =D24/D17 -> 1.8347923 | E25: =E24/E17 -> 1.7953142 | F25: =F24/F17 -> 1.7652383 | G25: =0.14 -> 0.14 | H25: =0.14 -> 0.14 | I25: =0.14 -> 0.14 | J25: =0.14 -> 0.14 | K25: =0.14 -> 0.14
B27: NOPAT | D27: =D24*(1-$E$13) -> 373267.2 | E27: =E24*(1-$E$13) -> 422468.16 | F27: =F24*(1-$E$13) -> 477417.6 | G27: =G24*(1-$E$13) -> -4543.5199 | H27: =H24*(1-$E$13) -> -545.11256 | I27: =I24*(1-$E$13) -> -65.303683 | J27: =J24*(1-$E$13) -> -7.726618 | K27: =K24*(1-$E$13) -> -0.81737016
B28: (+) D&A | D28: ='3 Statement'!D71 -> 13861 | E28: ='3 Statement'!E71 -> 22287 | F28: ='3 Statement'!F71 -> 34153 | G28: =0.16*G17 -> 5409.1008 | H28: =0.16*H17 -> 649.0921 | I28: =0.16*I17 -> 77.891052 | J28: =0.16*J17 -> 9.3469262 | K28: =0.16*K17 -> 1.1216311
B29: (-) CapEx | D29: ='3 Statement'!D78 -> -28107 | E29: ='3 Statement'!E78 -> -44477 | F29: ='3 Statement'!F78 -> -64551 | G29: =-0.17*G17 -> -5747.1696 | H29: =-0.17*H17 -> -689.66035 | I29: =-0.17*I17 -> -82.759242 | J29: =-0.17*J17 -> -9.9311091 | K29: =-0.17*K17 -> -1.1917331
B30: (-) Changes in WC | D30: ='3 Statement'!D74 -> -2388 | E30: ='3 Statement'!E74 -> 1824 | F30: ='3 Statement'!F74 -> -5350 | G30: =0.18 -> 0.18 | H30: =0.18 -> 0.18 | I30: =0.18 -> 0.18 | J30: =0.18 -> 0.18 | K30: =0.18 -> 0.18
B31: Unlevered Free Cash Flow | D31: =D27+D28+D29+D30 -> 356633.2 | E31: =E27+E28+E29+E30 -> 402102.16 | F31: =F27+F28+F29+F30 -> 441669.6 | G31: =G27+G28+G29+G30 -> -4881.4087 | H31: =H27+H28+H29+H30 -> -585.50082 | I31: =I27+I28+I29+I30 -> -69.991874 | J31: =J27+J28+J29+J30 -> -8.1308009 | K31: =K27+K28+K29+K30 -> -0.70747211
B33: DCF | G33: 2026 E | H33: 2027 E | I33: 2028 E | J33: Year"E" | K33: Year"E"
B34: Discount Period | G34: =YEARFRAC(TODAY(),$J$5) -> 0.075 | H34: =G34+1 -> 1.075 | I34: =H34+1 -> 2.075 | J34: =I34+1 -> 3.075 | K34: =J34+1 -> 4.075
B35: Discount Factor | G35: =(1/(1+$E$14))^G34 -> 0.9934335 | H35: =(1/(1+$E$14))^H34 -> 0.90989128 | I35: =(1/(1+$E$14))^I34 -> 0.8333745 | J35: =(1/(1+$E$14))^J34 -> 0.76329235 | K35: =(1/(1+$E$14))^K34 -> 0.69910372
B37: PV of UFCF | G37: =G31*G35 -> -4849.3549 | H37: =H31*H35 -> -532.74209 | I37: =I31*I35 -> -58.329443 | J37: =J31*J35 -> -6.2061781 | K37: =K31*K35 -> -0.49459638
B38: Total PV of UFCF | K38: =SUM(G37:K37) -> -5447.1272
B40: Terminal Value | K40: =(K31*(1+J6))/(E14-J6) -> -10.853137
B41: PV of TV | K41: =K40*K35 -> -7.5874683
B43: Enterprise Value | K43: =K41+K38 -> -5454.7147
B44: (-) Net Debt | K44: =J11-J7 -> 30346
B45: Equity Value | K45: =K41-K44 -> -30353.587
B47: (/) Shares Outstanding | K47: =J8 -> 7465
B48: Per Share Price Target | K48: =K45/K47 -> -4.0661202
B49: Implied Upside/Downside | K49: =(K48/J9-1) -> -1.0085113
B51: Sensitivity Analysis
B52: WACC Step | C52: 0.02
B53: Terminal Step | C53: 0.0025 | E53: =K48 -> -4.0661202 | F53: =G53-C53 -> 0.02 | G53: =H53-C53 -> 0.0225 | H53: =J6 -> 0.025 | I53: =H53+C53 -> 0.0275 | J53: =I53+C53 -> 0.03
E54: =E55-C52 -> 0.051815606 | F54: =( $G$31/(1+$E$54)^$G$34 +$H$31/(1+$E$54)^$H$34 +$I$31/(1+$E$54)^$I$34 +$J$31/(1+$E$54)^$J$34 +$K$31/(1+$E$54)^$K$34 +(($K$31*(1+F$53))/($E54-F$53))/(1+$E54)^$K$34 -$K$44 )/$K$47 -> -4.8027496 | G54: =( $G$31/(1+$E$54)^$G$34 +$H$31/(1+$E$54)^$H$34 +$I$31/(1+$E$54)^$I$34 +$J$31/(1+$E$54)^$J$34 +$K$31/(1+$E$54)^$K$34 +(($K$31*(1+G$53))/($E54-G$53))/(1+$E54)^$K$34 -$K$44 )/$K$47 -> -4.8029671 | H54: =( $G$31/(1+$E$54)^$G$34 +$H$31/(1+$E$54)^$H$34 +$I$31/(1+$E$54)^$I$34 +$J$31/(1+$E$54)^$J$34 +$K$31/(1+$E$54)^$K$34 +(($K$31*(1+H$53))/($E54-H$53))/(1+$E54)^$K$34 -$K$44 )/$K$47 -> -4.8032251 | I54: =( $G$31/(1+$E$54)^$G$34 +$H$31/(1+$E$54)^$H$34 +$I$31/(1+$E$54)^$I$34 +$J$31/(1+$E$54)^$J$34 +$K$31/(1+$E$54)^$K$34 +(($K$31*(1+I$53))/($E54-I$53))/(1+$E54)^$K$34 -$K$44 )/$K$47 -> -4.8035362 | J54: =( $G$31/(1+$E$54)^$G$34 +$H$31/(1+$E$54)^$H$34 +$I$31/(1+$E$54)^$I$34 +$J$31/(1+$E$54)^$J$34 +$K$31/(1+$E$54)^$K$34 +(($K$31*(1+J$53))/($E54-J$53))/(1+$E54)^$K$34 -$K$44 )/$K$47 -> -4.8039186
E55: =E56-C52 -> 0.071815606 | F55: =( $G$31/(1+$E$55)^$G$34 +$H$31/(1+$E$55)^$H$34 +$I$31/(1+$E$55)^$I$34 +$J$31/(1+$E$55)^$J$34 +$K$31/(1+$E$55)^$K$34 +(($K$31*(1+F$53))/($E55-F$53))/(1+$E$55)^$K$34 -$K$44 )/$K$47 -> -4.7988923 | G55: =( $G$31/(1+$E$55)^$G$34 +$H$31/(1+$E$55)^$H$34 +$I$31/(1+$E$55)^$I$34 +$J$31/(1+$E$55)^$J$34 +$K$31/(1+$E$55)^$K$34 +(($K$31*(1+G$53))/($E55-G$53))/(1+$E$55)^$K$34 -$K$44 )/$K$47 -> -4.7989672 | H55: =( $G$31/(1+$E$55)^$G$34 +$H$31/(1+$E$55)^$H$34 +$I$31/(1+$E$55)^$I$34 +$J$31/(1+$E$55)^$J$34 +$K$31/(1+$E$55)^$K$34 +(($K$31*(1+H$53))/($E55-H$53))/(1+$E$55)^$K$34 -$K$44 )/$K$47 -> -4.7990501 | I55: =( $G$31/(1+$E$55)^$G$34 +$H$31/(1+$E$55)^$H$34 +$I$31/(1+$E$55)^$I$34 +$J$31/(1+$E$55)^$J$34 +$K$31/(1+$E$55)^$K$34 +(($K$31*(1+I$53))/($E55-I$53))/(1+$E$55)^$K$34 -$K$44 )/$K$47 -> -4.7991424 | J55: =( $G$31/(1+$E$55)^$G$34 +$H$31/(1+$E$55)^$H$34 +$I$31/(1+$E$55)^$I$34 +$J$31/(1+$E$55)^$J$34 +$K$31/(1+$E$55)^$K$34 +(($K$31*(1+J$53))/($E55-J$53))/(1+$E$55)^$K$34 -$K$44 )/$K$47 -> -4.7992457
E56: =E14 -> 0.091815606 | F56: =( $G$31/(1+$E$56)^$G$34 +$H$31/(1+$E$56)^$H$34 +$I$31/(1+$E$56)^$I$34 +$J$31/(1+$E$56)^$J$34 +$K$31/(1+$E$56)^$K$34 +(($K$31*(1+F$53))/($E$56-F$53))/(1+$E$56)^$K$34 -$K$44 )/$K$47 -> -4.7957337 | G56: =( $G$31/(1+$E$56)^$G$34 +$H$31/(1+$E$56)^$H$34 +$I$31/(1+$E$56)^$I$34 +$J$31/(1+$E$56)^$J$34 +$K$31/(1+$E$56)^$K$34 +(($K$31*(1+G$53))/($E$56-G$53))/(1+$E$56)^$K$34 -$K$44 )/$K$47 -> -4.79577 | H56: =( $G$31/(1+$E$56)^$G$34 +$H$31/(1+$E$56)^$H$34 +$I$31/(1+$E$56)^$I$34 +$J$31/(1+$E$56)^$J$34 +$K$31/(1+$E$56)^$K$34 +(($K$31*(1+H$53))/($E$56-H$53))/(1+$E$56)^$K$34 -$K$44 )/$K$47 -> -4.7958091 | I56: =( $G$31/(1+$E$56)^$G$34 +$H$31/(1+$E$56)^$H$34 +$I$31/(1+$E$56)^$I$34 +$J$31/(1+$E$56)^$J$34 +$K$31/(1+$E$56)^$K$34 +(($K$31*(1+I$53))/($E$56-I$53))/(1+$E$56)^$K$34 -$K$44 )/$K$47 -> -4.7958512 | J56: =( $G$31/(1+$E$56)^$G$34 +$H$31/(1+$E$56)^$H$34 +$I$31/(1+$E$56)^$I$34 +$J$31/(1+$E$56)^$J$34 +$K$31/(1+$E$56)^$K$34 +(($K$31*(1+J$53))/($E$56-J$53))/(1+$E$56)^$K$34 -$K$44 )/$K$47 -> -4.7958966
E57: =E56+C52 -> 0.11181561 | F57: =( $G$31/(1+$E$57)^$G$34 +$H$31/(1+$E$57)^$H$34 +$I$31/(1+$E$57)^$I$34 +$J$31/(1+$E$57)^$J$34 +$K$31/(1+$E$57)^$K$34 +(($K$31*(1+F$53))/($E$57-F$53))/(1+$E$57)^$K$34 -$K$44 )/$K$47 -> -4.7928746 | G57: =( $G$31/(1+$E$57)^$G$34 +$H$31/(1+$E$57)^$H$34 +$I$31/(1+$E$57)^$I$34 +$J$31/(1+$E$57)^$J$34 +$K$31/(1+$E$57)^$K$34 +(($K$31*(1+G$53))/($E$57-G$53))/(1+$E$57)^$K$34 -$K$44 )/$K$47 -> -4.7928955 | H57: =( $G$31/(1+$E$57)^$G$34 +$H$31/(1+$E$57)^$H$34 +$I$31/(1+$E$57)^$I$34 +$J$31/(1+$E$57)^$J$34 +$K$31/(1+$E$57)^$K$34 +(($K$31*(1+H$53))/($E$57-H$53))/(1+$E$57)^$K$34 -$K$44 )/$K$47 -> -4.7929175 | I57: =( $G$31/(1+$E$57)^$G$34 +$H$31/(1+$E$57)^$H$34 +$I$31/(1+$E$57)^$I$34 +$J$31/(1+$E$57)^$J$34 +$K$31/(1+$E$57)^$K$34 +(($K$31*(1+I$53))/($E$57-I$53))/(1+$E$57)^$K$34 -$K$44 )/$K$47 -> -4.7929409 | J57: =( $G$31/(1+$E$57)^$G$34 +$H$31/(1+$E$57)^$H$34 +$I$31/(1+$E$57)^$I$34 +$J$31/(1+$E$57)^$J$34 +$K$31/(1+$E$57)^$K$34 +(($K$31*(1+J$53))/($E$57-J$53))/(1+$E$57)^$K$34 -$K$44 )/$K$47 -> -4.7929657
E58: =E57+C52 -> 0.13181561 | F58: =( $G$31/(1+$E$58)^$G$34 +$H$31/(1+$E$58)^$H$34 +$I$31/(1+$E$58)^$I$34 +$J$31/(1+$E$58)^$J$34 +$K$31/(1+$E$58)^$K$34 +(($K$31*(1+F$53))/($E$58-F$53))/(1+$E$58)^$K$34 -$K$44 )/$K$47 -> -4.790198 | G58: =( $G$31/(1+$E$58)^$G$34 +$H$31/(1+$E$58)^$H$34 +$I$31/(1+$E$58)^$I$34 +$J$31/(1+$E$58)^$J$34 +$K$31/(1+$E$58)^$K$34 +(($K$31*(1+G$53))/($E$58-G$53))/(1+$E$58)^$K$34 -$K$44 )/$K$47 -> -4.7902113 | H58: =( $G$31/(1+$E$58)^$G$34 +$H$31/(1+$E$58)^$H$34 +$I$31/(1+$E$58)^$I$34 +$J$31/(1+$E$58)^$J$34 +$K$31/(1+$E$58)^$K$34 +(($K$31*(1+H$53))/($E$58-H$53))/(1+$E$58)^$K$34 -$K$44 )/$K$47 -> -4.7902251 | I58: =( $G$31/(1+$E$58)^$G$34 +$H$31/(1+$E$58)^$H$34 +$I$31/(1+$E$58)^$I$34 +$J$31/(1+$E$58)^$J$34 +$K$31/(1+$E$58)^$K$34 +(($K$31*(1+I$53))/($E$58-I$53))/(1+$E$58)^$K$34 -$K$44 )/$K$47 -> -4.7902397 | J58: =( $G$31/(1+$E$58)^$G$34 +$H$31/(1+$E$58)^$H$34 +$I$31/(1+$E$58)^$I$34 +$J$31/(1+$E$58)^$J$34 +$K$31/(1+$E$58)^$K$34 +(($K$31*(1+J$53))/($E$58-J$53))/(1+$E$58)^$K$34 -$K$44 )/$K$47 -> -4.7902549

Sheet DCF Bull
B2: Microsoft Corporation DCF Analysis
B4: WACC | E4: 0.1 | G4: Other Assumptions
B5: Beta | E5: 1.2 | G5: Fiscal Year End | J5: 46022
B6: Market Risk Premium | E6: 0.0433 | G6: LTGR | J6: 0.025
B7: Risk Free Rate | E7: 0.0406 | G7: Cash & Equivalents | J7: ='DCF Base'!J7 -> 30242
B8: Cost of Equity | E8: =E7+(E5*E6) -> 0.09256 | G8: Diluted S/O | J8: ='DCF Base'!J8 -> 7465
B9: Weight of Equity | E9: =J10/SUM(J10:J11) -> 0.98329456 | G9: Current Price | J9: ='DCF Base'!J9 -> 477.73
B10: Cost of Debt | E10: ='3 Statement'!O9 -> 0.05 | G10: Mkt Cap | J10: =J8*J9 -> 3566254.5
B11: After Tax CoD | E11: =E10*(1-E13) -> 0.048 | G11: BV Debt | J11: ='DCF Base'!J11 -> 60588
B12: Weight of Debt | E12: =1-E9 -> 0.01670544 | G12: Financial Units | J12: USD in millions
B13: Tax Rate | E13: ='3 Statement'!O8 -> 0.04
B14: WACC | E14: =(E9*E8)+(E12*E10*(1-E13)) -> 0.091815606
B16: Free Cash Flow | D16: 2023 A | E16: 2024 A | F16: 2025 A | G16: 2026 E | H16: 2027 E | I16: 2028 E | J16: Year"E" | K16: Year"E"
B17: Revenue | D17: ='3 Statement'!D5 -> 211915 | E17: ='3 Statement'!E5 -> 245122 | F17: ='3 Statement'!F5 -> 281724 | G17: =F17*G18 -> 53527.56 | H17: =G17*H18 -> 10170.236 | I17: =H17*I18 -> 1932.3449 | J17: =I17*J18 -> 367.14553 | K17: =J17*K18 -> 69.757651
B18: Revenue Growth (%) | E18: =E17/D17-1 -> 0.15669962 | F18: =F17/E17-1 -> 0.14932156 | G18: =0.19 -> 0.19 | H18: =0.19 -> 0.19 | I18: =0.19 -> 0.19 | J18: =0.19 -> 0.19 | K18: =0.19 -> 0.19
B19: (-) COGS | D19: ='3 Statement'!D6 -> 65863 | E19: ='3 Statement'!E6 -> 74114 | F19: ='3 Statement'!F6 -> 87831 | G19: =G17*G21 -> 10705.512 | H19: =H17*H21 -> 2034.0473 | I19: =I17*I21 -> 386.46898 | J19: =J17*J21 -> 73.429107 | K19: =K17*K21 -> 13.95153
B20: GP | D20: =D17-D19 -> 146052 | E20: =E17-E19 -> 171008 | F20: =F17-F19 -> 193893 | G20: =G17-G19 -> 42822.048 | H20: =H17-H19 -> 8136.1891 | I20: =I17-I19 -> 1545.8759 | J20: =J17-J19 -> 293.71643 | K20: =K17-K19 -> 55.806121
B21: GP Margin (%) | E21: =E20/D20-1 -> 0.17087065 | F21: =F20/E20-1 -> 0.13382415 | G21: =0.2 -> 0.2 | H21: =0.2 -> 0.2 | I21: =0.2 -> 0.2 | J21: =0.2 -> 0.2 | K21: =0.2 -> 0.2
B23: (-) Op Ex | D23: =SUM('3 Statement'!D9:D11) -> 242768 | E23: =SUM('3 Statement'!E9:E11) -> 269063 | F23: =SUM('3 Statement'!F9:F11) -> 303417 | G23: =G17*G25 -> 11240.788 | H23: =H17*H25 -> 2135.7496 | I23: =I17*I25 -> 405.79243 | J23: =J17*J25 -> 77.100562 | K23: =K17*K25 -> 14.649107
B24: EBIT | D24: =D20+D23 -> 388820 | E24: =E20+E23 -> 440071 | F24: =F20+F23 -> 497310 | G24: =G21-G23 -> -11240.588 | H24: =H21-H23 -> -2135.5496 | I24: =I21-I23 -> -405.59243 | J24: =J21-J23 -> -76.900562 | K24: =K21-K23 -> -14.449107
B25: EBIT Margin (%) | D25: =D24/D17 -> 1.8347923 | E25: =E24/E17 -> 1.7953142 | F25: =F24/F17 -> 1.7652383 | G25: =0.21 -> 0.21 | H25: =0.21 -> 0.21 | I25: =0.21 -> 0.21 | J25: =0.21 -> 0.21 | K25: =0.21 -> 0.21
B27: NOPAT | D27: =D24*(1-$E$13) -> 373267.2 | E27: =E24*(1-$E$13) -> 422468.16 | F27: =F24*(1-$E$13) -> 477417.6 | G27: =G24*(1-$E$13) -> -10790.964 | H27: =H24*(1-$E$13) -> -2050.1277 | I27: =I24*(1-$E$13) -> -389.36874 | J27: =J24*(1-$E$13) -> -73.82454 | K27: =K24*(1-$E$13) -> -13.871143
B28: (+) D&A | D28: ='3 Statement'!D71 -> 13861 | E28: ='3 Statement'!E71 -> 22287 | F28: ='3 Statement'!F71 -> 34153 | G28: =0.23*G17 -> 12311.339 | H28: =0.23*H17 -> 2339.1544 | I28: =0.23*I17 -> 444.43933 | J28: =0.23*J17 -> 84.443473 | K28: =0.23*K17 -> 16.04426 | M28: *
B29: (-) CapEx | D29: ='3 Statement'!D78 -> -28107 | E29: ='3 Statement'!E78 -> -44477 | F29: ='3 Statement'!F78 -> -64551 | G29: =-0.24*G17 -> -12846.614 | H29: =-0.24*H17 -> -2440.8567 | I29: =-0.24*I17 -> -463.76278 | J29: =-0.24*J17 -> -88.114928 | K29: =-0.24*K17 -> -16.741836
B30: (-) Changes in WC | D30: ='3 Statement'!D74 -> -2388 | E30: ='3 Statement'!E74 -> 1824 | F30: ='3 Statement'!F74 -> -5350 | G30: =0.25 -> 0.25 | H30: =0.25 -> 0.25 | I30: =0.25 -> 0.25 | J30: =0.25 -> 0.25 | K30: =0.25 -> 0.25
B31: Unlevered Free Cash Flow | D31: =D27+D28+D29+D30 -> 356633.2 | E31: =E27+E28+E29+E30 -> 402102.16 | F31: =F27+F28+F29+F30 -> 441669.6 | G31: =G27+G28+G29+G30 -> -11325.99 | H31: =H27+H28+H29+H30 -> -2151.58 | I31: =I27+I28+I29+I30 -> -408.44218 | J31: =J27+J28+J29+J30 -> -77.245995 | K31: =K27+K28+K29+K30 -> -14.318719
B33: DCF | G33: 2026 E | H33: 2027 E | I33: 2028 E | J33: Year"E" | K33: Year"E"
B34: Discount Period | G34: =YEARFRAC(TODAY(),$J$5) -> 0.075 | H34: =G34+1 -> 1.075 | I34: =H34+1 -> 2.075 | J34: =I34+1 -> 3.075 | K34: =J34+1 -> 4.075
B35: Discount Factor | G35: =(1/(1+$E$14))^G34 -> 0.9934335 | H35: =(1/(1+$E$14))^H34 -> 0.90989128 | I35: =(1/(1+$E$14))^I34 -> 0.8333745 | J35: =(1/(1+$E$14))^J34 -> 0.76329235 | K35: =(1/(1+$E$14))^K34 -> 0.69910372
B37: PV of UFCF | G37: =G31*G35 -> -11251.618 | H37: =H31*H35 -> -1957.7039 | I37: =I31*I35 -> -340.3853 | J37: =J31*J35 -> -58.961277 | K37: =K31*K35 -> -10.01027
B38: Total PV of UFCF | K38: =SUM(G37:K37) -> -13618.678
B40: Terminal Value | K40: =(K31*(1+J6))/(E14-J6) -> -219.65957
B41: PV of TV | K41: =K40*K35 -> -153.56482
B43: Enterprise Value | K43: =K41+K38 -> -13772.243
B44: (-) Net Debt | K44: =J11-J7 -> 30346
B45: Equity Value | K45: =K41-K44 -> -30499.565
B47: (/) Shares Outstanding | K47: =J8 -> 7465
B48: Per Share Price Target | K48: =K45/K47 -> -4.0856751
B49: Implied Upside/Downside | K49: =(K48/J9-1) -> -1.0085523
B51: Sensitivity Analysis
B52: WACC Step | C52: #
B53: Terminal Step | C53: # | E53: =K48 -> -4.0856751 | F53: =G53-C53 -> #VALUE! | G53: =H53-C53 -> #VALUE! | H53: =J6 -> 0.025 | I53: =H53+C53 -> #VALUE! | J53: =I53+C53 -> #VALUE!
E54: =E55-C52 -> #VALUE! | F54: =( $G$31/(1+$E$54)^$G$34 +$H$31/(1+$E$54)^$H$34 +$I$31/(1+$E$54)^$I$34 +$J$31/(1+$E$54)^$J$34 +$K$31/(1+$E$54)^$K$34 +(($K$31*(1+F$53))/($E54-F$53))/(1+$E54)^$K$34 -$K$44 )/$K$47 -> #VALUE! | G54: =( $G$31/(1+$E$54)^$G$34 +$H$31/(1+$E$54)^$H$34 +$I$31/(1+$E$54)^$I$34 +$J$31/(1+$E$54)^$J$34 +$K$31/(1+$E$54)^$K$34 +(($K$31*(1+G$53))/($E54-G$53))/(1+$E54)^$K$34 -$K$44 )/$K$47 -> #VALUE! | H54: =( $G$31/(1+$E$54)^$G$34 +$H$31/(1+$E$54)^$H$34 +$I$31/(1+$E$54)^$I$34 +$J$31/(1+$E$54)^$J$34 +$K$31/(1+$E$54)^$K$34 +(($K$31*(1+H$53))/($E54-H$53))/(1+$E54)^$K$34 -$K$44 )/$K$47 -> #VALUE! | I54: =( $G$31/(1+$E$54)^$G$34 +$H$31/(1+$E$54)^$H$34 +$I$31/(1+$E$54)^$I$34 +$J$31/(1+$E$54)^$J$34 +$K$31/(1+$E$54)^$K$34 +(($K$31*(1+I$53))/($E54-I$53))/(1+$E54)^$K$34 -$K$44 )/$K$47 -> #VALUE! | J54: =( $G$31/(1+$E$54)^$G$34 +$H$31/(1+$E$54)^$H$34 +$I$31/(1+$E$54)^$I$34 +$J$31/(1+$E$54)^$J$34 +$K$31/(1+$E$54)^$K$34 +(($K$31*(1+J$53))/($E54-J$53))/(1+$E54)^$K$34 -$K$44 )/$K$47 -> #VALUE!
E55: =E56-C52 -> #VALUE! | F55: =( $G$31/(1+$E$55)^$G$34 +$H$31/(1+$E$55)^$H$34 +$I$31/(1+$E$55)^$I$34 +$J$31/(1+$E$55)^$J$34 +$K$31/(1+$E$55)^$K$34 +(($K$31*(1+F$53))/($E55-F$53))/(1+$E$55)^$K$34 -$K$44 )/$K$47 -> #VALUE! | G55: =( $G$31/(1+$E$55)^$G$34 +$H$31/(1+$E$55)^$H$34 +$I$31/(1+$E$55)^$I$34 +$J$31/(1+$E$55)^$J$34 +$K$31/(1+$E$55)^$K$34 +(($K$31*(1+G$53))/($E55-G$53))/(1+$E$55)^$K$34 -$K$44 )/$K$47 -> #VALUE! | H55: =( $G$31/(1+$E$55)^$G$34 +$H$31/(1+$E$55)^$H$34 +$I$31/(1+$E$55)^$I$34 +$J$31/(1+$E$55)^$J$34 +$K$31/(1+$E$55)^$K$34 +(($K$31*(1+H$53))/($E55-H$53))/(1+$E$55)^$K$34 -$K$44 )/$K$47 -> #VALUE! | I55: =( $G$31/(1+$E$55)^$G$34 +$H$31/(1+$E$55)^$H$34 +$I$31/(1+$E$55)^$I$34 +$J$31/(1+$E$55)^$J$34 +$K$31/(1+$E$55)^$K$34 +(($K$31*(1+I$53))/($E55-I$53))/(1+$E$55)^$K$34 -$K$44 )/$K$47 -> #VALUE! | J55: =( $G$31/(1+$E$55)^$G$34 +$H$31/(1+$E$55)^$H$34 +$I$31/(1+$E$55)^$I$34 +$J$31/(1+$E$55)^$J$34 +$K$31/(1+$E$55)^$K$34 +(($K$31*(1+J$53))/($E55-J$53))/(1+$E$55)^$K$34 -$K$44 )/$K$47 -> #VALUE!
E56: =E14 -> 0.091815606 | F56: =( $G$31/(1+$E$56)^$G$34 +$H$31/(1+$E$56)^$H$34 +$I$31/(1+$E$56)^$I$34 +$J$31/(1+$E$56)^$J$34 +$K$31/(1+$E$56)^$K$34 +(($K$31*(1+F$53))/($E$56-F$53))/(1+$E$56)^$K$34 -$K$44 )/$K$47 -> #VALUE! | G56: =( $G$31/(1+$E$56)^$G$34 +$H$31/(1+$E$56)^$H$34 +$I$31/(1+$E$56)^$I$34 +$J$31/(1+$E$56)^$J$34 +$K$31/(1+$E$56)^$K$34 +(($K$31*(1+G$53))/($E$56-G$53))/(1+$E$56)^$K$34 -$K$44 )/$K$47 -> #VALUE! | H56: =( $G$31/(1+$E$56)^$G$34 +$H$31/(1+$E$56)^$H$34 +$I$31/(1+$E$56)^$I$34 +$J$31/(1+$E$56)^$J$34 +$K$31/(1+$E$56)^$K$34 +(($K$31*(1+H$53))/($E$56-H$53))/(1+$E$56)^$K$34 -$K$44 )/$K$47 -> -5.9100125 | I56: =( $G$31/(1+$E$56)^$G$34 +$H$31/(1+$E$56)^$H$34 +$I$31/(1+$E$56)^$I$34 +$J$31/(1+$E$56)^$J$34 +$K$31/(1+$E$56)^$K$34 +(($K$31*(1+I$53))/($E$56-I$53))/(1+$E$56)^$K$34 -$K$44 )/$K$47 -> #VALUE! | J56: =( $G$31/(1+$E$56)^$G$34 +$H$31/(1+$E$56)^$H$34 +$I$31/(1+$E$56)^$I$34 +$J$31/(1+$E$56)^$J$34 +$K$31/(1+$E$56)^$K$34 +(($K$31*(1+J$53))/($E$56-J$53))/(1+$E$56)^$K$34 -$K$44 )/$K$47 -> #VALUE!
E57: =E56+C52 -> #VALUE! | F57: =( $G$31/(1+$E$57)^$G$34 +$H$31/(1+$E$57)^$H$34 +$I$31/(1+$E$57)^$I$34 +$J$31/(1+$E$57)^$J$34 +$K$31/(1+$E$57)^$K$34 +(($K$31*(1+F$53))/($E$57-F$53))/(1+$E$57)^$K$34 -$K$44 )/$K$47 -> #VALUE! | G57: =( $G$31/(1+$E$57)^$G$34 +$H$31/(1+$E$57)^$H$34 +$I$31/(1+$E$57)^$I$34 +$J$31/(1+$E$57)^$J$34 +$K$31/(1+$E$57)^$K$34 +(($K$31*(1+G$53))/($E$57-G$53))/(1+$E$57)^$K$34 -$K$44 )/$K$47 -> #VALUE! | H57: =( $G$31/(1+$E$57)^$G$34 +$H$31/(1+$E$57)^$H$34 +$I$31/(1+$E$57)^$I$34 +$J$31/(1+$E$57)^$J$34 +$K$31/(1+$E$57)^$K$34 +(($K$31*(1+H$53))/($E$57-H$53))/(1+$E$57)^$K$34 -$K$44 )/$K$47 -> #VALUE! | I57: =( $G$31/(1+$E$57)^$G$34 +$H$31/(1+$E$57)^$H$34 +$I$31/(1+$E$57)^$I$34 +$J$31/(1+$E$57)^$J$34 +$K$31/(1+$E$57)^$K$34 +(($K$31*(1+I$53))/($E$57-I$53))/(1+$E$57)^$K$34 -$K$44 )/$K$47 -> #VALUE! | J57: =( $G$31/(1+$E$57)^$G$34 +$H$31/(1+$E$57)^$H$34 +$I$31/(1+$E$57)^$I$34 +$J$31/(1+$E$57)^$J$34 +$K$31/(1+$E$57)^$K$34 +(($K$31*(1+J$53))/($E$57-J$53))/(1+$E$57)^$K$34 -$K$44 )/$K$47 -> #VALUE!
E58: =E57+C52 -> #VALUE! | F58: =( $G$31/(1+$E$58)^$G$34 +$H$31/(1+$E$58)^$H$34 +$I$31/(1+$E$58)^$I$34 +$J$31/(1+$E$58)^$J$34 +$K$31/(1+$E$58)^$K$34 +(($K$31*(1+F$53))/($E$58-F$53))/(1+$E$58)^$K$34 -$K$44 )/$K$47 -> #VALUE! | G58: =( $G$31/(1+$E$58)^$G$34 +$H$31/(1+$E$58)^$H$34 +$I$31/(1+$E$58)^$I$34 +$J$31/(1+$E$58)^$J$34 +$K$31/(1+$E$58)^$K$34 +(($K$31*(1+G$53))/($E$58-G$53))/(1+$E$58)^$K$34 -$K$44 )/$K$47 -> #VALUE! | H58: =( $G$31/(1+$E$58)^$G$34 +$H$31/(1+$E$58)^$H$34 +$I$31/(1+$E$58)^$I$34 +$J$31/(1+$E$58)^$J$34 +$K$31/(1+$E$58)^$K$34 +(($K$31*(1+H$53))/($E$58-H$53))/(1+$E$58)^$K$34 -$K$44 )/$K$47 -> #VALUE! | I58: =( $G$31/(1+$E$58)^$G$34 +$H$31/(1+$E$58)^$H$34 +$I$31/(1+$E$58)^$I$34 +$J$31/(1+$E$58)^$J$34 +$K$31/(1+$E$58)^$K$34 +(($K$31*(1+I$53))/($E$58-I$53))/(1+$E$58)^$K$34 -$K$44 )/$K$47 -> #VALUE! | J58: =( $G$31/(1+$E$58)^$G$34 +$H$31/(1+$E$58)^$H$34 +$I$31/(1+$E$58)^$I$34 +$J$31/(1+$E$58)^$J$34 +$K$31/(1+$E$58)^$K$34 +(($K$31*(1+J$53))/($E$58-J$53))/(1+$E$58)^$K$34 -$K$44 )/$K$47 -> #VALUE!

Sheet 3 Statement
ZZ1: model_role
B2: Microsoft Corporation 3 Statement Model (millions)
B4: Income Statement | D4: 2023 A | E4: 2024 A | F4: 2025 A | G4: 2026 E | H4: 2027 E | I4: 2028 E | J4: 2029 E | K4: 2030 E | M4: Assumptions | N4: Type | O4: Value
B5: Revenue | D5: 211915 | E5: 245122 | F5: 281724 | G5: =F5*(1+O5) -> 284541.24 | H5: =G5*(1+P5) -> 287386.65 | I5: =H5*(1+Q5) -> 290260.52 | J5: =I5*(1+R5) -> 293163.12 | K5: =J5*(1+S5) -> 296094.76 | M5: Revenue | N5: constant | O5: 0.01 | P5: 0.01 | Q5: 0.01 | R5: 0.01 | S5: 0.01 | V5: 416161000000 | ZZ5: IS_REVENUE
B6: Cost of Revenue | D6: 65863 | E6: 74114 | F6: 87831 | G6: =G5-G7 -> 83018.485 | H6: =H5-H7 -> 78100.937 | I6: =I5-I7 -> 73076.736 | J6: =J5-J7 -> 67944.241 | K6: =K5-K7 -> 62701.788 | M6: Gross Margin | N6: constant | O6: 0.02 | P6: 0.02 | Q6: 0.02 | R6: 0.02 | S6: 0.02 | V6: 220960000000 | Y6: "researchAndDevelopmentExpenses": 34550000000, | ZZ6: IS_COGS
B7: Gross Profit | D7: 146052 | E7: 171008 | F7: 193893 | G7: =G8*G5 -> 201522.75 | H7: =H8*H5 -> 209285.72 | I7: =I8*I5 -> 217183.78 | J7: =J8*J5 -> 225218.88 | K7: =K8*K5 -> 233392.97 | M7: Operating Margin | N7: constant | O7: 0.03 | P7: 0.03 | Q7: 0.03 | R7: 0.03 | S7: 0.03 | V7: 195201000000 | Y7: "generalAndAdministrativeExpenses": 0, | ZZ7: IS_GROSS_PROFIT
B8: Gross Margin % | D8: =D7/D5 -> 0.68920086 | E8: =E7/E5 -> 0.69764444 | F8: =F7/F5 -> 0.68823742 | G8: =F8+(O6) -> 0.70823742 | H8: =G8+(P6) -> 0.72823742 | I8: =H8+(Q6) -> 0.74823742 | J8: =I8+(R6) -> 0.76823742 | K8: =J8+(S6) -> 0.78823742 | M8: Tax Rate | N8: constant | O8: 0.04 | P8: 0.04 | Q8: 0.04 | R8: 0.04 | S8: 0.04 | V8: 34550000000 | Y8: "sellingAndMarketingExpenses": 0, | ZZ8: BS_ACCOUNTS_RECEIVABLE
B9: Research & Development Expenses | D9: 97376 | E9: 113848 | F9: 139810 | G9: =(F9/F12)*(G7-G12) -> 68718.492 | H9: =(G9/G12)*(H7-H12) -> 30264.605 | I9: =(H9/H12)*(I7-I12) -> 11962.218 | J9: =(I9/I12)*(J7-J12) -> 4247.2464 | K9: =(J9/J12)*(K7-K12) -> 1355.0485 | M9: Interest Rate on Debt | N9: constant | O9: 0.05 | P9: 0.05 | Q9: 0.05 | R9: 0.05 | S9: 0.05 | V9: 0 | Y9: "sellingGeneralAndAdministrativeExpenses": 27601000000, | ZZ9: BS_ACCOUNTS_RECEIVABLE
B10: Selling, General & Administrative Expenses (SG&A) | D10: 145392 | E10: 155215 | F10: 163607 | G10: =(F10/F12)*(G7-G12) -> 80415.037 | H10: =(G10/G12)*(H7-H12) -> 35415.931 | I10: =(H10/H12)*(I7-I12) -> 13998.302 | J10: =(I10/I12)*(J7-J12) -> 4970.1683 | K10: =(J10/J12)*(K7-K12) -> 1585.6907 | V10: 0 | Y10: "otherExpenses": 0, | ZZ10: IS_OPERATING_EXPENSE
B11: Other Expenses | D11: 0 | E11: 0 | F11: 0 | G11: =(F11/F12)*(G7-G12) -> 0 | H11: =(G11/G12)*(H7-H12) -> 0 | I11: =(H11/H12)*(I7-I12) -> 0 | J11: =(I11/I12)*(J7-J12) -> 0 | K11: =(J11/J12)*(K7-K12) -> 0 | V11: 27601000000 | Y11: "operatingExpenses": 62151000000,
B12: Operating Profit | D12: 88523 | E12: 109433 | F12: 128528 | G12: =G13*G5 -> 138349.52 | H12: =H13*H5 -> 148354.61 | I12: =I13*I5 -> 158545.97 | J12: =J13*J5 -> 168926.33 | K12: =K13*K5 -> 179498.43 | ZZ12: IS_OPERATING_INCOME
B13: Operating Margin % | D13: =D12/D5 -> 0.41772881 | E13: =E12/E5 -> 0.446443 | F13: =F12/F5 -> 0.45621956 | G13: =F13+O7 -> 0.48621956 | H13: =G13+P7 -> 0.51621956 | I13: =H13+Q7 -> 0.54621956 | J13: =I13+R7 -> 0.57621956 | K13: =J13+S7 -> 0.60621956 | ZZ13: BS_ACCOUNTS_RECEIVABLE
B14: Net Interest Income | D14: 1026 | E14: 222 | F14: 262 | G14: =($F$14/$F$5)*G5 -> 264.62 | H14: =($F$14/$F$5)*H5 -> 267.2662 | I14: =($F$14/$F$5)*I5 -> 269.93886 | J14: =($F$14/$F$5)*J5 -> 272.63825 | K14: =($F$14/$F$5)*K5 -> 275.36463 | ZZ14: IS_NON_OPERATING_INCOME
B15: Other Non Operating Expenses | D15: 145392 | E15: 155215 | F15: 163607 | G15: =F15 -> 163607 | H15: =G15 -> 163607 | I15: =H15 -> 163607 | J15: =I15 -> 163607 | K15: =J15 -> 163607 | ZZ15: IS_OPERATING_EXPENSE
B16: Income Before Taxes | D16: 89311 | E16: 107787 | F16: 123627 | G16: =G12-G14-G15 -> -25522.103 | H16: =H12-H14-H15 -> -15519.654 | I16: =I12-I14-I15 -> -5330.9652 | J16: =J12-J14-J15 -> 5046.6888 | K16: =K12-K14-K15 -> 15616.068 | ZZ16: IS_OPERATING_INCOME
B17: Income Tax Expense | D17: 16950 | E17: 19651 | F17: 21795 | G17: =G16*O9 -> -1276.1051 | H17: =H16*P9 -> -775.98271 | I17: =I16*Q9 -> -266.54826 | J17: =J16*R9 -> 252.33444 | K17: =K16*S9 -> 780.80342 | ZZ17: IS_TAX_EXPENSE
B18: Net Income | D18: 144722 | E18: 176272 | F18: 203664 | G18: =G16-G17 -> -24245.998 | H18: =H16-H17 -> -14743.672 | I18: =I16-I17 -> -5064.417 | J18: =J16-J17 -> 4794.3544 | K18: =K16-K17 -> 14835.265 | ZZ18: IS_NET_INCOME
B19: Net Income Margin % | G19: =G18/G5 -> -0.085210839 | H19: =H18/H5 -> -0.051302562 | I19: =I18/I5 -> -0.017447833 | J19: =J18/J5 -> 0.016353879 | K19: =K18/K5 -> 0.050103099 | ZZ19: IS_NET_INCOME
B20: EPS | D20: 9.72e-06 | E20: 1.186e-05 | F20: 1.37e-05 | G20: =G18/G21 -> -0.17343346 | H20: =H18/H21 -> -0.10547014 | I20: =I18/I21 -> -0.036231342 | J20: =J18/J21 -> 0.034301741 | K20: =K18/K21 -> 0.10614815 | ZZ20: IS_NET_INCOME
B21: Weighted Average Shares Outstanding | D21: 97376 | E21: 113848 | F21: 139810 | G21: =F21+O70 -> 139800 | H21: =G21+P70 -> 139790 | I21: =H21+Q70 -> 139780 | J21: =I21+R70 -> 139770 | K21: =J21+S70 -> 139760 | ZZ21: BS_ACCOUNTS_RECEIVABLE
B24: Balance Sheet | D24: 2023 A | E24: 2024 A | F24: 2025 A | G24: 2026 E | H24: 2027 E | I24: 2028 E | J24: 2029 E | K24: 2030 E | M24: Assumptions | N24: Type | O24: Value
B25: Cash & Cash Equivalents | D25: 34704 | E25: 18315 | F25: 30242 | G25: =G101 -> 17262.795 | H25: =H101 -> 32963.726 | I25: =I101 -> 57602.979 | J25: =J101 -> 91351.224 | K25: =K101 -> 134382.03 | M25: Depreciation % of PPE | N25: constant | O25: 0.06 | P25: 0.06 | Q25: 0.06 | R25: 0.06 | S25: 0.06 | ZZ25: BS_CASH
B26: Short-Term Investments | D26: 76552 | E26: 57216 | F26: 64323 | G26: =(F26/F$5)*G$5 -> 64966.23 | H26: =(G26/G$5)*H$5 -> 65615.892 | I26: =(H26/H$5)*I$5 -> 66272.051 | J26: =(I26/I$5)*J$5 -> 66934.772 | K26: =(J26/J$5)*K$5 -> 67604.119 | M26: Inventory % Sales | N26: constant | O26: 0.07 | P26: 0.07 | Q26: 0.07 | R26: 0.07 | S26: 0.07
B27: Net Receivables | D27: 48688 | E27: 56924 | F27: 69905 | G27: =(F27/F$5)*G$5 -> 70604.05 | H27: =(G27/G$5)*H$5 -> 71310.091 | I27: =(H27/H$5)*I$5 -> 72023.191 | J27: =(I27/I$5)*J$5 -> 72743.423 | K27: =(J27/J$5)*K$5 -> 73470.858 | M27: Long Term Debt Change | N27: constant | O27: 0.06 | P27: 0.06 | Q27: 0.06 | R27: 0.06 | S27: 0.06
B28: Inventory | D28: 2500 | E28: 1246 | F28: 938 | G28: =G5*O26 -> 19917.887 | H28: =H5*P26 -> 20117.066 | I28: =I5*Q26 -> 20318.236 | J28: =J5*R26 -> 20521.419 | K28: =K5*S26 -> 20726.633 | ZZ28: BS_INVENTORY
B29: Prepaid Expenses | D29: 0 | E29: 0 | F29: 0 | G29: =(F29/F$5)*G$5 -> 0 | H29: =(G29/G$5)*H$5 -> 0 | I29: =(H29/H$5)*I$5 -> 0 | J29: =(I29/I$5)*J$5 -> 0 | K29: =(J29/J$5)*K$5 -> 0
B30: Other Current Assets | D30: 21813 | E30: 26033 | F30: 25723 | G30: =(F30/F$5)*G$5 -> 25980.23 | H30: =(G30/G$5)*H$5 -> 26240.032 | I30: =(H30/H$5)*I$5 -> 26502.433 | J30: =(I30/I$5)*J$5 -> 26767.457 | K30: =(J30/J$5)*K$5 -> 27035.132
B31: Total Current Assets | D31: 184257 | E31: 159734 | F31: 191131 | G31: =SUM(G25:G30) -> 198731.19 | H31: =SUM(H25:H30) -> 216246.81 | I31: =SUM(I25:I30) -> 242718.89 | J31: =SUM(J25:J30) -> 278318.29 | K31: =SUM(K25:K30) -> 323218.77
B32: Property, Plant & Equipment (Net) | D32: 109987 | E32: 154552 | F32: 229789 | G32: =F32-G81-G74 -> 249518.81 | H32: =G32-H81-H74 -> 250475.4 | I32: =H32-I81-I74 -> 251441.57 | J32: =I32-J81-J74 -> 252417.39 | K32: =J32-K81-K74 -> 253402.98
B33: Goodwill | D33: 67886 | E33: 119220 | F33: 119509 | G33: =F33 -> 119509 | H33: =G33 -> 119509 | I33: =H33 -> 119509 | J33: =I33 -> 119509 | K33: =J33 -> 119509
B34: Intangible Assets | D34: 9366 | E34: 27597 | F34: 22604 | G34: =F34 -> 22604 | H34: =G34 -> 22604 | I34: =H34 -> 22604 | J34: =I34 -> 22604 | K34: =J34 -> 22604
B35: Long-Term Investments | D35: 9879 | E35: 14600 | F35: 15405 | G35: =(F35/F$5)*G$5 -> 15559.05 | H35: =(G35/G$5)*H$5 -> 15714.64 | I35: =(H35/H$5)*I$5 -> 15871.787 | J35: =(I35/I$5)*J$5 -> 16030.505 | K35: =(J35/J$5)*K$5 -> 16190.81
B36: Tax Assets | D36: 0 | E36: 0 | F36: 0 | G36: =(F36/F$5)*G$5 -> 0 | H36: =(G36/G$5)*H$5 -> 0 | I36: =(H36/H$5)*I$5 -> 0 | J36: =(I36/I$5)*J$5 -> 0 | K36: =(J36/J$5)*K$5 -> 0
B37: Other Non-Current Assets | D37: 30601 | E37: 36460 | F37: 40565 | G37: =(F37/F$5)*G$5 -> 40970.65 | H37: =(G37/G$5)*H$5 -> 41380.357 | I37: =(H37/H$5)*I$5 -> 41794.16 | J37: =(I37/I$5)*J$5 -> 42212.102 | K37: =(J37/J$5)*K$5 -> 42634.223
B38: Other Non-Operating Adjustments | G38: =G67-SUM(G31,G32:G37) -> -33498.147 | H38: =H67-SUM(H31,H32:H37) -> -49406.873 | I38: =I67-SUM(I31,I32:I37) -> -65382.562 | J38: =J67-SUM(J31,J32:J37) -> -81425.881 | K38: =K67-SUM(K31,K32:K37) -> -97537.509
B39: Total Long-term Assets | D39: -2756 | E39: -1289 | F39: 2516 | G39: =SUM(G32:G37) -> 448161.51 | H39: =SUM(H32:H37) -> 449683.4 | I39: =SUM(I32:I37) -> 451220.52 | J39: =SUM(J32:J37) -> 452773 | K39: =SUM(K32:K37) -> 454341.01
B40: Total Assets | D40: 411976 | E40: 512163 | F40: 619003 | G40: =SUM(G31,G39,G38) -> 613394.55 | H40: =SUM(H31,H39,H38) -> 616523.34 | I40: =SUM(I31,I39,I38) -> 628556.84 | J40: =SUM(J31,J39,J38) -> 649665.41 | K40: =SUM(K31,K39,K38) -> 680022.27
B42: Accounts Payable | D42: 18095 | E42: 21996 | F42: 27724 | G42: =(F42/F$5)*G$5 -> 28001.24 | H42: =(G42/G$5)*H$5 -> 28281.252 | I42: =(H42/H$5)*I$5 -> 28564.065 | J42: =(I42/I$5)*J$5 -> 28849.706 | K42: =(J42/J$5)*K$5 -> 29138.203 | ZZ42: BS_ACCOUNTS_PAYABLE
B43: Other Payables | D43: 4152 | E43: 5017 | F43: 7211 | G43: =(F43/F$5)*G$5 -> 7283.11 | H43: =(G43/G$5)*H$5 -> 7355.9411 | I43: =(H43/H$5)*I$5 -> 7429.5005 | J43: =(I43/I$5)*J$5 -> 7503.7955 | K43: =(J43/J$5)*K$5 -> 7578.8335
B44: Accrued Expenses | D44: 0 | E44: 0 | F44: 0 | G44: =(F44/F$5)*G$5 -> 0 | H44: =(G44/G$5)*H$5 -> 0 | I44: =(H44/H$5)*I$5 -> 0 | J44: =(I44/I$5)*J$5 -> 0 | K44: =(J44/J$5)*K$5 -> 0 | ZZ44: BS_ACCRUED_LIABILITIES
B45: Short-Term Debt | D45: 5247 | E45: 8942 | F45: 2999 | G45: =(F45/F$5)*G$5 -> 3028.99 | H45: =(G45/G$5)*H$5 -> 3059.2799 | I45: =(H45/H$5)*I$5 -> 3089.8727 | J45: =(I45/I$5)*J$5 -> 3120.7714 | K45: =(J45/J$5)*K$5 -> 3151.9791 | ZZ45: BS_DEBT_CURRENT
B46: Current Capital Lease Obligations | D46: 0 | E46: 0 | F46: 0 | G46: =(F46/F$5)*G$5 -> 0 | H46: =(G46/G$5)*H$5 -> 0 | I46: =(H46/H$5)*I$5 -> 0 | J46: =(I46/I$5)*J$5 -> 0 | K46: =(J46/J$5)*K$5 -> 0 | ZZ46: BS_ACCOUNTS_PAYABLE
B47: Tax Payables | D47: 4152 | E47: 5017 | F47: 0 | G47: =(F47/F$5)*G$5 -> 0 | H47: =(G47/G$5)*H$5 -> 0 | I47: =(H47/H$5)*I$5 -> 0 | J47: =(I47/I$5)*J$5 -> 0 | K47: =(J47/J$5)*K$5 -> 0
B48: Deferred Revenue (Current) | D48: 50901 | E48: 57582 | F48: 64555 | G48: =(F48/F$5)*G$5 -> 65200.55 | H48: =(G48/G$5)*H$5 -> 65852.556 | I48: =(H48/H$5)*I$5 -> 66511.081 | J48: =(I48/I$5)*J$5 -> 67176.192 | K48: =(J48/J$5)*K$5 -> 67847.954 | ZZ48: IS_REVENUE
B49: Other Current Liabilities | D49: 25754 | E49: 31749 | F49: 38729 | G49: =(F49/F$5)*G$5 -> 39116.29 | H49: =(G49/G$5)*H$5 -> 39507.453 | I49: =(H49/H$5)*I$5 -> 39902.527 | J49: =(I49/I$5)*J$5 -> 40301.553 | K49: =(J49/J$5)*K$5 -> 40704.568
B50: Total Current Liabilities | D50: 104149 | E50: 125286 | F50: 141218 | G50: =SUM(G42:G49) -> 142630.18 | H50: =SUM(H42:H49) -> 144056.48 | I50: =SUM(I42:I49) -> 145497.05 | J50: =SUM(J42:J49) -> 146952.02 | K50: =SUM(K42:K49) -> 148421.54
B51: Long-Term Debt | D51: 41990 | E51: 42688 | F51: 40152 | G51: =F51*(1+O27) -> 42561.12 | H51: =G51*(1+P27) -> 45114.787 | I51: =H51*(1+Q27) -> 47821.674 | J51: =I51*(1+R27) -> 50690.975 | K51: =J51*(1+S27) -> 53732.433 | ZZ51: BS_DEBT_CURRENT
B52: Non-Current Capital Lease Obligations | D52: 12728 | E52: 15497 | F52: 17437 | G52: =F52 -> 17437 | H52: =G52 -> 17437 | I52: =H52 -> 17437 | J52: =I52 -> 17437 | K52: =J52 -> 17437 | ZZ52: BS_ACCOUNTS_PAYABLE
B53: Deferred Revenue (Non-Current) | D53: 2912 | E53: 2602 | F53: 2710 | G53: =(F53/F$5)*G$5 -> 2737.1 | H53: =(G53/G$5)*H$5 -> 2764.471 | I53: =(H53/H$5)*I$5 -> 2792.1157 | J53: =(I53/I$5)*J$5 -> 2820.0369 | K53: =(J53/J$5)*K$5 -> 2848.2372 | ZZ53: IS_REVENUE
B54: Deferred Tax Liabilities (Non-Current) | D54: 433 | E54: 2618 | F54: 2835 | G54: =(F54/F$5)*G$5 -> 2863.35 | H54: =(G54/G$5)*H$5 -> 2891.9835 | I54: =(H54/H$5)*I$5 -> 2920.9033 | J54: =(I54/I$5)*J$5 -> 2950.1124 | K54: =(J54/J$5)*K$5 -> 2979.6135
B55: Other Non-Current Liabilities | D55: 43541 | E55: 54995 | F55: 71172 | G55: =F55 -> 71172 | H55: =G55 -> 71172 | I55: =H55 -> 71172 | J55: =I55 -> 71172 | K55: =J55 -> 71172
B56: Total Non-Current Liabilities | D56: 101604 | E56: 118400 | F56: 134306 | G56: =SUM(G51:G55) -> 136770.57 | H56: =SUM(H51:H55) -> 139380.24 | I56: =SUM(I51:I55) -> 142143.69 | J56: =SUM(J51:J55) -> 145070.12 | K56: =SUM(K51:K55) -> 148169.28
B57: Total Liabilities | D57: 205753 | E57: 243686 | F57: 275524 | G57: =SUM(G50,G56) -> 279400.75 | H57: =SUM(H50,H56) -> 283436.72 | I57: =SUM(I50,I56) -> 287640.74 | J57: =SUM(J50,J56) -> 292022.14 | K57: =SUM(K50,K56) -> 296590.82
B59: Preferred Stock | D59: 0 | E59: 0 | F59: 0 | G59: =F59+G90 -> 0 | H59: =G59+H90 -> 0 | I59: =H59+I90 -> 0 | J59: =I59+J90 -> 0 | K59: =J59+K90 -> 0
B60: Treasury Stock | D60: 0 | E60: 0 | F60: 0 | G60: =F60+G89 -> 0 | H60: =G60+H89 -> 0 | I60: =H60+I89 -> 0 | J60: =I60+J89 -> 0 | K60: =J60+K89 -> 0
B61: Common Stock | D61: 93718 | E61: 100923 | F61: 109095 | G61: =F61+G73 -> 121188.74 | H61: =G61+H73 -> 133403.42 | I61: =H61+I73 -> 145740.24 | J61: =I61+J73 -> 158200.43 | K61: =J61+K73 -> 170785.23
B62: Retained Earnings | D62: 118848 | E62: 173144 | F62: 237731 | G62: =F62+G18+G91 -> 216152.06 | H62: =G62+H18+H91 -> 203030.19 | I62: =H62+I18+I91 -> 198522.86 | J62: =I62+J18+J91 -> 202789.84 | K62: =J62+K18+K91 -> 215993.22 | ZZ62: BS_ACCOUNTS_RECEIVABLE
B63: Additional Paid-In Capital | D63: 0 | E63: 0 | F63: 0 | G63: =F63 -> 0 | H63: =G63 -> 0 | I63: =H63 -> 0 | J63: =I63 -> 0 | K63: =J63 -> 0 | ZZ63: BS_ACCOUNTS_PAYABLE
B64: Accumulated Other Comprehensive Income (Loss) | D64: -6343 | E64: -5590 | F64: -3347 | G64: =F64 -> -3347 | H64: =G64 -> -3347 | I64: =H64 -> -3347 | J64: =I64 -> -3347 | K64: =J64 -> -3347
B65: Other Stockholders’ Equity | D65: 0 | E65: 0 | F65: 0 | G65: =F65 -> 0 | H65: =G65 -> 0 | I65: =H65 -> 0 | J65: =I65 -> 0 | K65: =J65 -> 0
B66: Total Equity | D66: 206223 | E66: 268477 | F66: 343479 | G66: =SUM(G59:G65) -> 333993.8 | H66: =SUM(H59:H65) -> 333086.61 | I66: =SUM(I59:I65) -> 340916.1 | J66: =SUM(J59:J65) -> 357643.27 | K66: =SUM(K59:K65) -> 383431.45
B67: Total Liabilities & Equity | D67: =SUM(D66,D57) -> 411976 | E67: =SUM(E66,E57) -> 512163 | F67: =SUM(F66,F57) -> 619003 | G67: =SUM(G66,G57) -> 613394.55 | H67: =SUM(H66,H57) -> 616523.34 | I67: =SUM(I66,I57) -> 628556.84 | J67: =SUM(J66,J57) -> 649665.41 | K67: =SUM(K66,K57) -> 680022.27
B69: Cash Flow Statement | D69: 2023 A | E69: 2024 A | F69: 2025 A | G69: 2026 E | H69: 2027 E | I69: 2028 E | J69: 2029 E | K69: 2030 E | M69: Assumptions | N69: Type | O69: Value | ZZ69: BS_CASH
B70: Net Income | D70: 144722 | E70: 176272 | F70: 203664 | G70: =G18 -> -24245.998 | H70: =H18 -> -14743.672 | I70: =I18 -> -5064.417 | J70: =J18 -> 4794.3544 | K70: =K18 -> 14835.265 | M70: Share Repurchases | N70: constant | O70: -10 | P70: -10 | Q70: -10 | R70: -10 | S70: -10 | ZZ70: IS_NET_INCOME
B71: Depreciation & Amortization | D71: 13861 | E71: 22287 | F71: 34153 | G71: =O25*F32 -> 13787.34 | H71: =P25*G32 -> 14971.128 | I71: =Q25*H32 -> 15028.524 | J71: =R25*I32 -> 15086.494 | K71: =S25*J32 -> 15145.044 | M71: Dividends as a % of Net Income | N71: constant | O71: 0.11 | P71: 0.11 | Q71: 0.11 | R71: 0.11 | S71: 0.11 | ZZ71: CF_DEPRECIATION
B72: Deferred Income Tax | D72: -6059 | E72: -4738 | F72: -7056 | G72: =(-G36+G54)-(-F36+F54) -> 28.35 | H72: =(-H36+H54)-(-G36+G54) -> 28.6335 | I72: =(-I36+I54)-(-H36+H54) -> 28.919835 | J72: =(-J36+J54)-(-I36+I54) -> 29.209033 | K72: =(-K36+K54)-(-J36+J54) -> 29.501124 | M72: CAPEX | N72: constant | O72: -9 | P72: -9 | Q72: -9 | R72: -9 | S72: -9
B73: Stock-Based Compensation | D73: 9611 | E73: 10734 | F73: 11974 | G73: =(F73/F$5)*G$5 -> 12093.74 | H73: =(G73/G$5)*H$5 -> 12214.677 | I73: =(H73/H$5)*I$5 -> 12336.824 | J73: =(I73/I$5)*J$5 -> 12460.192 | K73: =(J73/J$5)*K$5 -> 12584.794
B74: Change in Working Capital | D74: -2388 | E74: 1824 | F74: -5350 | G74: =(SUM(F27:F30,F37)-SUM(F47:F49,F42:F44,F53,F55))-(SUM(G27:G30,G37)-SUM(G47:G49,G42:G44,G53,G55)) -> -18932.527 | H74: =(SUM(G27:G30,G37)-SUM(G47:G49,G42:G44,G53,G55))-(SUM(H27:H30,H37)-SUM(H47:H49,H42:H44,H53,H55)) -> -151.34527 | I74: =(SUM(H27:H30,H37)-SUM(H47:H49,H42:H44,H53,H55))-(SUM(I27:I30,I37)-SUM(I47:I49,I42:I44,I53,I55)) -> -152.85872 | J74: =(SUM(I27:I30,I37)-SUM(I47:I49,I42:I44,I53,I55))-(SUM(J27:J30,J37)-SUM(J47:J49,J42:J44,J53,J55)) -> -154.38731 | K74: =(SUM(J27:J30,J37)-SUM(J47:J49,J42:J44,J53,J55))-(SUM(K27:K30,K37)-SUM(K47:K49,K42:K44,K53,K55)) -> -155.93118 | ZZ74: CF_CHANGE_IN_WORKING_CAPITAL
B75: Other Non-Cash Items | D75: 34704 | E75: 18315 | F75: 30242 | G75: 0 | H75: 0 | I75: 0 | J75: 0 | K75: 0 | ZZ75: BS_CASH
B76: Net Cash Provided by Operating Activities | D76: 87582 | E76: 118548 | F76: 136162 | G76: =SUM(G70:G75) -> -17269.094 | H76: =SUM(H70:H75) -> 12319.422 | I76: =SUM(I70:I75) -> 22176.993 | J76: =SUM(J70:J75) -> 32215.863 | K76: =SUM(K70:K75) -> 42438.673 | ZZ76: BS_CASH
B78: Investments in Property, Plant & Equipment (CapEx) | D78: -28107 | E78: -44477 | F78: -64551 | G78: =O72 -> -9 | H78: =P72 -> -9 | I78: =Q72 -> -9 | J78: =R72 -> -9 | K78: =S72 -> -9 | ZZ78: CF_CAPEX
B79: Net Acquisitions | G79: 0 | H79: 0 | I79: 0 | J79: 0 | K79: =(J$79/$F$5)*K$5 -> 0
B80: Purchases of Investments | G80: 0 | H80: 0 | I80: 0 | J80: 0 | K80: 0
B81: Sales / Maturities of Investments | D81: 211915 | E81: 245122 | F81: 281724 | G81: =F26-G26+F35-G35 -> -797.28 | H81: =G26-H26+G35-H35 -> -805.2528 | I81: =H26-I26+H35-I35 -> -813.30533 | J81: =I26-J26+I35-J35 -> -821.43838 | K81: =J26-K26+J35-K35 -> -829.65277 | ZZ81: IS_REVENUE
B82: Other Investing Activities | G82: 0 | H82: 0 | I82: 0 | J82: 0 | K82: 0
B83: Net Cash Provided by Investing Activities | D83: 34704 | E83: 18315 | F83: 30242 | G83: =SUM(G78:G82) -> -806.28 | H83: =SUM(H78:H82) -> -814.2528 | I83: =SUM(I78:I82) -> -822.30533 | J83: =SUM(J78:J82) -> -830.43838 | K83: =SUM(K78:K82) -> -838.65277 | ZZ83: BS_CASH
B85: Net Debt Issuance | D85: 5247 | E85: 8942 | F85: 2999 | G85: =G51+G45-F45-F51 -> 2439.11 | H85: =H51+H45-G45-G51 -> 2583.9571 | I85: =I51+I45-H45-H51 -> 2737.48 | J85: =J51+J45-I45-I51 -> 2900.1992 | K85: =K51+K45-J45-J51 -> 3072.6662 | ZZ85: BS_DEBT_CURRENT
B86: Net Stock Issuance | D86: -20379 | E86: -15252 | F86: -16364 | G86: =O70 -> -10 | H86: =P70 -> -10 | I86: =Q70 -> -10 | J86: =R70 -> -10 | K86: =S70 -> -10
B87: Net Common Stock Issuance | D87: -20379 | E87: -15252 | F87: -16364 | G87: 0 | H87: 0 | I87: 0 | J87: 0 | K87: 0
B88: Common Stock Issued | D88: 1866 | E88: 2002 | F88: 2056 | G88: 0 | H88: 0 | I88: 0 | J88: 0 | K88: 0
B89: Common Stock Repurchased | D89: -22245 | E89: -17254 | F89: -18420 | G89: 0 | H89: 0 | I89: 0 | J89: 0 | K89: 0
B90: Net Preferred Stock Issuance | D90: 0 | E90: 0 | F90: 0 | G90: 0 | H90: 0 | I90: 0 | J90: 0 | K90: 0
B91: Dividends Paid (Net) | D91: -19800 | E91: -21771 | F91: -24082 | G91: =-O71*G18 -> 2667.0597 | H91: =-P71*H18 -> 1621.8039 | I91: =-Q71*I18 -> 557.08587 | J91: =-R71*J18 -> -527.37898 | K91: =-S71*K18 -> -1631.8791 | ZZ91: CF_DIVIDENDS_PAID
B92: Common Dividends Paid | D92: -19800 | E92: -21771 | F92: -24082 | G92: 0 | H92: 0 | I92: 0 | J92: 0 | K92: 0 | ZZ92: CF_DIVIDENDS_PAID
B93: Preferred Dividends Paid | D93: -19800 | E93: -21771 | F93: -24082 | G93: 0 | H93: 0 | I93: 0 | J93: 0 | K93: 0 | ZZ93: CF_DIVIDENDS_PAID
B94: Other Financing Activities | D94: -1006 | E94: -1309 | F94: -2291 | G94: 0 | H94: 0 | I94: 0 | J94: 0 | K94: 0
B95: Net Cash Provided by Financing Activities | D95: -43935 | E95: -37757 | F95: -51699 | G95: =SUM(G85:G94) -> 5096.1697 | H95: =SUM(H85:H94) -> 4195.761 | I95: =SUM(I85:I94) -> 3284.5659 | J95: =SUM(J85:J94) -> 2362.8202 | K95: =SUM(K85:K94) -> 1430.7871 | ZZ95: BS_CASH
B97: Effect of Foreign Exchange on Cash | D97: 34704 | E97: 18315 | F97: 30242 | G97: 0 | H97: 0 | I97: 0 | J97: 0 | K97: 0 | ZZ97: BS_CASH
B99: Cash at Beginning of Period | D99: 34704 | E99: 18315 | F99: 30242 | G99: =F101 -> 30242 | H99: =G101 -> 17262.795 | I99: =H101 -> 32963.726 | J99: =I101 -> 57602.979 | K99: =J101 -> 91351.224 | ZZ99: BS_CASH
B100: Net Change in Cash | D100: 20773 | E100: -16389 | F100: 11927 | G100: =G95+G97+G83+G76 -> -12979.205 | H100: =H95+H97+H83+H76 -> 15700.931 | I100: =I95+I97+I83+I76 -> 24639.253 | J100: =J95+J97+J83+J76 -> 33748.245 | K100: =K95+K97+K83+K76 -> 43030.807 | ZZ100: BS_CASH
B101: Cash at End of Period | D101: 34704 | E101: 18315 | F101: 30242 | G101: =G99+G100 -> 17262.795 | H101: =H99+H100 -> 32963.726 | I101: =I99+I100 -> 57602.979 | J101: =J99+J100 -> 91351.224 | K101: =K99+K100 -> 134382.03 | ZZ101: BS_CASH
B103: Free Cash Flow | D103: 34704 | E103: 18315 | F103: 30242 | G103: =G$12*(1-$O$9)+G71-G78-G74 -> 164160.91 | H103: =H12*(1-P9)+H71-H78-H74 -> 156068.36 | I103: =I12*(1-Q9)+I71-I78-I74 -> 165809.06 | J103: =J12*(1-R9)+J71-J78-J74 -> 175729.89 | K103: =K12*(1-S9)+K71-K78-K74 -> 185833.49 | ZZ103: BS_CASH
B106: Balance Check | D106: =D40-D67 -> 0 | E106: =E40-E67 -> 0 | F106: =F40-F67 -> 0 | G106: =G40-G67 -> 0 | H106: =H40-H67 -> 0 | I106: =I40-I67 -> 0 | J106: =J40-J67 -> 0 | K106: =K40-K67 -> 0

Sheet RV
B2: Microsoft Corporation Relative Valuation
D4: EV/Sales | E4: Price/Sales | F4: Price/Earnings | G4: Price/Book Value | I4: Weight
B5: Microsoft Corporation | D5: =G16/F16 -> 12.71215 | E5: =E16/(F16/(K16/1000000)) -> 12.658682 | F5: =E16/I16 -> 35.024194 | G5: =E16/(J16/(K16/1000000)) -> 10.382744 | I5: EV/Sales | J5: 0.25
B6: GM | D6: =G17/F17 -> 0.96295019 | E6: =E17/(F17/(K17/1000000)) -> 0.44987255 | F6: =E17/I17 -> 11.725275 | G6: =E17/(J17/(K17/1000000)) -> 1.3369643 | I6: Price/Sales | J6: 0.25
B7: ORCL | D7: =G18/F18 -> 11.778322 | E7: =E18/(F18/(K18/1000000)) -> 10.372205 | F7: =E18/I18 -> 47.864055 | G7: =E18/(J18/(K18/1000000)) -> 29.11125 | I7: Price/Earnings | J7: 0.25
B8: TSLA | D8: =G19/F19 -> 14.700758 | E8: =E19/(F19/(K19/1000000)) -> 15.996484 | F8: =E19/I19 -> 218.9902 | G8: =E19/(J19/(K19/1000000)) -> 21.432344 | I8: Price/Book Value | J8: 0.25
B9: AAPL | D9: =G20/F20 -> 10.239844 | E9: =E20/(F20/(K20/1000000)) -> 10.245037 | F9: =E20/I20 -> 38.089812 | G9: =E20/(J20/(K20/1000000)) -> 57.824646
B10: Low | D10: =MIN(D5:D9) -> 0.96295019 | E10: =MIN(E5:E9) -> 0.44987255 | F10: =MIN(F5:F9) -> 11.725275 | G10: =MIN(G5:G9) -> 1.3369643 | I10: Implied Price Target | J10: =(D13*J5)+(E13*J6)+(F13*J7)+(G13*J8) -> 704.02863
B11: Average | D11: =AVERAGE(D5:D9) -> 10.078805 | E11: =AVERAGE(E5:E9) -> 9.9444559 | F11: =AVERAGE(F5:F9) -> 70.338706 | G11: =AVERAGE(G5:G9) -> 24.01759 | I11: Implied Upside/Downside | J11: =(J10/E16)-1 -> 0.47369566
B12: High | D12: =MAX(D5:D9) -> 14.700758 | E12: =MAX(E5:E9) -> 15.996484 | F12: =MAX(F5:F9) -> 218.9902 | G12: =MAX(G5:G9) -> 57.824646
B13: Microsoft Corporation | D13: =(((D11)*F16)-H16)/(K16/1000000) -> 376.30211 | E13: =E11*(F16/(K16/1000000)) -> 375.29697 | F13: =F11*(I16) -> 959.41996 | G13: =G11*(J16/(K16/1000000)) -> 1105.0955
B15: Financials | D15: Market Cap | E15: Share Price | F15: Sales | G15: Enterprise Value | H15: Net Debt | I15: EPS | J15: Book Value | K15: Shares/OS
B16: Microsoft Corporation | D16: 3550971.8 | E16: 477.73 | F16: 281724 | G16: 3581317.8 | H16: 30346 | I16: 13.64 | J16: 343479 | K16: 7465000000
B17: GM | D17: 69676.309 | E17: 74.69 | F17: 187442 | G17: 180497.31 | H17: 110821 | I17: 6.37 | J17: 63072 | K17: 1129000000
B18: ORCL | D18: 582745.93 | E18: 207.73 | F18: 57399 | G18: 676063.93 | H18: 93318 | I18: 4.34 | J18: 20451 | K18: 2866000000
B19: TSLA | D19: 1438633.1 | E19: 446.74 | F19: 97690 | G19: 1436117.1 | H19: -2516 | I19: 2.04 | J19: 72913 | K19: 3498000000
B20: AAPL | D20: 4198700.7 | E20: 284.15 | F20: 416161 | G20: 4261423.7 | H20: 62723 | I20: 7.46 | J20: 73733 | K20: 15004697000

Sheet Beta
B2: Ticker | C2: MSFT
B3: Benchmark | C3: S&P 500
B4: Lookback (years) | C4: 5
B5: Beta | C5: =SLOPE(E8:E1260,F8:F1260) -> 1.1566004
B6: Date | C6: Ticker Adj Close | D6: Benchmark Adj Close | E6: Ticker Returns | F6: Benchmark Returns
B7: 44172 | C7: 205.61977 | D7: 3691.96
B8: 44173 | C8: 207.27016 | D8: 3702.25 | E8: =((C8/C7)-1)*100 -> 0.80264201 | F8: =((D8/D7)-1)*100 -> 0.27871481
B9: 44174 | C9: 203.23055 | D9: 3672.8201 | E9: =((C9/C8)-1)*100 -> -1.9489597 | F9: =((D9/D8)-1)*100 -> -0.79492016
B10: 44175 | C10: 202.0023 | D10: 3668.1001 | E10: =((C10/C9)-1)*100 -> -0.60435845 | F10: =((D10/D9)-1)*100 -> -0.12851081
B11: 44176 | C11: 204.63148 | D11: 3663.46 | E11: =((C11/C10)-1)*100 -> 1.3015599 | F11: =((D11/D10)-1)*100 -> -0.12649973
B12: 44179 | C12: 205.53343 | D12: 3647.49 | E12: =((C12/C11)-1)*100 -> 0.44076649 | F12: =((D12/D11)-1)*100 -> -0.4359259
B13: 44180 | C13: 205.46623 | D13: 3694.6201 | E13: =((C13/C12)-1)*100 -> -0.032695268 | F13: =((D13/D12)-1)*100 -> 1.2921249
B14: 44181 | C14: 210.40791 | D14: 3701.1699 | E14: =((C14/C13)-1)*100 -> 2.4051061 | F14: =((D14/D13)-1)*100 -> 0.17727952
B15: 44182 | C15: 210.54224 | D15: 3722.48 | E15: =((C15/C14)-1)*100 -> 0.063839386 | F15: =((D15/D14)-1)*100 -> 0.57576548
B16: 44183 | C16: 209.74579 | D16: 3709.4099 | E16: =((C16/C15)-1)*100 -> -0.37828408 | F16: =((D16/D15)-1)*100 -> -0.35111185
B17: 44186 | C17: 213.58394 | D17: 3694.9199 | E17: =((C17/C16)-1)*100 -> 1.8299056 | F17: =((D17/D16)-1)*100 -> -0.39062791
B18: 44187 | C18: 214.8793 | D18: 3687.26 | E18: =((C18/C17)-1)*100 -> 0.6064896 | F18: =((D18/D17)-1)*100 -> -0.20730929
B19: 44188 | C19: 212.0775 | D19: 3690.01 | E19: =((C19/C18)-1)*100 -> -1.3038964 | F19: =((D19/D18)-1)*100 -> 0.074581125
... B1260: 45994 | C1260: 477.73001 | D1260: 6849.7202 | E1260: =((C1260/C1259)-1)*100 -> -2.5040794 | F1260: =((D1260/D1259)-1)*100 -> 0.29797913

Sheet DCF Q
B2: "Company Name" DCF Analysis (UNITS)
B4: WACC | G4: Other Assumptions
B5: Beta | E5: # | G5: Fiscal Year End | J5: 46022
B6: Market Risk Premium | E6: # | G6: LTGR | J6: 0.02
B7: Risk Free Rate | E7: # | G7: Cash & Equivalents | J7: # | L7: 1 year (4 Quarters) historical and forecasted
B8: Cost of Equity | E8: =E7+(E5*E6) -> #VALUE! | G8: Diluted S/O | J8: #
B9: Weight of Equity | E9: =J10/SUM(J10:J11) -> #VALUE! | G9: Current Price | J9: #
B10: Cost of Debt | E10: # | G10: Mkt Cap | J10: =J8*J9 -> #VALUE!
B11: After Tax CoD | E11: =E10*(1-E13) -> #VALUE! | G11: BV debt
B12: Weight of Debt | E12: =1-E9 -> #VALUE! | G12: Financial Units
B13: Tax Rate | E13: #
B14: WACC | E14: =(E9*E8)+(E11*E12) -> #VALUE!
B16: Free Cash Flow | D16: Q1 "YEAR""A" | E16: Q2 "YEAR""A" | F16: Q3 "YEAR""A" | G16: Q4 "YEAR""A" | H16: "####"A | I16: Q1 "YEAR""E" | J16: Q2 "YEAR""E" | K16: Q3 "YEAR""E" | L16: Q4 "YEAR""E" | M16: "####"E
B17: Revenue | D17: HIST | E17: HIST | F17: HIST | G17: HIST | H17: =SUM(D17:G17) -> 0 | I17: Forecast Formula | J17: Forecast Formula | K17: Forecast Formula | L17: Forecast Formula | M17: =SUM(I17:L17) -> 0
B18: Revenue Growth (%) | E18: =IFERROR(E17/D17-1,"") | F18: =IFERROR(F17/E17-1,"") | G18: =IFERROR(G17/F17-1,"") | I18: =I17/H17-1 -> #VALUE! | J18: =J17/I17-1 -> #VALUE! | K18: =K17/J17-1 -> #VALUE! | L18: =L17/K17-1 -> #VALUE!
B19: (-) COGS | D19: HIST | E19: HIST | F19: HIST | G19: HIST | H19: =SUM(D19:G19) -> 0 | M19: =SUM(I19:L19) -> 0
B20: GP | D20: =D17+D19 -> #VALUE! | E20: =E17+E19 -> #VALUE! | F20: =F17+F19 -> #VALUE! | G20: =G17+G19 -> #VALUE! | H20: =H17+H19 -> 0 | I20: =I17+I19 -> #VALUE! | J20: =J17+J19 -> #VALUE! | K20: =K17+K19 -> #VALUE! | ... M20: =M17+M19 -> 0
B21: GP Margin (%) | D21: =D19/D17 -> #VALUE! | E21: =E19/E17 -> #VALUE! | F21: =F19/F17 -> #VALUE! | G21: =G19/G17 -> #VALUE! | H21: =H19/H17 -> #DIV/0! | I21: =I19/I17 -> #VALUE! | J21: =J19/J17 -> #VALUE! | K21: =K19/K17 -> #VALUE! | ... M21: =M19/M17 -> #DIV/0!
B23: (-) Op Ex | D23: HIST | E23: HIST | F23: HIST | G23: HIST | H23: =SUM(D23:G23) -> 0 | I23: Forecast Formula | J23: Forecast Formula | K23: Forecast Formula | L23: Forecast Formula | M23: =SUM(I23:L23) -> 0
B24: EBIT | D24: =D20+D23 -> #VALUE! | E24: =E20+E23 -> #VALUE! | F24: =F20+F23 -> #VALUE! | G24: =G20+G23 -> #VALUE! | H24: =H20+H23 -> 0 | I24: =I20+I23 -> #VALUE! | J24: =J20+J23 -> #VALUE! | K24: =K20+K23 -> #VALUE! | ... M24: =M20+M23 -> 0
B25: EBIT Margin (%) | D25: =D24/D17 -> #VALUE! | E25: =E24/E17 -> #VALUE! | F25: =F24/F17 -> #VALUE! | G25: =G24/G17 -> #VALUE! | H25: =H23/H17 -> #DIV/0! | I25: =I23/I17 -> #VALUE! | J25: =J23/J17 -> #VALUE! | K25: =K23/K17 -> #VALUE! | L25: =L23/L17 -> #VALUE! | M25: =M23/M17 -> #DIV/0!
B27: NOPAT | D27: =D24*(1-$E$13) -> #VALUE! | E27: =E24*(1-$E$13) -> #VALUE! | F27: =F24*(1-$E$13) -> #VALUE! | G27: =G24*(1-$E$13) -> #VALUE! | H27: =H24*(1-$E$13) -> #VALUE! | I27: =I24*(1-$E$13) -> #VALUE! | J27: =J24*(1-$E$13) -> #VALUE! | K27: =K24*(1-$E$13) -> #VALUE! | ... M27: =M24*(1-$E$13) -> #VALUE!
B28: (+) D&A | D28: HIST | E28: HIST | F28: HIST | G28: HIST | H28: =SUM(D28:G28) -> 0 | I28: Forecast Formula | J28: Forecast Formula | K28: Forecast Formula | L28: Forecast Formula | M28: =SUM(I28:L28) -> 0
B29: (-) CapEx | D29: HIST | E29: HIST | F29: HIST | G29: HIST | H29: =SUM(D29:G29) -> 0 | I29: Forecast Formula | J29: Forecast Formula | K29: Forecast Formula | L29: Forecast Formula | M29: =SUM(I29:L29) -> 0
B30: (-) Changes in WC | D30: HIST | E30: HIST | F30: HIST | G30: HIST | H30: =SUM(D30:G30) -> 0 | I30: Forecast Formula | J30: Forecast Formula | K30: Forecast Formula | L30: Forecast Formula | M30: =SUM(I30:L30) -> 0
B31: Unlevered Free Cash Flow | D31: =D27+D28+D29+D30 -> #VALUE! | E31: =E27+E28+E29+E30 -> #VALUE! | F31: =F27+F28+F29+F30 -> #VALUE! | G31: =G27+G28+G29+G30 -> #VALUE! | H31: =H27+H28+H29+H30 -> #VALUE! | I31: =I27+I28+I29+I30 -> #VALUE! | J31: =J27+J28+J29+J30 -> #VALUE! | K31: =K27+K28+K29+K30 -> #VALUE! | ... M31: =M27+M28+M29+M30 -> #VALUE!
B33: DCF | I33: Year"E" | J33: Year"E" | K33: Year"E" | L33: Year"E" | M33: Year"E"
B34: Discount Period | I34: =YEARFRAC(TODAY(),$J$5) -> 0.075 | J34: =I34+0.25 -> 0.325 | K34: =J34+0.25 -> 0.575 | L34: =K34+0.25 -> 0.825
B35: Discount Factor | I35: =(1/(1+$E$14))^I34 -> #VALUE! | J35: =(1/(1+$E$14))^J34 -> #VALUE! | K35: =(1/(1+$E$14))^K34 -> #VALUE! | L35: =(1/(1+$E$14))^L34 -> #VALUE!
B37: PV of UFCF | I37: =I31*I35 -> #VALUE! | J37: =J31*J35 -> #VALUE! | K37: =K31*K35 -> #VALUE! | L37: =L31*L35 -> #VALUE! | M37: =SUM(I37:L37) -> #VALUE!
B38: Total PV of UFCF | M38: =SUM(M37) -> #VALUE!
B40: Terminal Value | M40: =(M31*(1+J6))/(E14-F2) -> #VALUE!
B41: PV of TV | M41: =M40*M35 -> #VALUE!
B43: Enterprise Value | M43: =M38+M41 -> #VALUE!
B44: (-) Net Debt | M44: =-($J$11-$J$7) -> #VALUE!
B45: Equity Value | M45: =M43+M44 -> #VALUE!
B47: (/) Shares Outstanding | M47: =J8 -> #
B48: Per Share Price Target | M48: =M45/M47 -> #VALUE!
B49: Implied Upside/Downside | M49: =M48/J9-1 -> #VALUE!

Sheet 3-STMT Q
B2: "Company Name" 3 Statement Model (UNITS)
B4: Income Statement
D5: Q1 "YEAR""A" | E5: Q2 "YEAR""A" | F5: Q3 "YEAR""A" | G5: Q4 "YEAR""A" | H5: "####"A | I5: Q1 "YEAR""E" | J5: Q2 "YEAR""E" | K5: Q3 "YEAR""E" | L5: Q4 "YEAR""E" | M5: "####"E | O5: Assumptions | P5: Type | Q5: Value
B6: Line Item | O6: Revenue | P6: Custom | Q6: 0.02 | R6: 0.04 | S6: 0.03
B7: Line Item | O7: Gross Margin | P7: Step | Q7: 0.005
B8: Gross Income | O8: Operating Costs | P8: Step | Q8: 0.0075
B9: Gross Margin % | O9: EBITDA Margin | P9: Custom | R9: **ford doesn’t report
B10: Line Item | O10: Tax Rate | P10: Constant | Q10: 0.21
B11: Line Item | O11: Interest Rate on Debt | P11: Custom | Q11: 0.06 | R11: 0.05 | S11: 0.04 | T11: 0.07
B12: Operating Income
B13: Operating Margin %
B14: Line Item
B15: Income before Taxes
B16: Income Tax Expense
B17: Net Income
B18: Net Income Margin %
B19: EPS
B21: Balance Sheet
B22: Assets | D22: Q1 "YEAR""A" | E22: Q2 "YEAR""A" | F22: Q3 "YEAR""A" | G22: Q4 "YEAR""A" | H22: "####"A | I22: Q1 "YEAR""E" | J22: Q2 "YEAR""E" | K22: Q3 "YEAR""E" | L22: Q4 "YEAR""E" | M22: "####"E
B23: Line Item
B24: Line Item
B25: Total Current Assets
B26: Line Item
B27: Line Item
B28: Line Item
B29: Line Item
B30: Total Assets
B32: Liabilties
B33: Line Item
B34: Line Item
B35: Line Item
... B51: Cash Flow Statement
B52: Cash Flows from Operating Activities | D52: Q1 "YEAR""A" | E52: Q2 "YEAR""A" | F52: Q3 "YEAR""A" | G52: Q4 "YEAR""A" | H52: "####"A | I52: Q1 "YEAR""E" | J52: Q2 "YEAR""E" | K52: Q3 "YEAR""E" | L52: Q4 "YEAR""E" | M52: "####"E
B53: Line Item
B54: Line Item
B55: Total Current Assets
B56: Line Item
B57: Line Item
B58: Line Item
B59: Line Item
B60: Net Cash Provided by/(used in) Operating Activities
B62: Cash Flows from Investing Activities
B63: Line Item
B64: Line Item
B65: Line Item
... B84: Cash, Cash Equivalents, and Restricted Cash at End of Period

Sheet 3-STMT Quarterly
B2: "Company Name" Balance Sheet (UNITS)
B4: Assets | D4: Q1 "YEAR""A" | E4: Q2 "YEAR""A" | F4: Q3 "YEAR""A" | G4: Q4 "YEAR""A" | H4: "####"A | I4: Q1 "YEAR""E" | J4: Q2 "YEAR""E" | K4: Q3 "YEAR""E" | L4: Q4 "YEAR""E" | M4: "####"E
B5: Line Item
B6: Line Item
B7: Total Current Assets
B8: Line Item
B9: Line Item
B10: Line Item
B11: Line Item
B12: Total Assets
B14: Liabilties
B15: Line Item
B16: Line Item
B17: Line Item
... B31: Total Liabilities and Equity

Sheet CF STMT Annual 
B2: "Company Name" Statements of Cash Flows (UNITS)
B4: Cash Flows from Operating Activities | D4: Year"A" | E4: Year"A" | F4: Year"A" | G4: Year"A" | H4: Year"A" | I4: Year"E" | J4: Year"E"
B5: Line Item
B6: Line Item
B7: Total Current Assets
B8: Line Item
B9: Line Item
B10: Line Item
B11: Line Item
B12: Net Cash Provided by/(used in) Operating Activities
B14: Cash Flows from Investing Activities
B15: Line Item
B16: Line Item
B17: Line Item
... B36: Cash, Cash Equivalents, and Restricted Cash at End of Period

Sheet CF STMT Quarterly
B2: "Company Name" Statements of Cash Flows (UNITS)
B4: Cash Flows from Operating Activities | D4: Q1 "YEAR""A" | E4: Q2 "YEAR""A" | F4: Q3 "YEAR""A" | G4: Q4 "YEAR""A" | H4: "####"A | I4: Q1 "YEAR""E" | J4: Q2 "YEAR""E" | K4: Q3 "YEAR""E" | L4: Q4 "YEAR""E" | M4: "####"E
B5: Line Item
B6: Line Item
B7: Total Current Assets
B8: Line Item
B9: Line Item
B10: Line Item
B11: Line Item
B12: Net Cash Provided by/(used in) Operating Activities
B14: Cash Flows from Investing Activities
B15: Line Item
B16: Line Item
B17: Line Item
... B36: Cash, Cash Equivalents, and Restricted Cash at End of Period
