Workbook

Sheet Cover
B2: Microsoft Corporation
B3: MSFT
B4: 12/04/2025

Sheet Summary
B2: Microsoft Corporation
B3: Ticker | C3: MSFT
B4: Current Stock Price | C4: 477.73 | D4: As of 12/04/2025
B5: Weighted Implied Stock Price | C5: =(C9*D9)+(C10*D10)
B6: Implied Upside/Downside | C6: =(C4/C5-1)
B8: Method | C8: Weight | D8: Price Target
B9: DCF | C9: 0.5 | D9: =(C13*D13)+(C14*D14)+(C15*D15)
B10: Relative Valuation | C10: 0.5 | D10: =(C18*D18)+(C19*D19)+(C20*D20)+(C21*D21)
B12: DCF Case | C12: Weight | D12: Price Target
B13: Base | C13: 0.6 | D13: ='DCF Base'!K48
B14: Bear | C14: 0.2 | D14: ='DCF Bear'!K48
B15: Bull | C15: 0.2 | D15: ='DCF Bull'!K48
B17: Relative Method | C17: Weight | D17: Price Target
B18: EV/Sales | C18: =RV!J5 | D18: =RV!D13
B19: Price/Sales | C19: =RV!J6 | D19: =RV!E13
B20: Price/Earnings | C20: =RV!J7 | D20: =RV!F13
B21: Price/Book Value | C21: =RV!J8 | D21: =RV!G13

Sheet DCF Base
ZZ1: model_role
B2: Microsoft Corporation DCF Base
B4: WACC | E4: 0.1 | G4: Other Assumptions
B5: Beta | E5: =Beta!C5 | G5: Fiscal Year End | J5: 46022
B6: Market Risk Premium | E6: 0.0433 | G6: LTGR | J6: 0.025 | ZZ6: BS_ACCOUNTS_RECEIVABLE
B7: Risk Free Rate | E7: 0.0406 | G7: Cash & Equivalents | J7: 30242
B8: Cost of Equity | E8: =E7+(E5*E6) | G8: Shares Outstanding | J8: 7465
B9: Weight of Equity | E9: =J10/SUM(J10:J11) | G9: Current Price | J9: 477.73
B10: Cost of Debt | E10: ='3 Statement'!O9 | G10: Mkt Cap | J10: 3550971.8 | ZZ10: BS_DEBT_CURRENT
B11: After Tax CoD | E11: =E10*(1-E13) | G11: Net Debt | J11: 60588
B12: Weight of Debt | E12: =1-E9 | G12: Financial Units | J12: USD in millions | ZZ12: BS_DEBT_CURRENT
B13: Tax Rate | E13: ='3 Statement'!O8
B14: WACC | E14: =(E9*E8)+(E12*E10*(1-E13))
B16: Free Cash Flow | D16: 2023 | E16: 2024 | F16: 2025 | G16: 2026 E | H16: 2027 E | I16: 2028 E | J16: 2029 E | K16: 2030 E | ZZ16: BS_CASH
B17: Revenue | D17: ='3 Statement'!D5 | E17: ='3 Statement'!E5 | F17: ='3 Statement'!F5 | G17: ='3 Statement'!G5 | H17: ='3 Statement'!H5 | I17: ='3 Statement'!I5 | J17: ='3 Statement'!J5 | K17: ='3 Statement'!K5 | ZZ17: IS_REVENUE
B18: Revenue Growth (%) | E18: =E17/D17-1 | F18: =F17/E17-1 | G18: =0.03 | H18: =0.03 | I18: =0.03 | J18: =0.03 | K18: =0.03 | ZZ18: IS_REVENUE
B19: (-) COGS | D19: ='3 Statement'!D6 | E19: ='3 Statement'!E6 | F19: ='3 Statement'!F6 | G19: =G17-G20 | H19: =H17-H20 | I19: =I17-I20 | J19: =J17-J20 | K19: =K17-K20 | ZZ19: IS_COGS
B20: GP | D20: =D17-D19 | E20: =E17-E19 | F20: =F17-F19 | G20: =G21*G17 | H20: =H21*H17 | I20: =I21*I17 | J20: =J21*J17 | K20: =K21*K17
B21: GP Margin (%) | D21: =D20/D17 | E21: =E20/E17 | F21: =F20/F17 | G21: =0.7 | H21: =0.7 | I21: =0.7 | J21: =0.7 | K21: =0.7 | ZZ21: BS_ACCOUNTS_RECEIVABLE
B23: (-) Op Ex | D23: =-('[1]3 Statement'!D12-'[1]3 Statement'!D7) | E23: =-('[1]3 Statement'!E12-'[1]3 Statement'!E7) | F23: =-('[1]3 Statement'!F12-'[1]3 Statement'!F7) | G23: =G20-G24 | H23: =H20-H24 | I23: =I20-I24 | J23: =J20-J24 | K23: =K20-K24 | ZZ23: IS_OPERATING_EXPENSE
B24: EBIT | D24: =D20-D23 | E24: =E20-E23 | F24: =F20-F23 | G24: =G25*G17 | H24: =H25*H17 | I24: =I25*I17 | J24: =J25*J17 | K24: =K25*K17 | ZZ24: IS_EBIT
B25: EBIT Margin (%) | D25: =D24/D17 | E25: ='[2]3 Statement'!E13 | F25: ='[2]3 Statement'!F13 | G25: =0.5 | H25: =0.5 | I25: =0.5 | J25: =0.5 | K25: =0.5 | ZZ25: IS_EBIT
B27: NOPAT | D27: =D24*(1-$E$13) | E27: =E24*(1-$E$13) | F27: =F24*(1-$E$13) | G27: =G24*(1-$E$13) | H27: =H24*(1-$E$13) | I27: =I24*(1-$E$13) | J27: =J24*(1-$E$13) | K27: =K24*(1-$E$13) | ZZ27: IS_NOPAT
B28: (+) D&A | D28: ='3 Statement'!D71 | E28: ='3 Statement'!E71 | F28: ='3 Statement'!F71 | G28: =0.15*G17 | H28: =0.15*H17 | I28: =0.15*I17 | J28: =0.15*J17 | K28: =0.15*K17 | ZZ28: CF_DEPRECIATION
B29: (-) CapEx | D29: ='3 Statement'!D78 | E29: ='3 Statement'!E78 | F29: ='3 Statement'!F78 | G29: ='3 Statement'!G78 | H29: ='3 Statement'!H78 | I29: ='3 Statement'!I78 | J29: ='3 Statement'!J78 | K29: ='3 Statement'!K78 | ZZ29: CF_CAPEX
B30: (-) Changes in WC | D30: ='3 Statement'!D74 | E30: ='3 Statement'!E74 | F30: ='3 Statement'!F74 | G30: ='3 Statement'!G74 | H30: ='3 Statement'!H74 | I30: ='3 Statement'!I74 | J30: ='3 Statement'!J74 | K30: ='3 Statement'!K74 | ZZ30: CF_CHANGE_IN_WORKING_CAPITAL
B31: Unlevered Free Cash Flow | D31: =D27+D28+D29+D30 | E31: =E27+E28+E29+E30 | F31: =F27+F28+F29+F30 | G31: =G27+G28+G29+G30 | H31: =H27+H28+H29+H30 | I31: =I27+I28+I29+I30 | J31: =J27+J28+J29+J30 | K31: =K27+K28+K29+K30 | ZZ31: BS_CASH
B33: DCF | G33: 2026 E | H33: 2027 E | I33: 2028 E | J33: 2029 E | K33: 2030 E
B34: Discount Period | G34: =YEARFRAC(TODAY(),$J$5) | H34: =G34+1 | I34: =H34+1 | J34: =I34+1 | K34: =J34+1
B35: Discount Factor | G35: =(1/(1+$E$14))^G34 | H35: =(1/(1+$E$14))^H34 | I35: =(1/(1+$E$14))^I34 | J35: =(1/(1+$E$14))^J34 | K35: =(1/(1+$E$14))^K34
B37: PV of UFCF | G37: =G31*G35 | H37: =H31*H35 | I37: =I31*I35 | J37: =J31*J35 | K37: =K31*K35
B38: Total PV of UFCF | K38: =SUM(G37:K37)
B40: Terminal Value | K40: =(K31*(1+J6))/(E14-J6)
B41: PV of TV | K41: =K40*K35
B43: Enterprise Value | K43: =K41+K38
B44: (-) Net Debt | K44: =J11 | ZZ44: BS_DEBT_CURRENT
B45: Equity Value | K45: =K43-K44
B47: (/) Shares Outstanding | K47: =J8 | ZZ47: BS_ACCOUNTS_RECEIVABLE
B48: Per Share Price Target | K48: =K45/K47 | ZZ48: BS_ACCOUNTS_RECEIVABLE
B49: Implied Upside/Downside | K49: =(K48/J9-1)
B51: Sensitivity Analysis
B52: WACC Step | C52: 0.02
B53: Terminal Step | C53: 0.0025 | E53: =K48 | F53: =G53-C53 | G53: =H53-C53 | H53: =J6 | I53: =H53+C53 | J53: =I53+C53
E54: =E55-C52 | F54: =( $G$31/(1+$E$54)^$G$34 +$H$31/(1+$E$54)^$H$34 +$I$31/(1+$E$54)^$I$34 +$J$31/(1+$E$54)^$J$34 +$K$31/(1+$E$54)^$K$34 +(($K$31*(1+F$53))/($E54-F$53))/(1+$E54)^$K$34 -$K$44 )/$K$47 | G54: =( $G$31/(1+$E$54)^$G$34 +$H$31/(1+$E$54)^$H$34 +$I$31/(1+$E$54)^$I$34 +$J$31/(1+$E$54)^$J$34 +$K$31/(1+$E$54)^$K$34 +(($K$31*(1+G$53))/($E54-G$53))/(1+$E54)^$K$34 -$K$44 )/$K$47 | H54: =( $G$31/(1+$E$54)^$G$34 +$H$31/(1+$E$54)^$H$34 +$I$31/(1+$E$54)^$I$34 +$J$31/(1+$E$54)^$J$34 +$K$31/(1+$E$54)^$K$34 +(($K$31*(1+H$53))/($E54-H$53))/(1+$E54)^$K$34 -$K$44 )/$K$47 | I54: =( $G$31/(1+$E$54)^$G$34 +$H$31/(1+$E$54)^$H$34 +$I$31/(1+$E$54)^$I$34 +$J$31/(1+$E$54)^$J$34 +$K$31/(1+$E$54)^$K$34 +(($K$31*(1+I$53))/($E54-I$53))/(1+$E54)^$K$34 -$K$44 )/$K$47 | J54: =( $G$31/(1+$E$54)^$G$34 +$H$31/(1+$E$54)^$H$34 +$I$31/(1+$E$54)^$I$34 +$J$31/(1+$E$54)^$J$34 +$K$31/(1+$E$54)^$K$34 +(($K$31*(1+J$53))/($E54-J$53))/(1+$E54)^$K$34 -$K$44 )/$K$47
E55: =E56-C52 | F55: =( $G$31/(1+$E$55)^$G$34 +$H$31/(1+$E$55)^$H$34 +$I$31/(1+$E$55)^$I$34 +$J$31/(1+$E$55)^$J$34 +$K$31/(1+$E$55)^$K$34 +(($K$31*(1+F$53))/($E55-F$53))/(1+$E$55)^$K$34 -$K$44 )/$K$47 | G55: =( $G$31/(1+$E$55)^$G$34 +$H$31/(1+$E$55)^$H$34 +$I$31/(1+$E$55)^$I$34 +$J$31/(1+$E$55)^$J$34 +$K$31/(1+$E$55)^$K$34 +(($K$31*(1+G$53))/($E55-G$53))/(1+$E$55)^$K$34 -$K$44 )/$K$47 | H55: =( $G$31/(1+$E$55)^$G$34 +$H$31/(1+$E$55)^$H$34 +$I$31/(1+$E$55)^$I$34 +$J$31/(1+$E$55)^$J$34 +$K$31/(1+$E$55)^$K$34 +(($K$31*(1+H$53))/($E55-H$53))/(1+$E$55)^$K$34 -$K$44 )/$K$47 | I55: =( $G$31/(1+$E$55)^$G$34 +$H$31/(1+$E$55)^$H$34 +$I$31/(1+$E$55)^$I$34 +$J$31/(1+$E$55)^$J$34 +$K$31/(1+$E$55)^$K$34 +(($K$31*(1+I$53))/($E55-I$53))/(1+$E$55)^$K$34 -$K$44 )/$K$47 | J55: =( $G$31/(1+$E$55)^$G$34 +$H$31/(1+$E$55)^$H$34 +$I$31/(1+$E$55)^$I$34 +$J$31/(1+$E$55)^$J$34 +$K$31/(1+$E$55)^$K$34 +(($K$31*(1+J$53))/($E55-J$53))/(1+$E$55)^$K$34 -$K$44 )/$K$47
E56: =E14 | F56: =( $G$31/(1+$E$56)^$G$34 +$H$31/(1+$E$56)^$H$34 +$I$31/(1+$E$56)^$I$34 +$J$31/(1+$E$56)^$J$34 +$K$31/(1+$E$56)^$K$34 +(($K$31*(1+F$53))/($E$56-F$53))/(1+$E$56)^$K$34 -$K$44 )/$K$47 | G56: =( $G$31/(1+$E$56)^$G$34 +$H$31/(1+$E$56)^$H$34 +$I$31/(1+$E$56)^$I$34 +$J$31/(1+$E$56)^$J$34 +$K$31/(1+$E$56)^$K$34 +(($K$31*(1+G$53))/($E$56-G$53))/(1+$E$56)^$K$34 -$K$44 )/$K$47 | H56: =( $G$31/(1+$E$56)^$G$34 +$H$31/(1+$E$56)^$H$34 +$I$31/(1+$E$56)^$I$34 +$J$31/(1+$E$56)^$J$34 +$K$31/(1+$E$56)^$K$34 +(($K$31*(1+H$53))/($E$56-H$53))/(1+$E$56)^$K$34 -$K$44 )/$K$47 | I56: =( $G$31/(1+$E$56)^$G$34 +$H$31/(1+$E$56)^$H$34 +$I$31/(1+$E$56)^$I$34 +$J$31/(1+$E$56)^$J$34 +$K$31/(1+$E$56)^$K$34 +(($K$31*(1+I$53))/($E$56-I$53))/(1+$E$56)^$K$34 -$K$44 )/$K$47 | J56: =( $G$31/(1+$E$56)^$G$34 +$H$31/(1+$E$56)^$H$34 +$I$31/(1+$E$56)^$I$34 +$J$31/(1+$E$56)^$J$34 +$K$31/(1+$E$56)^$K$34 +(($K$31*(1+J$53))/($E$56-J$53))/(1+$E$56)^$K$34 -$K$44 )/$K$47
E57: =E56+C52 | F57: =( $G$31/(1+$E$57)^$G$34 +$H$31/(1+$E$57)^$H$34 +$I$31/(1+$E$57)^$I$34 +$J$31/(1+$E$57)^$J$34 +$K$31/(1+$E$57)^$K$34 +(($K$31*(1+F$53))/($E$57-F$53))/(1+$E$57)^$K$34 -$K$44 )/$K$47 | G57: =( $G$31/(1+$E$57)^$G$34 +$H$31/(1+$E$57)^$H$34 +$I$31/(1+$E$57)^$I$34 +$J$31/(1+$E$57)^$J$34 +$K$31/(1+$E$57)^$K$34 +(($K$31*(1+G$53))/($E$57-G$53))/(1+$E$57)^$K$34 -$K$44 )/$K$47 | H57: =( $G$31/(1+$E$57)^$G$34 +$H$31/(1+$E$57)^$H$34 +$I$31/(1+$E$57)^$I$34 +$J$31/(1+$E$57)^$J$34 +$K$31/(1+$E$57)^$K$34 +(($K$31*(1+H$53))/($E$57-H$53))/(1+$E$57)^$K$34 -$K$44 )/$K$47 | I57: =( $G$31/(1+$E$57)^$G$34 +$H$31/(1+$E$57)^$H$34 +$I$31/(1+$E$57)^$I$34 +$J$31/(1+$E$57)^$J$34 +$K$31/(1+$E$57)^$K$34 +(($K$31*(1+I$53))/($E$57-I$53))/(1+$E$57)^$K$34 -$K$44 )/$K$47 | J57: =( $G$31/(1+$E$57)^$G$34 +$H$31/(1+$E$57)^$H$34 +$I$31/(1+$E$57)^$I$34 +$J$31/(1+$E$57)^$J$34 +$K$31/(1+$E$57)^$K$34 +(($K$31*(1+J$53))/($E$57-J$53))/(1+$E$57)^$K$34 -$K$44 )/$K$47
E58: =E57+C52 | F58: =( $G$31/(1+$E$58)^$G$34 +$H$31/(1+$E$58)^$H$34 +$I$31/(1+$E$58)^$I$34 +$J$31/(1+$E$58)^$J$34 +$K$31/(1+$E$58)^$K$34 +(($K$31*(1+F$53))/($E$58-F$53))/(1+$E$58)^$K$34 -$K$44 )/$K$47 | G58: =( $G$31/(1+$E$58)^$G$34 +$H$31/(1+$E$58)^$H$34 +$I$31/(1+$E$58)^$I$34 +$J$31/(1+$E$58)^$J$34 +$K$31/(1+$E$58)^$K$34 +(($K$31*(1+G$53))/($E$58-G$53))/(1+$E$58)^$K$34 -$K$44 )/$K$47 | H58: =( $G$31/(1+$E$58)^$G$34 +$H$31/(1+$E$58)^$H$34 +$I$31/(1+$E$58)^$I$34 +$J$31/(1+$E$58)^$J$34 +$K$31/(1+$E$58)^$K$34 +(($K$31*(1+H$53))/($E$58-H$53))/(1+$E$58)^$K$34 -$K$44 )/$K$47 | I58: =( $G$31/(1+$E$58)^$G$34 +$H$31/(1+$E$58)^$H$34 +$I$31/(1+$E$58)^$I$34 +$J$31/(1+$E$58)^$J$34 +$K$31/(1+$E$58)^$K$34 +(($K$31*(1+I$53))/($E$58-I$53))/(1+$E$58)^$K$34 -$K$44 )/$K$47 | J58: =( $G$31/(1+$E$58)^$G$34 +$H$31/(1+$E$58)^$H$34 +$I$31/(1+$E$58)^$I$34 +$J$31/(1+$E$58)^$J$34 +$K$31/(1+$E$58)^$K$34 +(($K$31*(1+J$53))/($E$58-J$53))/(1+$E$58)^$K$34 -$K$44 )/$K$47

Sheet DCF Bear
ZZ1: model_role
B2: Microsoft Corporation DCF Bear
B4: WACC | E4: 0.1 | G4: Other Assumptions
B5: Beta | E5: =Beta!C5 | G5: Fiscal Year End | J5: 46022
B6: Market Risk Premium | E6: 0.0433 | G6: LTGR | J6: 0.025 | ZZ6: BS_ACCOUNTS_RECEIVABLE
B7: Risk Free Rate | E7: 0.0406 | G7: Cash & Equivalents | J7: ='DCF Base'!J7
B8: Cost of Equity | E8: =E7+(E5*E6) | G8: Diluted S/O | J8: ='DCF Base'!J8
B9: Weight of Equity | E9: =J10/SUM(J10:J11) | G9: Current Price | J9: ='DCF Base'!J9
B10: Cost of Debt | E10: ='3 Statement'!O9 | G10: Mkt Cap | J10: =J8*J9 | ZZ10: BS_DEBT_CURRENT
B11: After Tax CoD | E11: =E10*(1-E13) | G11: BV Debt | J11: ='DCF Base'!J11
B12: Weight of Debt | E12: =1-E9 | G12: Financial Units | J12: USD in millions | ZZ12: BS_DEBT_CURRENT
B13: Tax Rate | E13: ='3 Statement'!O8
B14: WACC | E14: =(E9*E8)+(E12*E10*(1-E13))
B16: Free Cash Flow | D16: 2023 | E16: 2024 | F16: 2025 | G16: 2026 E | H16: 2027 E | I16: 2028 E | J16: 2029 E | K16: 2030 E | ZZ16: BS_CASH
B17: Revenue | D17: ='3 Statement'!D5 | E17: ='3 Statement'!E5 | F17: ='3 Statement'!F5 | G17: =F17*(1+G18) | H17: =G17*(1+H18) | I17: =H17*(1+I18) | J17: =I17*(1+J18) | K17: =J17*(1+K18) | ZZ17: IS_REVENUE
B18: Revenue Growth (%) | E18: =E17/D17-1 | F18: =F17/E17-1 | G18: =0.02 | H18: =0.02 | I18: =0.02 | J18: =0.02 | K18: =0.02 | ZZ18: IS_REVENUE
B19: (-) COGS | D19: ='3 Statement'!D6 | E19: ='3 Statement'!E6 | F19: ='3 Statement'!F6 | G19: =G17-G20 | H19: =H17-H20 | I19: =I17-I20 | J19: =J17-J20 | K19: =K17-K20 | ZZ19: IS_COGS
B20: GP | D20: =D17-D19 | E20: =E17-E19 | F20: =F17-F19 | G20: =G17*G21 | H20: =H17*H21 | I20: =I17*I21 | J20: =J17*J21 | K20: =K17*K21
B21: GP Margin (%) | E21: =E20/E17 | F21: =F20/F17 | G21: =0.65 | H21: =0.65 | I21: =0.65 | J21: =0.65 | K21: =0.65 | ZZ21: BS_ACCOUNTS_RECEIVABLE
B23: (-) Op Ex | D23: =SUM('3 Statement'!D9:D11) | E23: =SUM('3 Statement'!E9:E11) | F23: =SUM('3 Statement'!F9:F11) | G23: =G20-G24 | H23: =H20-H24 | I23: =I20-I24 | J23: =J20-J24 | K23: =K20-K24 | ZZ23: IS_OPERATING_EXPENSE
B24: EBIT | D24: =D20+D23 | E24: =E20+E23 | F24: =F20+F23 | G24: =G25*G17 | H24: =H25*H17 | I24: =I25*I17 | J24: =J25*J17 | K24: =K25*K17 | ZZ24: IS_EBIT
B25: EBIT Margin (%) | D25: =D24/D17 | E25: =E24/E17 | F25: =F24/F17 | G25: =0.4 | H25: =0.4 | I25: =0.4 | J25: =0.4 | K25: =0.4 | ZZ25: IS_EBIT
B27: NOPAT | D27: =D24*(1-$E$13) | E27: =E24*(1-$E$13) | F27: =F24*(1-$E$13) | G27: =G24*(1-$E$13) | H27: =H24*(1-$E$13) | I27: =I24*(1-$E$13) | J27: =J24*(1-$E$13) | K27: =K24*(1-$E$13) | ZZ27: IS_NOPAT
B28: (+) D&A | D28: ='3 Statement'!D71 | E28: ='3 Statement'!E71 | F28: ='3 Statement'!F71 | G28: =0.1*G17 | H28: =0.1*H17 | I28: =0.1*I17 | J28: =0.1*J17 | K28: =0.1*K17 | ZZ28: CF_DEPRECIATION
B29: (-) CapEx | D29: ='3 Statement'!D78 | E29: ='3 Statement'!E78 | F29: ='3 Statement'!F78 | G29: =-0.17*G17 | H29: =-0.17*H17 | I29: =-0.17*I17 | J29: =-0.17*J17 | K29: =-0.17*K17 | ZZ29: CF_CAPEX
B30: (-) Changes in WC | D30: ='3 Statement'!D74 | E30: ='3 Statement'!E74 | F30: ='3 Statement'!F74 | G30: =-50.0 | H30: =-50.0 | I30: =-50.0 | J30: =-50.0 | K30: =-50.0 | ZZ30: CF_CHANGE_IN_WORKING_CAPITAL
B31: Unlevered Free Cash Flow | D31: =D27+D28+D29+D30 | E31: =E27+E28+E29+E30 | F31: =F27+F28+F29+F30 | G31: =G27+G28+G29+G30 | H31: =H27+H28+H29+H30 | I31: =I27+I28+I29+I30 | J31: =J27+J28+J29+J30 | K31: =K27+K28+K29+K30 | ZZ31: BS_CASH
B33: DCF | G33: 2026 E | H33: 2027 E | I33: 2028 E | J33: 2029 E | K33: 2030 E
B34: Discount Period | G34: =YEARFRAC(TODAY(),$J$5) | H34: =G34+1 | I34: =H34+1 | J34: =I34+1 | K34: =J34+1
B35: Discount Factor | G35: =(1/(1+$E$14))^G34 | H35: =(1/(1+$E$14))^H34 | I35: =(1/(1+$E$14))^I34 | J35: =(1/(1+$E$14))^J34 | K35: =(1/(1+$E$14))^K34
B37: PV of UFCF | G37: =G31*G35 | H37: =H31*H35 | I37: =I31*I35 | J37: =J31*J35 | K37: =K31*K35
B38: Total PV of UFCF | K38: =SUM(G37:K37)
B40: Terminal Value | K40: =(K31*(1+J6))/(E14-J6)
B41: PV of TV | K41: =K40*K35
B43: Enterprise Value | K43: =K41+K38
B44: (-) Net Debt | K44: =J11 | ZZ44: BS_DEBT_CURRENT
B45: Equity Value | K45: =K43-K44
B47: (/) Shares Outstanding | K47: =J8 | ZZ47: BS_ACCOUNTS_RECEIVABLE
B48: Per Share Price Target | K48: =K45/K47 | ZZ48: BS_ACCOUNTS_RECEIVABLE
B49: Implied Upside/Downside | K49: =(K48/J9-1)
B51: Sensitivity Analysis
B52: WACC Step | C52: 0.02
B53: Terminal Step | C53: 0.0025 | E53: =K48 | F53: =G53-C53 | G53: =H53-C53 | H53: =J6 | I53: =H53+C53 | J53: =I53+C53
E54: =E55-C52 | F54: =( $G$31/(1+$E$54)^$G$34 +$H$31/(1+$E$54)^$H$34 +$I$31/(1+$E$54)^$I$34 +$J$31/(1+$E$54)^$J$34 +$K$31/(1+$E$54)^$K$34 +(($K$31*(1+F$53))/($E54-F$53))/(1+$E54)^$K$34 -$K$44 )/$K$47 | G54: =( $G$31/(1+$E$54)^$G$34 +$H$31/(1+$E$54)^$H$34 +$I$31/(1+$E$54)^$I$34 +$J$31/(1+$E$54)^$J$34 +$K$31/(1+$E$54)^$K$34 +(($K$31*(1+G$53))/($E54-G$53))/(1+$E54)^$K$34 -$K$44 )/$K$47 | H54: =( $G$31/(1+$E$54)^$G$34 +$H$31/(1+$E$54)^$H$34 +$I$31/(1+$E$54)^$I$34 +$J$31/(1+$E$54)^$J$34 +$K$31/(1+$E$54)^$K$34 +(($K$31*(1+H$53))/($E54-H$53))/(1+$E54)^$K$34 -$K$44 )/$K$47 | I54: =( $G$31/(1+$E$54)^$G$34 +$H$31/(1+$E$54)^$H$34 +$I$31/(1+$E$54)^$I$34 +$J$31/(1+$E$54)^$J$34 +$K$31/(1+$E$54)^$K$34 +(($K$31*(1+I$53))/($E54-I$53))/(1+$E54)^$K$34 -$K$44 )/$K$47 | J54: =( $G$31/(1+$E$54)^$G$34 +$H$31/(1+$E$54)^$H$34 +$I$31/(1+$E$54)^$I$34 +$J$31/(1+$E$54)^$J$34 +$K$31/(1+$E$54)^$K$34 +(($K$31*(1+J$53))/($E54-J$53))/(1+$E54)^$K$34 -$K$44 )/$K$47
E55: =E56-C52 | F55: =( $G$31/(1+$E$55)^$G$34 +$H$31/(1+$E$55)^$H$34 +$I$31/(1+$E$55)^$I$34 +$J$31/(1+$E$55)^$J$34 +$K$31/(1+$E$55)^$K$34 +(($K$31*(1+F$53))/($E55-F$53))/(1+$E$55)^$K$34 -$K$44 )/$K$47 | G55: =( $G$31/(1+$E$55)^$G$34 +$H$31/(1+$E$55)^$H$34 +$I$31/(1+$E$55)^$I$34 +$J$31/(1+$E$55)^$J$34 +$K$31/(1+$E$55)^$K$34 +(($K$31*(1+G$53))/($E55-G$53))/(1+$E$55)^$K$34 -$K$44 )/$K$47 | H55: =( $G$31/(1+$E$55)^$G$34 +$H$31/(1+$E$55)^$H$34 +$I$31/(1+$E$55)^$I$34 +$J$31/(1+$E$55)^$J$34 +$K$31/(1+$E$55)^$K$34 +(($K$31*(1+H$53))/($E55-H$53))/(1+$E$55)^$K$34 -$K$44 )/$K$47 | I55: =( $G$31/(1+$E$55)^$G$34 +$H$31/(1+$E$55)^$H$34 +$I$31/(1+$E$55)^$I$34 +$J$31/(1+$E$55)^$J$34 +$K$31/(1+$E$55)^$K$34 +(($K$31*(1+I$53))/($E55-I$53))/(1+$E$55)^$K$34 -$K$44 )/$K$47 | J55: =( $G$31/(1+$E$55)^$G$34 +$H$31/(1+$E$55)^$H$34 +$I$31/(1+$E$55)^$I$34 +$J$31/(1+$E$55)^$J$34 +$K$31/(1+$E$55)^$K$34 +(($K$31*(1+J$53))/($E55-J$53))/(1+$E$55)^$K$34 -$K$44 )/$K$47
E56: =E14 | F56: =( $G$31/(1+$E$56)^$G$34 +$H$31/(1+$E$56)^$H$34 +$I$31/(1+$E$56)^$I$34 +$J$31/(1+$E$56)^$J$34 +$K$31/(1+$E$56)^$K$34 +(($K$31*(1+F$53))/($E$56-F$53))/(1+$E$56)^$K$34 -$K$44 )/$K$47 | G56: =( $G$31/(1+$E$56)^$G$34 +$H$31/(1+$E$56)^$H$34 +$I$31/(1+$E$56)^$I$34 +$J$31/(1+$E$56)^$J$34 +$K$31/(1+$E$56)^$K$34 +(($K$31*(1+G$53))/($E$56-G$53))/(1+$E$56)^$K$34 -$K$44 )/$K$47 | H56: =( $G$31/(1+$E$56)^$G$34 +$H$31/(1+$E$56)^$H$34 +$I$31/(1+$E$56)^$I$34 +$J$31/(1+$E$56)^$J$34 +$K$31/(1+$E$56)^$K$34 +(($K$31*(1+H$53))/($E$56-H$53))/(1+$E$56)^$K$34 -$K$44 )/$K$47 | I56: =( $G$31/(1+$E$56)^$G$34 +$H$31/(1+$E$56)^$H$34 +$I$31/(1+$E$56)^$I$34 +$J$31/(1+$E$56)^$J$34 +$K$31/(1+$E$56)^$K$34 +(($K$31*(1+I$53))/($E$56-I$53))/(1+$E$56)^$K$34 -$K$44 )/$K$47 | J56: =( $G$31/(1+$E$56)^$G$34 +$H$31/(1+$E$56)^$H$34 +$I$31/(1+$E$56)^$I$34 +$J$31/(1+$E$56)^$J$34 +$K$31/(1+$E$56)^$K$34 +(($K$31*(1+J$53))/($E$56-J$53))/(1+$E$56)^$K$34 -$K$44 )/$K$47
E57: =E56+C52 | F57: =( $G$31/(1+$E$57)^$G$34 +$H$31/(1+$E$57)^$H$34 +$I$31/(1+$E$57)^$I$34 +$J$31/(1+$E$57)^$J$34 +$K$31/(1+$E$57)^$K$34 +(($K$31*(1+F$53))/($E$57-F$53))/(1+$E$57)^$K$34 -$K$44 )/$K$47 | G57: =( $G$31/(1+$E$57)^$G$34 +$H$31/(1+$E$57)^$H$34 +$I$31/(1+$E$57)^$I$34 +$J$31/(1+$E$57)^$J$34 +$K$31/(1+$E$57)^$K$34 +(($K$31*(1+G$53))/($E$57-G$53))/(1+$E$57)^$K$34 -$K$44 )/$K$47 | H57: =( $G$31/(1+$E$57)^$G$34 +$H$31/(1+$E$57)^$H$34 +$I$31/(1+$E$57)^$I$34 +$J$31/(1+$E$57)^$J$34 +$K$31/(1+$E$57)^$K$34 +(($K$31*(1+H$53))/($E$57-H$53))/(1+$E$57)^$K$34 -$K$44 )/$K$47 | I57: =( $G$31/(1+$E$57)^$G$34 +$H$31/(1+$E$57)^$H$34 +$I$31/(1+$E$57)^$I$34 +$J$31/(1+$E$57)^$J$34 +$K$31/(1+$E$57)^$K$34 +(($K$31*(1+I$53))/($E$57-I$53))/(1+$E$57)^$K$34 -$K$44 )/$K$47 | J57: =( $G$31/(1+$E$57)^$G$34 +$H$31/(1+$E$57)^$H$34 +$I$31/(1+$E$57)^$I$34 +$J$31/(1+$E$57)^$J$34 +$K$31/(1+$E$57)^$K$34 +(($K$31*(1+J$53))/($E$57-J$53))/(1+$E$57)^$K$34 -$K$44 )/$K$47
E58: =E57+C52 | F58: =( $G$31/(1+$E$58)^$G$34 +$H$31/(1+$E$58)^$H$34 +$I$31/(1+$E$58)^$I$34 +$J$31/(1+$E$58)^$J$34 +$K$31/(1+$E$58)^$K$34 +(($K$31*(1+F$53))/($E$58-F$53))/(1+$E$58)^$K$34 -$K$44 )/$K$47 | G58: =( $G$31/(1+$E$58)^$G$34 +$H$31/(1+$E$58)^$H$34 +$I$31/(1+$E$58)^$I$34 +$J$31/(1+$E$58)^$J$34 +$K$31/(1+$E$58)^$K$34 +(($K$31*(1+G$53))/($E$58-G$53))/(1+$E$58)^$K$34 -$K$44 )/$K$47 | H58: =( $G$31/(1+$E$58)^$G$34 +$H$31/(1+$E$58)^$H$34 +$I$31/(1+$E$58)^$I$34 +$J$31/(1+$E$58)^$J$34 +$K$31/(1+$E$58)^$K$34 +(($K$31*(1+H$53))/($E$58-H$53))/(1+$E$58)^$K$34 -$K$44 )/$K$47 | I58: =( $G$31/(1+$E$58)^$G$34 +$H$31/(1+$E$58)^$H$34 +$I$31/(1+$E$58)^$I$34 +$J$31/(1+$E$58)^$J$34 +$K$31/(1+$E$58)^$K$34 +(($K$31*(1+I$53))/($E$58-I$53))/(1+$E$58)^$K$34 -$K$44 )/$K$47 | J58: =( $G$31/(1+$E$58)^$G$34 +$H$31/(1+$E$58)^$H$34 +$I$31/(1+$E$58)^$I$34 +$J$31/(1+$E$58)^$J$34 +$K$31/(1+$E$58)^$K$34 +(($K$31*(1+J$53))/($E$58-J$53))/(1+$E$58)^$K$34 -$K$44 )/$K$47

Sheet DCF Bull
ZZ1: model_role
B2: Microsoft Corporation DCF Bull
B4: WACC | E4: 0.1 | G4: Other Assumptions
B5: Beta | E5: 1.2 | G5: Fiscal Year End | J5: 46022
B6: Market Risk Premium | E6: 0.0433 | G6: LTGR | J6: 0.025 | ZZ6: BS_ACCOUNTS_RECEIVABLE
B7: Risk Free Rate | E7: 0.0406 | G7: Cash & Equivalents | J7: ='DCF Base'!J7
B8: Cost of Equity | E8: =E7+(E5*E6) | G8: Diluted S/O | J8: ='DCF Base'!J8
B9: Weight of Equity | E9: =J10/SUM(J10:J11) | G9: Current Price | J9: ='DCF Base'!J9
B10: Cost of Debt | E10: ='3 Statement'!O9 | G10: Mkt Cap | J10: =J8*J9 | ZZ10: BS_DEBT_CURRENT
B11: After Tax CoD | E11: =E10*(1-E13) | G11: BV Debt | J11: ='DCF Base'!J11
B12: Weight of Debt | E12: =1-E9 | G12: Financial Units | J12: USD in millions | ZZ12: BS_DEBT_CURRENT
B13: Tax Rate | E13: ='3 Statement'!O8
B14: WACC | E14: =(E9*E8)+(E12*E10*(1-E13))
B16: Free Cash Flow | D16: 2023 | E16: 2024 | F16: 2025 | G16: 2026 E | H16: 2027 E | I16: 2028 E | J16: 2029 E | K16: 2030 E | ZZ16: BS_CASH
B17: Revenue | D17: ='3 Statement'!D5 | E17: ='3 Statement'!E5 | F17: ='3 Statement'!F5 | G17: =F17*(1+G18) | H17: =G17*(1+H18) | I17: =H17*(1+I18) | J17: =I17*(1+J18) | K17: =J17*(1+K18) | ZZ17: IS_REVENUE
B18: Revenue Growth (%) | E18: =E17/D17-1 | F18: =F17/E17-1 | G18: =0.2 | H18: =0.2 | I18: =0.2 | J18: =0.2 | K18: =0.2 | ZZ18: IS_REVENUE
B19: (-) COGS | D19: ='3 Statement'!D6 | E19: ='3 Statement'!E6 | F19: ='3 Statement'!F6 | G19: =G17-G20 | H19: =H17-H20 | I19: =I17-I20 | J19: =J17-J20 | K19: =K17-K20 | ZZ19: IS_COGS
B20: GP | D20: =D17-D19 | E20: =E17-E19 | F20: =F17-F19 | G20: =G17*G21 | H20: =H17*H21 | I20: =I17*I21 | J20: =J17*J21 | K20: =K17*K21
B21: GP Margin (%) | E21: =E20/E17 | F21: =F20/F17 | G21: =0.8 | H21: =0.8 | I21: =0.8 | J21: =0.8 | K21: =0.8 | ZZ21: BS_ACCOUNTS_RECEIVABLE
B23: (-) Op Ex | D23: =SUM('3 Statement'!D9:D11) | E23: =SUM('3 Statement'!E9:E11) | F23: =SUM('3 Statement'!F9:F11) | G23: =G20-G24 | H23: =H20-H24 | I23: =I20-I24 | J23: =J20-J24 | K23: =K20-K24 | ZZ23: IS_OPERATING_EXPENSE
B24: EBIT | D24: =D20+D23 | E24: =E20+E23 | F24: =F20+F23 | G24: =G25*G17 | H24: =H25*H17 | I24: =I25*I17 | J24: =J25*J17 | K24: =K25*K17 | ZZ24: IS_EBIT
B25: EBIT Margin (%) | D25: =D24/D17 | E25: =E24/E17 | F25: =F24/F17 | G25: =0.55 | H25: =0.55 | I25: =0.55 | J25: =0.55 | K25: =0.55 | ZZ25: IS_EBIT
B27: NOPAT | D27: =D24*(1-$E$13) | E27: =E24*(1-$E$13) | F27: =F24*(1-$E$13) | G27: =G24*(1-$E$13) | H27: =H24*(1-$E$13) | I27: =I24*(1-$E$13) | J27: =J24*(1-$E$13) | K27: =K24*(1-$E$13) | ZZ27: IS_NOPAT
B28: (+) D&A | D28: ='3 Statement'!D71 | E28: ='3 Statement'!E71 | F28: ='3 Statement'!F71 | G28: =0.16*G17 | H28: =0.16*H17 | I28: =0.16*I17 | J28: =0.16*J17 | K28: =0.16*K17 | M28: * | ZZ28: CF_DEPRECIATION
B29: (-) CapEx | D29: ='3 Statement'!D78 | E29: ='3 Statement'!E78 | F29: ='3 Statement'!F78 | G29: =-0.17*G17 | H29: =-0.17*H17 | I29: =-0.17*I17 | J29: =-0.17*J17 | K29: =-0.17*K17 | ZZ29: CF_CAPEX
B30: (-) Changes in WC | D30: ='3 Statement'!D74 | E30: ='3 Statement'!E74 | F30: ='3 Statement'!F74 | G30: =-50.0 | H30: =-50.0 | I30: =-50.0 | J30: =-50.0 | K30: =-50.0 | ZZ30: CF_CHANGE_IN_WORKING_CAPITAL
B31: Unlevered Free Cash Flow | D31: =D27+D28+D29+D30 | E31: =E27+E28+E29+E30 | F31: =F27+F28+F29+F30 | G31: =G27+G28+G29+G30 | H31: =H27+H28+H29+H30 | I31: =I27+I28+I29+I30 | J31: =J27+J28+J29+J30 | K31: =K27+K28+K29+K30 | ZZ31: BS_CASH
B33: DCF | G33: 2026 E | H33: 2027 E | I33: 2028 E | J33: 2029 E | K33: 2030 E
B34: Discount Period | G34: =YEARFRAC(TODAY(),$J$5) | H34: =G34+1 | I34: =H34+1 | J34: =I34+1 | K34: =J34+1
B35: Discount Factor | G35: =(1/(1+$E$14))^G34 | H35: =(1/(1+$E$14))^H34 | I35: =(1/(1+$E$14))^I34 | J35: =(1/(1+$E$14))^J34 | K35: =(1/(1+$E$14))^K34
B37: PV of UFCF | G37: =G31*G35 | H37: =H31*H35 | I37: =I31*I35 | J37: =J31*J35 | K37: =K31*K35
B38: Total PV of UFCF | K38: =SUM(G37:K37)
B40: Terminal Value | K40: =(K31*(1+J6))/(E14-J6)
B41: PV of TV | K41: =K40*K35
B43: Enterprise Value | K43: =K41+K38
B44: (-) Net Debt | K44: =J11 | ZZ44: BS_DEBT_CURRENT
B45: Equity Value | K45: =K43-K44
B47: (/) Shares Outstanding | K47: =J8 | ZZ47: BS_ACCOUNTS_RECEIVABLE
B48: Per Share Price Target | K48: =K45/K47 | ZZ48: BS_ACCOUNTS_RECEIVABLE
B49: Implied Upside/Downside | K49: =(K48/J9-1)
B51: Sensitivity Analysis
B52: WACC Step | C52: 0.02
B53: Terminal Step | C53: 0.0025 | E53: =K48 | F53: =G53-C53 | G53: =H53-C53 | H53: =J6 | I53: =H53+C53 | J53: =I53+C53
E54: =E55-C52 | F54: =( $G$31/(1+$E$54)^$G$34 +$H$31/(1+$E$54)^$H$34 +$I$31/(1+$E$54)^$I$34 +$J$31/(1+$E$54)^$J$34 +$K$31/(1+$E$54)^$K$34 +(($K$31*(1+F$53))/($E54-F$53))/(1+$E54)^$K$34 -$K$44 )/$K$47 | G54: =( $G$31/(1+$E$54)^$G$34 +$H$31/(1+$E$54)^$H$34 +$I$31/(1+$E$54)^$I$34 +$J$31/(1+$E$54)^$J$34 +$K$31/(1+$E$54)^$K$34 +(($K$31*(1+G$53))/($E54-G$53))/(1+$E54)^$K$34 -$K$44 )/$K$47 | H54: =( $G$31/(1+$E$54)^$G$34 +$H$31/(1+$E$54)^$H$34 +$I$31/(1+$E$54)^$I$34 +$J$31/(1+$E$54)^$J$34 +$K$31/(1+$E$54)^$K$34 +(($K$31*(1+H$53))/($E54-H$53))/(1+$E54)^$K$34 -$K$44 )/$K$47 | I54: =( $G$31/(1+$E$54)^$G$34 +$H$31/(1+$E$54)^$H$34 +$I$31/(1+$E$54)^$I$34 +$J$31/(1+$E$54)^$J$34 +$K$31/(1+$E$54)^$K$34 +(($K$31*(1+I$53))/($E54-I$53))/(1+$E54)^$K$34 -$K$44 )/$K$47 | J54: =( $G$31/(1+$E$54)^$G$34 +$H$31/(1+$E$54)^$H$34 +$I$31/(1+$E$54)^$I$34 +$J$31/(1+$E$54)^$J$34 +$K$31/(1+$E$54)^$K$34 +(($K$31*(1+J$53))/($E54-J$53))/(1+$E54)^$K$34 -$K$44 )/$K$47
E55: =E56-C52 | F55: =( $G$31/(1+$E$55)^$G$34 +$H$31/(1+$E$55)^$H$34 +$I$31/(1+$E$55)^$I$34 +$J$31/(1+$E$55)^$J$34 +$K$31/(1+$E$55)^$K$34 +(($K$31*(1+F$53))/($E55-F$53))/(1+$E$55)^$K$34 -$K$44 )/$K$47 | G55: =( $G$31/(1+$E$55)^$G$34 +$H$31/(1+$E$55)^$H$34 +$I$31/(1+$E$55)^$I$34 +$J$31/(1+$E$55)^$J$34 +$K$31/(1+$E$55)^$K$34 +(($K$31*(1+G$53))/($E55-G$53))/(1+$E$55)^$K$34 -$K$44 )/$K$47 | H55: =( $G$31/(1+$E$55)^$G$34 +$H$31/(1+$E$55)^$H$34 +$I$31/(1+$E$55)^$I$34 +$J$31/(1+$E$55)^$J$34 +$K$31/(1+$E$55)^$K$34 +(($K$31*(1+H$53))/($E55-H$53))/(1+$E$55)^$K$34 -$K$44 )/$K$47 | I55: =( $G$31/(1+$E$55)^$G$34 +$H$31/(1+$E$55)^$H$34 +$I$31/(1+$E$55)^$I$34 +$J$31/(1+$E$55)^$J$34 +$K$31/(1+$E$55)^$K$34 +(($K$31*(1+I$53))/($E55-I$53))/(1+$E$55)^$K$34 -$K$44 )/$K$47 | J55: =( $G$31/(1+$E$55)^$G$34 +$H$31/(1+$E$55)^$H$34 +$I$31/(1+$E$55)^$I$34 +$J$31/(1+$E$55)^$J$34 +$K$31/(1+$E$55)^$K$34 +(($K$31*(1+J$53))/($E55-J$53))/(1+$E$55)^$K$34 -$K$44 )/$K$47
E56: =E14 | F56: =( $G$31/(1+$E$56)^$G$34 +$H$31/(1+$E$56)^$H$34 +$I$31/(1+$E$56)^$I$34 +$J$31/(1+$E$56)^$J$34 +$K$31/(1+$E$56)^$K$34 +(($K$31*(1+F$53))/($E$56-F$53))/(1+$E$56)^$K$34 -$K$44 )/$K$47 | G56: =( $G$31/(1+$E$56)^$G$34 +$H$31/(1+$E$56)^$H$34 +$I$31/(1+$E$56)^$I$34 +$J$31/(1+$E$56)^$J$34 +$K$31/(1+$E$56)^$K$34 +(($K$31*(1+G$53))/($E$56-G$53))/(1+$E$56)^$K$34 -$K$44 )/$K$47 | H56: =( $G$31/(1+$E$56)^$G$34 +$H$31/(1+$E$56)^$H$34 +$I$31/(1+$E$56)^$I$34 +$J$31/(1+$E$56)^$J$34 +$K$31/(1+$E$56)^$K$34 +(($K$31*(1+H$53))/($E$56-H$53))/(1+$E$56)^$K$34 -$K$44 )/$K$47 | I56: =( $G$31/(1+$E$56)^$G$34 +$H$31/(1+$E$56)^$H$34 +$I$31/(1+$E$56)^$I$34 +$J$31/(1+$E$56)^$J$34 +$K$31/(1+$E$56)^$K$34 +(($K$31*(1+I$53))/($E$56-I$53))/(1+$E$56)^$K$34 -$K$44 )/$K$47 | J56: =( $G$31/(1+$E$56)^$G$34 +$H$31/(1+$E$56)^$H$34 +$I$31/(1+$E$56)^$I$34 +$J$31/(1+$E$56)^$J$34 +$K$31/(1+$E$56)^$K$34 +(($K$31*(1+J$53))/($E$56-J$53))/(1+$E$56)^$K$34 -$K$44 )/$K$47
E57: =E56+C52 | F57: =( $G$31/(1+$E$57)^$G$34 +$H$31/(1+$E$57)^$H$34 +$I$31/(1+$E$57)^$I$34 +$J$31/(1+$E$57)^$J$34 +$K$31/(1+$E$57)^$K$34 +(($K$31*(1+F$53))/($E$57-F$53))/(1+$E$57)^$K$34 -$K$44 )/$K$47 | G57: =( $G$31/(1+$E$57)^$G$34 +$H$31/(1+$E$57)^$H$34 +$I$31/(1+$E$57)^$I$34 +$J$31/(1+$E$57)^$J$34 +$K$31/(1+$E$57)^$K$34 +(($K$31*(1+G$53))/($E$57-G$53))/(1+$E$57)^$K$34 -$K$44 )/$K$47 | H57: =( $G$31/(1+$E$57)^$G$34 +$H$31/(1+$E$57)^$H$34 +$I$31/(1+$E$57)^$I$34 +$J$31/(1+$E$57)^$J$34 +$K$31/(1+$E$57)^$K$34 +(($K$31*(1+H$53))/($E$57-H$53))/(1+$E$57)^$K$34 -$K$44 )/$K$47 | I57: =( $G$31/(1+$E$57)^$G$34 +$H$31/(1+$E$57)^$H$34 +$I$31/(1+$E$57)^$I$34 +$J$31/(1+$E$57)^$J$34 +$K$31/(1+$E$57)^$K$34 +(($K$31*(1+I$53))/($E$57-I$53))/(1+$E$57)^$K$34 -$K$44 )/$K$47 | J57: =( $G$31/(1+$E$57)^$G$34 +$H$31/(1+$E$57)^$H$34 +$I$31/(1+$E$57)^$I$34 +$J$31/(1+$E$57)^$J$34 +$K$31/(1+$E$57)^$K$34 +(($K$31*(1+J$53))/($E$57-J$53))/(1+$E$57)^$K$34 -$K$44 )/$K$47
E58: =E57+C52 | F58: =( $G$31/(1+$E$58)^$G$34 +$H$31/(1+$E$58)^$H$34 +$I$31/(1+$E$58)^$I$34 +$J$31/(1+$E$58)^$J$34 +$K$31/(1+$E$58)^$K$34 +(($K$31*(1+F$53))/($E$58-F$53))/(1+$E$58)^$K$34 -$K$44 )/$K$47 | G58: =( $G$31/(1+$E$58)^$G$34 +$H$31/(1+$E$58)^$H$34 +$I$31/(1+$E$58)^$I$34 +$J$31/(1+$E$58)^$J$34 +$K$31/(1+$E$58)^$K$34 +(($K$31*(1+G$53))/($E$58-G$53))/(1+$E$58)^$K$34 -$K$44 )/$K$47 | H58: =( $G$31/(1+$E$58)^$G$34 +$H$31/(1+$E$58)^$H$34 +$I$31/(1+$E$58)^$I$34 +$J$31/(1+$E$58)^$J$34 +$K$31/(1+$E$58)^$K$34 +(($K$31*(1+H$53))/($E$58-H$53))/(1+$E$58)^$K$34 -$K$44 )/$K$47 | I58: =( $G$31/(1+$E$58)^$G$34 +$H$31/(1+$E$58)^$H$34 +$I$31/(1+$E$58)^$I$34 +$J$31/(1+$E$58)^$J$34 +$K$31/(1+$E$58)^$K$34 +(($K$31*(1+I$53))/($E$58-I$53))/(1+$E$58)^$K$34 -$K$44 )/$K$47 | J58: =( $G$31/(1+$E$58)^$G$34 +$H$31/(1+$E$58)^$H$34 +$I$31/(1+$E$58)^$I$34 +$J$31/(1+$E$58)^$J$34 +$K$31/(1+$E$58)^$K$34 +(($K$31*(1+J$53))/($E$58-J$53))/(1+$E$58)^$K$34 -$K$44 )/$K$47

Sheet 3 Statement
ZZ1: model_role
B2: Microsoft Corporation 3 Statement Model (UNITS)
B4: Income Statement | D4: 2023 A | E4: 2024 A | F4: 2025 A | G4: 2026 E | H4: 2027 E | I4: 2028 E | J4: 2029 E | K4: 2030 E | M4: Assumptions | N4: Type | O4: Value
B5: Revenue | D5: 211915 | E5: 245122 | F5: 281724 | G5: =F5*(1+O5) | H5: =G5*(1+P5) | I5: =H5*(1+Q5) | J5: =I5*(1+R5) | K5: =J5*(1+S5) | M5: Revenue | N5: constant | O5: 0.03 | P5: 0.03 | Q5: 0.03 | R5: 0.03 | S5: 0.03 | ZZ5: IS_REVENUE
B6: Cost of Revenue | D6: 65863 | E6: 74114 | F6: 87831 | G6: =G5-G7 | H6: =H5-H7 | I6: =I5-I7 | J6: =J5-J7 | K6: =K5-K7 | M6: Gross Margin | N6: constant | O6: 0.7 | P6: 0.7 | Q6: 0.7 | R6: 0.7 | S6: 0.7 | ZZ6: IS_COGS
B7: Gross Profit | D7: 146052 | E7: 171008 | F7: 193893 | G7: =G8*G5 | H7: =H8*H5 | I7: =I8*I5 | J7: =J8*J5 | K7: =K8*K5 | M7: Operating Margin | N7: constant | O7: 0.5 | P7: 0.5 | Q7: 0.5 | R7: 0.5 | S7: 0.5 | ZZ7: IS_GROSS_PROFIT
B8: Gross Margin % | D8: =D7/D5 | E8: =E7/E5 | F8: =F7/F5 | G8: =F8+(O6) | H8: =G8+(P6) | I8: =H8+(Q6) | J8: =I8+(R6) | K8: =J8+(S6) | M8: Tax Rate | N8: constant | O8: 0.21 | P8: 0.21 | Q8: 0.21 | R8: 0.21 | S8: 0.21 | ZZ8: BS_ACCOUNTS_RECEIVABLE
B9: Research & Development Expenses | D9: 97376 | E9: 113848 | F9: 139810 | G9: =(F9/F12)*(G7-G12) | H9: =(G9/G12)*(H7-H12) | I9: =(H9/H12)*(I7-I12) | J9: =(I9/I12)*(J7-J12) | K9: =(J9/J12)*(K7-K12) | M9: Interest Rate on Debt | N9: constant | O9: 0.05 | P9: 0.05 | Q9: 0.05 | R9: 0.05 | S9: 0.05 | ZZ9: BS_ACCOUNTS_RECEIVABLE
B10: Selling, General & Administrative Expenses (SG&A) | D10: 145392 | E10: 155215 | F10: 163607 | G10: =(F10/F12)*(G7-G12) | H10: =(G10/G12)*(H7-H12) | I10: =(H10/H12)*(I7-I12) | J10: =(I10/I12)*(J7-J12) | K10: =(J10/J12)*(K7-K12) | ZZ10: IS_OPERATING_EXPENSE
B11: Other Expenses | D11: 0 | E11: 0 | F11: 0 | G11: =(F11/F12)*(G7-G12) | H11: =(G11/G12)*(H7-H12) | I11: =(H11/H12)*(I7-I12) | J11: =(I11/I12)*(J7-J12) | K11: =(J11/J12)*(K7-K12)
B12: Operating Profit | D12: 88523 | E12: 109433 | F12: 128528 | G12: =G13*G5 | H12: =H13*H5 | I12: =I13*I5 | J12: =J13*J5 | K12: =K13*K5 | ZZ12: IS_OPERATING_INCOME
B13: Operating Margin % | D13: =D12/D5 | E13: =E12/E5 | F13: =F12/F5 | G13: =F13+O7 | H13: =G13+P7 | I13: =H13+Q7 | J13: =I13+R7 | K13: =J13+S7 | ZZ13: BS_ACCOUNTS_RECEIVABLE
B14: Net Interest Income | D14: 1026 | E14: 222 | F14: 262 | G14: =($F$14/$F$5)*G5 | H14: =($F$14/$F$5)*H5 | I14: =($F$14/$F$5)*I5 | J14: =($F$14/$F$5)*J5 | K14: =($F$14/$F$5)*K5 | ZZ14: IS_NON_OPERATING_INCOME
B15: Other Non Operating Expenses | D15: 145392 | E15: 155215 | F15: 163607 | G15: =F15 | H15: =G15 | I15: =H15 | J15: =I15 | K15: =J15 | ZZ15: IS_OPERATING_EXPENSE
B16: Income Before Taxes | D16: 89311 | E16: 107787 | F16: 123627 | G16: =G12-G14-G15 | H16: =H12-H14-H15 | I16: =I12-I14-I15 | J16: =J12-J14-J15 | K16: =K12-K14-K15 | ZZ16: IS_OPERATING_INCOME
B17: Income Tax Expense | D17: 16950 | E17: 19651 | F17: 21795 | G17: =G16*O9 | H17: =H16*P9 | I17: =I16*Q9 | J17: =J16*R9 | K17: =K16*S9 | ZZ17: IS_TAX_EXPENSE
B18: Net Income | D18: 144722 | E18: 176272 | F18: 203664 | G18: =G16-G17 | H18: =H16-H17 | I18: =I16-I17 | J18: =J16-J17 | K18: =K16-K17 | ZZ18: IS_NET_INCOME
B19: Net Income Margin % | G19: =G18/G5 | H19: =H18/H5 | I19: =I18/I5 | J19: =J18/J5 | K19: =K18/K5 | ZZ19: IS_NET_INCOME
B20: EPS | D20: 9.72e-06 | E20: 1.186e-05 | F20: 1.37e-05 | G20: =G18/G21 | H20: =H18/H21 | I20: =I18/I21 | J20: =J18/J21 | K20: =K18/K21 | ZZ20: IS_NET_INCOME
B21: Weighted Average Shares Outstanding | D21: 97376 | E21: 113848 | F21: 139810 | G21: =F21+O70 | H21: =G21+P70 | I21: =H21+Q70 | J21: =I21+R70 | K21: =J21+S70 | ZZ21: BS_ACCOUNTS_RECEIVABLE
B24: Balance Sheet | D24: 2023 A | E24: 2024 A | F24: 2025 A | G24: 2026 E | H24: 2027 E | I24: 2028 E | J24: 2029 E | K24: 2030 E | M24: Assumptions | N24: Type | O24: Value
B25: Cash & Cash Equivalents | D25: 34704 | E25: 18315 | F25: 30242 | G25: =G101 | H25: =H101 | I25: =I101 | J25: =J101 | K25: =K101 | M25: Depreciation % of PPE | N25: constant | O25: 0.15 | P25: 0.15 | Q25: 0.15 | R25: 0.15 | S25: 0.15 | ZZ25: BS_CASH
B26: Short-Term Investments | D26: 76552 | E26: 57216 | F26: 64323 | G26: =(F26/F$5)*G$5 | H26: =(G26/G$5)*H$5 | I26: =(H26/H$5)*I$5 | J26: =(I26/I$5)*J$5 | K26: =(J26/J$5)*K$5 | M26: Inventory % Sales | N26: constant | O26: 0.02 | P26: 0.02 | Q26: 0.02 | R26: 0.02 | S26: 0.02
B27: Net Receivables | D27: 48688 | E27: 56924 | F27: 69905 | G27: =(F27/F$5)*G$5 | H27: =(G27/G$5)*H$5 | I27: =(H27/H$5)*I$5 | J27: =(I27/I$5)*J$5 | K27: =(J27/J$5)*K$5 | M27: Long Term Debt Change | N27: constant | O27: 0 | P27: 0 | Q27: 0 | R27: 0 | S27: 0
B28: Inventory | D28: 2500 | E28: 1246 | F28: 938 | G28: =G5*O26 | H28: =H5*P26 | I28: =I5*Q26 | J28: =J5*R26 | K28: =K5*S26 | ZZ28: BS_INVENTORY
B29: Prepaid Expenses | D29: 0 | E29: 0 | F29: 0 | G29: =(F29/F$5)*G$5 | H29: =(G29/G$5)*H$5 | I29: =(H29/H$5)*I$5 | J29: =(I29/I$5)*J$5 | K29: =(J29/J$5)*K$5
B30: Other Current Assets | D30: 21813 | E30: 26033 | F30: 25723 | G30: =(F30/F$5)*G$5 | H30: =(G30/G$5)*H$5 | I30: =(H30/H$5)*I$5 | J30: =(I30/I$5)*J$5 | K30: =(J30/J$5)*K$5
B31: Total Current Assets | D31: 184257 | E31: 159734 | F31: 191131 | G31: =SUM(G25:G30) | H31: =SUM(H25:H30) | I31: =SUM(I25:I30) | J31: =SUM(J25:J30) | K31: =SUM(K25:K30)
B32: Property, Plant & Equipment (Net) | D32: 109987 | E32: 154552 | F32: 229789 | G32: =F32-G81-G74 | H32: =G32-H81-H74 | I32: =H32-I81-I74 | J32: =I32-J81-J74 | K32: =J32-K81-K74
B33: Goodwill | D33: 67886 | E33: 119220 | F33: 119509 | G33: =F33 | H33: =G33 | I33: =H33 | J33: =I33 | K33: =J33
B34: Intangible Assets | D34: 9366 | E34: 27597 | F34: 22604 | G34: =F34 | H34: =G34 | I34: =H34 | J34: =I34 | K34: =J34
B35: Long-Term Investments | D35: 9879 | E35: 14600 | F35: 15405 | G35: =(F35/F$5)*G$5 | H35: =(G35/G$5)*H$5 | I35: =(H35/H$5)*I$5 | J35: =(I35/I$5)*J$5 | K35: =(J35/J$5)*K$5
B36: Tax Assets | D36: 0 | E36: 0 | F36: 0 | G36: =(F36/F$5)*G$5 | H36: =(G36/G$5)*H$5 | I36: =(H36/H$5)*I$5 | J36: =(I36/I$5)*J$5 | K36: =(J36/J$5)*K$5
B37: Other Non-Current Assets | D37: 30601 | E37: 36460 | F37: 40565 | G37: =(F37/F$5)*G$5 | H37: =(G37/G$5)*H$5 | I37: =(H37/H$5)*I$5 | J37: =(I37/I$5)*J$5 | K37: =(J37/J$5)*K$5
B38: Other Non-Operating Adjustments | G38: =G67-SUM(G31,G32:G37) | H38: =H67-SUM(H31,H32:H37) | I38: =I67-SUM(I31,I32:I37) | J38: =J67-SUM(J31,J32:J37) | K38: =K67-SUM(K31,K32:K37)
B39: Total Long-term Assets | D39: -2756 | E39: -1289 | F39: 2516 | G39: =SUM(G32:G37) | H39: =SUM(H32:H37) | I39: =SUM(I32:I37) | J39: =SUM(J32:J37) | K39: =SUM(K32:K37)
B40: Total Assets | D40: 411976 | E40: 512163 | F40: 619003 | G40: =SUM(G31,G39,G38) | H40: =SUM(H31,H39,H38) | I40: =SUM(I31,I39,I38) | J40: =SUM(J31,J39,J38) | K40: =SUM(K31,K39,K38)
B42: Accounts Payable | D42: 18095 | E42: 21996 | F42: 27724 | G42: =(F42/F$5)*G$5 | H42: =(G42/G$5)*H$5 | I42: =(H42/H$5)*I$5 | J42: =(I42/I$5)*J$5 | K42: =(J42/J$5)*K$5 | ZZ42: BS_ACCOUNTS_PAYABLE
B43: Other Payables | D43: 4152 | E43: 5017 | F43: 7211 | G43: =(F43/F$5)*G$5 | H43: =(G43/G$5)*H$5 | I43: =(H43/H$5)*I$5 | J43: =(I43/I$5)*J$5 | K43: =(J43/J$5)*K$5
B44: Accrued Expenses | D44: 0 | E44: 0 | F44: 0 | G44: =(F44/F$5)*G$5 | H44: =(G44/G$5)*H$5 | I44: =(H44/H$5)*I$5 | J44: =(I44/I$5)*J$5 | K44: =(J44/J$5)*K$5 | ZZ44: BS_ACCRUED_LIABILITIES
B45: Short-Term Debt | D45: 5247 | E45: 8942 | F45: 2999 | G45: =(F45/F$5)*G$5 | H45: =(G45/G$5)*H$5 | I45: =(H45/H$5)*I$5 | J45: =(I45/I$5)*J$5 | K45: =(J45/J$5)*K$5 | ZZ45: BS_DEBT_CURRENT
B46: Current Capital Lease Obligations | D46: 0 | E46: 0 | F46: 0 | G46: =(F46/F$5)*G$5 | H46: =(G46/G$5)*H$5 | I46: =(H46/H$5)*I$5 | J46: =(I46/I$5)*J$5 | K46: =(J46/J$5)*K$5 | ZZ46: BS_ACCOUNTS_PAYABLE
B47: Tax Payables | D47: 4152 | E47: 5017 | F47: 0 | G47: =(F47/F$5)*G$5 | H47: =(G47/G$5)*H$5 | I47: =(H47/H$5)*I$5 | J47: =(I47/I$5)*J$5 | K47: =(J47/J$5)*K$5
B48: Deferred Revenue (Current) | D48: 50901 | E48: 57582 | F48: 64555 | G48: =(F48/F$5)*G$5 | H48: =(G48/G$5)*H$5 | I48: =(H48/H$5)*I$5 | J48: =(I48/I$5)*J$5 | K48: =(J48/J$5)*K$5 | ZZ48: IS_REVENUE
B49: Other Current Liabilities | D49: 25754 | E49: 31749 | F49: 38729 | G49: =(F49/F$5)*G$5 | H49: =(G49/G$5)*H$5 | I49: =(H49/H$5)*I$5 | J49: =(I49/I$5)*J$5 | K49: =(J49/J$5)*K$5
B50: Total Current Liabilities | D50: 104149 | E50: 125286 | F50: 141218 | G50: =SUM(G42:G49) | H50: =SUM(H42:H49) | I50: =SUM(I42:I49) | J50: =SUM(J42:J49) | K50: =SUM(K42:K49)
B51: Long-Term Debt | D51: 41990 | E51: 42688 | F51: 40152 | G51: =F51*(1+O27) | H51: =G51*(1+P27) | I51: =H51*(1+Q27) | J51: =I51*(1+R27) | K51: =J51*(1+S27) | ZZ51: BS_DEBT_CURRENT
B52: Non-Current Capital Lease Obligations | D52: 12728 | E52: 15497 | F52: 17437 | G52: =F52 | H52: =G52 | I52: =H52 | J52: =I52 | K52: =J52 | ZZ52: BS_ACCOUNTS_PAYABLE
B53: Deferred Revenue (Non-Current) | D53: 2912 | E53: 2602 | F53: 2710 | G53: =(F53/F$5)*G$5 | H53: =(G53/G$5)*H$5 | I53: =(H53/H$5)*I$5 | J53: =(I53/I$5)*J$5 | K53: =(J53/J$5)*K$5 | ZZ53: IS_REVENUE
B54: Deferred Tax Liabilities (Non-Current) | D54: 433 | E54: 2618 | F54: 2835 | G54: =(F54/F$5)*G$5 | H54: =(G54/G$5)*H$5 | I54: =(H54/H$5)*I$5 | J54: =(I54/I$5)*J$5 | K54: =(J54/J$5)*K$5
B55: Other Non-Current Liabilities | D55: 43541 | E55: 54995 | F55: 71172 | G55: =F55 | H55: =G55 | I55: =H55 | J55: =I55 | K55: =J55
B56: Total Non-Current Liabilities | D56: 101604 | E56: 118400 | F56: 134306 | G56: =SUM(G51:G55) | H56: =SUM(H51:H55) | I56: =SUM(I51:I55) | J56: =SUM(J51:J55) | K56: =SUM(K51:K55)
B57: Total Liabilities | D57: 205753 | E57: 243686 | F57: 275524 | G57: =SUM(G50,G56) | H57: =SUM(H50,H56) | I57: =SUM(I50,I56) | J57: =SUM(J50,J56) | K57: =SUM(K50,K56)
B59: Preferred Stock | D59: 0 | E59: 0 | F59: 0 | G59: =F59+G90 | H59: =G59+H90 | I59: =H59+I90 | J59: =I59+J90 | K59: =J59+K90
B60: Treasury Stock | D60: 0 | E60: 0 | F60: 0 | G60: =F60+G89 | H60: =G60+H89 | I60: =H60+I89 | J60: =I60+J89 | K60: =J60+K89
B61: Common Stock | D61: 93718 | E61: 100923 | F61: 109095 | G61: =F61+G73 | H61: =G61+H73 | I61: =H61+I73 | J61: =I61+J73 | K61: =J61+K73
B62: Retained Earnings | D62: 118848 | E62: 173144 | F62: 237731 | G62: =F62+G18+G91 | H62: =G62+H18+H91 | I62: =H62+I18+I91 | J62: =I62+J18+J91 | K62: =J62+K18+K91 | ZZ62: BS_ACCOUNTS_RECEIVABLE
B63: Additional Paid-In Capital | D63: 0 | E63: 0 | F63: 0 | G63: =F63 | H63: =G63 | I63: =H63 | J63: =I63 | K63: =J63 | ZZ63: BS_ACCOUNTS_PAYABLE
B64: Accumulated Other Comprehensive Income (Loss) | D64: -6343 | E64: -5590 | F64: -3347 | G64: =F64 | H64: =G64 | I64: =H64 | J64: =I64 | K64: =J64
B65: Other Stockholders’ Equity | D65: 0 | E65: 0 | F65: 0 | G65: =F65 | H65: =G65 | I65: =H65 | J65: =I65 | K65: =J65
B66: Total Equity | D66: 206223 | E66: 268477 | F66: 343479 | G66: =SUM(G59:G65) | H66: =SUM(H59:H65) | I66: =SUM(I59:I65) | J66: =SUM(J59:J65) | K66: =SUM(K59:K65)
B67: Total Liabilities & Equity | D67: =SUM(D66,D57) | E67: =SUM(E66,E57) | F67: =SUM(F66,F57) | G67: =SUM(G66,G57) | H67: =SUM(H66,H57) | I67: =SUM(I66,I57) | J67: =SUM(J66,J57) | K67: =SUM(K66,K57)
B69: Cash Flow Statement | D69: 2023 A | E69: 2024 A | F69: 2025 A | G69: 2026 E | H69: 2027 E | I69: 2028 E | J69: 2029 E | K69: 2030 E | M69: Assumptions | N69: Type | O69: Value | ZZ69: BS_CASH
B70: Net Income | D70: 144722 | E70: 176272 | F70: 203664 | G70: =G18 | H70: =H18 | I70: =I18 | J70: =J18 | K70: =K18 | M70: Share Repurchases (-) | N70: constant | O70: -10 | P70: -10 | Q70: -10 | R70: -10 | S70: -10 | ZZ70: IS_NET_INCOME
B71: Depreciation & Amortization | D71: 13861 | E71: 22287 | F71: 34153 | G71: =O25*F32 | H71: =P25*G32 | I71: =Q25*H32 | J71: =R25*I32 | K71: =S25*J32 | M71: Dividend as a % of Net Incomes | N71: constant | O71: 0.11 | P71: 0.11 | Q71: 0.11 | R71: 0.11 | S71: 0.11 | ZZ71: CF_DEPRECIATION
B72: Deferred Income Tax | D72: -6059 | E72: -4738 | F72: -7056 | G72: =(-G36+G54)-(-F36+F54) | H72: =(-H36+H54)-(-G36+G54) | I72: =(-I36+I54)-(-H36+H54) | J72: =(-J36+J54)-(-I36+I54) | K72: =(-K36+K54)-(-J36+J54) | M72: CAPEX (-) | N72: constant | O72: -60000 | P72: -60000 | Q72: -60000 | R72: -60000 | S72: -60000
B73: Stock-Based Compensation | D73: 9611 | E73: 10734 | F73: 11974 | G73: =(F73/F$5)*G$5 | H73: =(G73/G$5)*H$5 | I73: =(H73/H$5)*I$5 | J73: =(I73/I$5)*J$5 | K73: =(J73/J$5)*K$5
B74: Change in Working Capital | D74: -2388 | E74: 1824 | F74: -5350 | G74: =(SUM(F27:F30,F37)-SUM(F47:F49,F42:F44,F53,F55))-(SUM(G27:G30,G37)-SUM(G47:G49,G42:G44,G53,G55)) | H74: =(SUM(G27:G30,G37)-SUM(G47:G49,G42:G44,G53,G55))-(SUM(H27:H30,H37)-SUM(H47:H49,H42:H44,H53,H55)) | I74: =(SUM(H27:H30,H37)-SUM(H47:H49,H42:H44,H53,H55))-(SUM(I27:I30,I37)-SUM(I47:I49,I42:I44,I53,I55)) | J74: =(SUM(I27:I30,I37)-SUM(I47:I49,I42:I44,I53,I55))-(SUM(J27:J30,J37)-SUM(J47:J49,J42:J44,J53,J55)) | K74: =(SUM(J27:J30,J37)-SUM(J47:J49,J42:J44,J53,J55))-(SUM(K27:K30,K37)-SUM(K47:K49,K42:K44,K53,K55)) | ZZ74: CF_CHANGE_IN_WORKING_CAPITAL
B75: Other Non-Cash Items | D75: 34704 | E75: 18315 | F75: 30242 | G75: 0 | H75: 0 | I75: 0 | J75: 0 | K75: 0 | ZZ75: BS_CASH
B76: Net Cash Provided by Operating Activities | D76: 87582 | E76: 118548 | F76: 136162 | G76: =SUM(G70:G75) | H76: =SUM(H70:H75) | I76: =SUM(I70:I75) | J76: =SUM(J70:J75) | K76: =SUM(K70:K75) | ZZ76: BS_CASH
B78: Investments in Property, Plant & Equipment (CapEx) | D78: -28107 | E78: -44477 | F78: -64551 | G78: =O72 | H78: =P72 | I78: =Q72 | J78: =R72 | K78: =S72 | ZZ78: CF_CAPEX
B79: Net Acquisitions | G79: 0 | H79: 0 | I79: 0 | J79: 0 | K79: =(J$79/$F$5)*K$5
B80: Purchases of Investments | G80: 0 | H80: 0 | I80: 0 | J80: 0 | K80: 0
B81: Sales / Maturities of Investments | D81: 211915 | E81: 245122 | F81: 281724 | G81: =F26-G26+F35-G35 | H81: =G26-H26+G35-H35 | I81: =H26-I26+H35-I35 | J81: =I26-J26+I35-J35 | K81: =J26-K26+J35-K35 | ZZ81: IS_REVENUE
B82: Other Investing Activities | G82: 0 | H82: 0 | I82: 0 | J82: 0 | K82: 0
B83: Net Cash Provided by Investing Activities | D83: 34704 | E83: 18315 | F83: 30242 | G83: =SUM(G78:G82) | H83: =SUM(H78:H82) | I83: =SUM(I78:I82) | J83: =SUM(J78:J82) | K83: =SUM(K78:K82) | ZZ83: BS_CASH
B85: Net Debt Issuance | D85: 5247 | E85: 8942 | F85: 2999 | G85: =G51+G45-F45-F51 | H85: =H51+H45-G45-G51 | I85: =I51+I45-H45-H51 | J85: =J51+J45-I45-I51 | K85: =K51+K45-J45-J51 | ZZ85: BS_DEBT_CURRENT
B86: Net Stock Issuance | D86: -20379 | E86: -15252 | F86: -16364 | G86: =O70 | H86: =P70 | I86: =Q70 | J86: =R70 | K86: =S70
B87: Net Common Stock Issuance | D87: -20379 | E87: -15252 | F87: -16364 | G87: 0 | H87: 0 | I87: 0 | J87: 0 | K87: 0
B88: Common Stock Issued | D88: 1866 | E88: 2002 | F88: 2056 | G88: 0 | H88: 0 | I88: 0 | J88: 0 | K88: 0
B89: Common Stock Repurchased | D89: -22245 | E89: -17254 | F89: -18420 | G89: 0 | H89: 0 | I89: 0 | J89: 0 | K89: 0
B90: Net Preferred Stock Issuance | D90: 0 | E90: 0 | F90: 0 | G90: 0 | H90: 0 | I90: 0 | J90: 0 | K90: 0
B91: Dividends Paid (Net) | D91: -19800 | E91: -21771 | F91: -24082 | G91: =-O71*G18 | H91: =-P71*H18 | I91: =-Q71*I18 | J91: =-R71*J18 | K91: =-S71*K18 | ZZ91: CF_DIVIDENDS_PAID
B92: Common Dividends Paid | D92: -19800 | E92: -21771 | F92: -24082 | G92: 0 | H92: 0 | I92: 0 | J92: 0 | K92: 0 | ZZ92: CF_DIVIDENDS_PAID
B93: Preferred Dividends Paid | D93: -19800 | E93: -21771 | F93: -24082 | G93: 0 | H93: 0 | I93: 0 | J93: 0 | K93: 0 | ZZ93: CF_DIVIDENDS_PAID
B94: Other Financing Activities | D94: -1006 | E94: -1309 | F94: -2291 | G94: 0 | H94: 0 | I94: 0 | J94: 0 | K94: 0
B95: Net Cash Provided by Financing Activities | D95: -43935 | E95: -37757 | F95: -51699 | G95: =SUM(G85:G94) | H95: =SUM(H85:H94) | I95: =SUM(I85:I94) | J95: =SUM(J85:J94) | K95: =SUM(K85:K94) | ZZ95: BS_CASH
B97: Effect of Foreign Exchange on Cash | D97: 34704 | E97: 18315 | F97: 30242 | G97: 0 | H97: 0 | I97: 0 | J97: 0 | K97: 0 | ZZ97: BS_CASH
B99: Cash at Beginning of Period | D99: 34704 | E99: 18315 | F99: 30242 | G99: =F101 | H99: =G101 | I99: =H101 | J99: =I101 | K99: =J101 | ZZ99: BS_CASH
B100: Net Change in Cash | D100: 20773 | E100: -16389 | F100: 11927 | G100: =G95+G97+G83+G76 | H100: =H95+H97+H83+H76 | I100: =I95+I97+I83+I76 | J100: =J95+J97+J83+J76 | K100: =K95+K97+K83+K76 | ZZ100: BS_CASH
B101: Cash at End of Period | D101: 34704 | E101: 18315 | F101: 30242 | G101: =G99+G100 | H101: =H99+H100 | I101: =I99+I100 | J101: =J99+J100 | K101: =K99+K100 | ZZ101: BS_CASH
B103: Free Cash Flow | D103: 34704 | E103: 18315 | F103: 30242 | G103: =G$12*(1-$O$9)+G71-G78-G74 | H103: =H12*(1-P9)+H71-H78-H74 | I103: =I12*(1-Q9)+I71-I78-I74 | J103: =J12*(1-R9)+J71-J78-J74 | K103: =K12*(1-S9)+K71-K78-K74 | ZZ103: BS_CASH
B106: Balance Check | D106: =D40-D67 | E106: =E40-E67 | F106: =F40-F67 | G106: =G40-G67 | H106: =H40-H67 | I106: =I40-I67 | J106: =J40-J67 | K106: =K40-K67

Sheet RV
B2: Microsoft Corporation Relative Valuation
D4: EV/Sales | E4: Price/Sales | F4: Price/Earnings | G4: Price/Book Value | I4: Weight
B5: Microsoft Corporation | D5: =G16/F16 | E5: =E16/(F16/(K16/1000000)) | F5: =E16/I16 | G5: =E16/(J16/(K16/1000000)) | I5: EV/Sales | J5: 0.25
B6: AAPL | D6: =G17/F17 | E6: =E17/(F17/(K17/1000000)) | F6: =E17/I17 | G6: =E17/(J17/(K17/1000000)) | I6: Price/Sales | J6: 0.25
B7: AMZN | D7: =G18/F18 | E7: =E18/(F18/(K18/1000000)) | F7: =E18/I18 | G7: =E18/(J18/(K18/1000000)) | I7: Price/Earnings | J7: 0.25
B8: TSLA | D8: =G19/F19 | E8: =E19/(F19/(K19/1000000)) | F8: =E19/I19 | G8: =E19/(J19/(K19/1000000)) | I8: Price/Book Value | J8: 0.25
B9: ORCL | D9: =G20/F20 | E9: =E20/(F20/(K20/1000000)) | F9: =E20/I20 | G9: =E20/(J20/(K20/1000000))
B10: Low | D10: =MIN(D5:D9) | E10: =MIN(E5:E9) | F10: =MIN(F5:F9) | G10: =MIN(G5:G9) | I10: Implied Price Target | J10: =(D13*J5)+(E13*J6)+(F13*J7)+(G13*J8)
B11: Average | D11: =AVERAGE(D5:D9) | E11: =AVERAGE(E5:E9) | F11: =AVERAGE(F5:F9) | G11: =AVERAGE(G5:G9) | I11: Implied Upside/Downside | J11: =(J10/E16)-1
B12: High | D12: =MAX(D5:D9) | E12: =MAX(E5:E9) | F12: =MAX(F5:F9) | G12: =MAX(G5:G9)
B13: Microsoft Corporation | D13: =(((D11)*F16)-H16)/(K16/1000000) | E13: =E11*(F16/(K16/1000000)) | F13: =F11*(I16) | G13: =G11*(J16/(K16/1000000))
B15: Financials | D15: Market Cap | E15: Share Price | F15: Sales | G15: Enterprise Value | H15: Net Debt | I15: EPS | J15: Book Value | K15: Shares/OS
B16: Microsoft Corporation | D16: 3550971.8 | E16: 477.73 | F16: 281724 | G16: 3581317.8 | H16: 30346 | I16: 13.64 | J16: 343479 | K16: 7465000000
B17: AAPL | D17: 4143732.7 | E17: 280.43 | F17: 416161 | G17: 4206455.7 | H17: 62723 | I17: 7.46 | J17: 73733 | K17: 15004697000
B18: AMZN | D18: 2428854.4 | E18: 227.216 | F18: 637959 | G18: 2480975.4 | H18: 52121 | I18: 5.53 | J18: 285970 | K18: 10721000000
B19: TSLA | D19: 1442674.5 | E19: 447.995 | F19: 97690 | G19: 1440158.5 | H19: -2516 | I19: 2.04 | J19: 72913 | K19: 3498000000
B20: ORCL | D20: 591344.47 | E20: 210.7951 | F20: 57399 | G20: 684662.47 | H20: 93318 | I20: 4.34 | J20: 20451 | K20: 2866000000

Sheet Beta
B2: Ticker
B3: Benchmark | C3: S&P 500
B4: Lookback (years) | C4: 5
B5: Beta | C5: =SLOPE(E8:E1261,F8:F1261)
B6: Date | C6: Ticker Adj Close | D6: Benchmark Adj Close | E6: Ticker Returns | F6: Benchmark Returns
B7: 44168 | C7: 119.67622 | D7: 3666.72
B8: 44169 | C8: 119.00455 | D8: 3699.1201 | E8: {=((C8:C1261/C7:C1260)-1)*100} | F8: {=((D8:D1261/D7:D1260)-1)*100}
B9: 44172 | C9: 120.46474 | D9: 3691.96 | E9: 1.2270034 | F9: -0.19356377
B10: 44173 | C10: 121.07798 | D10: 3702.25 | E10: 0.50906441 | F10: 0.27871481
B11: 44174 | C11: 118.54703 | D11: 3672.8201 | E11: -2.0903491 | F11: -0.79492016
B12: 44175 | C12: 119.96826 | D12: 3668.1001 | E12: 1.1988779 | F12: -0.12851081
B13: 44176 | C13: 119.16031 | D13: 3663.46 | E13: -0.67347219 | F13: -0.12649973
B14: 44179 | C14: 118.54703 | D14: 3647.49 | E14: -0.51466907 | F14: -0.4359259
B15: 44180 | C15: 124.48508 | D15: 3694.6201 | E15: 5.0090242 | F15: 1.2921249
B16: 44181 | C16: 124.41692 | D16: 3701.1699 | E16: -0.054748234 | F16: 0.17727952
B17: 44182 | C17: 125.28331 | D17: 3722.48 | E17: 0.69635737 | F17: 0.57576548
B18: 44183 | C18: 123.29747 | D18: 3709.4099 | E18: -1.5850793 | F18: -0.35111185
B19: 44186 | C19: 124.8258 | D19: 3694.9199 | E19: 1.2395453 | F19: -0.39062791
B20: 44187 | C20: 128.37888 | D20: 3687.26 | E20: 2.846429 | F20: -0.20730929
... B1261: 45993 | C1261: 285.5047 | D1261: 6812.71 | E1261: 0.84941489 | F1261: 0.0011754363

Sheet DCF Q
B2: "Company Name" DCF Analysis (UNITS)
B4: WACC | G4: Other Assumptions
B5: Beta | E5: # | G5: Fiscal Year End | J5: 46022
B6: Market Risk Premium | E6: # | G6: LTGR | J6: 0.02
B7: Risk Free Rate | E7: # | G7: Cash & Equivalents | J7: # | L7: 1 year (4 Quarters) historical and forecasted
B8: Cost of Equity | E8: =E7+(E5*E6) | G8: Diluted S/O | J8: #
B9: Weight of Equity | E9: =J10/SUM(J10:J11) | G9: Current Price | J9: #
B10: Cost of Debt | E10: # | G10: Mkt Cap | J10: =J8*J9
B11: After Tax CoD | E11: =E10*(1-E13) | G11: BV debt
B12: Weight of Debt | E12: =1-E9 | G12: Financial Units
B13: Tax Rate | E13: #
B14: WACC | E14: =(E9*E8)+(E11*E12)
B16: Free Cash Flow | D16: Q1 "YEAR""A" | E16: Q2 "YEAR""A" | F16: Q3 "YEAR""A" | G16: Q4 "YEAR""A" | H16: "####"A | I16: Q1 "YEAR""E" | J16: Q2 "YEAR""E" | K16: Q3 "YEAR""E" | L16: Q4 "YEAR""E" | M16: "####"E
B17: Revenue | D17: HIST | E17: HIST | F17: HIST | G17: HIST | H17: =SUM(D17:G17) | I17: Forecast Formula | J17: Forecast Formula | K17: Forecast Formula | L17: Forecast Formula | M17: =SUM(I17:L17)
B18: Revenue Growth (%) | E18: =IFERROR(E17/D17-1,"") | F18: =IFERROR(F17/E17-1,"") | G18: =IFERROR(G17/F17-1,"") | I18: =I17/H17-1 | J18: =J17/I17-1 | K18: =K17/J17-1 | L18: =L17/K17-1
B19: (-) COGS | D19: HIST | E19: HIST | F19: HIST | G19: HIST | H19: =SUM(D19:G19) | M19: =SUM(I19:L19)
B20: GP | D20: =D17+D19 | E20: =E17+E19 | F20: =F17+F19 | G20: =G17+G19 | H20: =H17+H19 | I20: =I17+I19 | J20: =J17+J19 | K20: =K17+K19 | ... M20: =M17+M19
B21: GP Margin (%) | D21: =D19/D17 | E21: =E19/E17 | F21: =F19/F17 | G21: =G19/G17 | H21: =H19/H17 | I21: =I19/I17 | J21: =J19/J17 | K21: =K19/K17 | ... M21: =M19/M17
B23: (-) Op Ex | D23: HIST | E23: HIST | F23: HIST | G23: HIST | H23: =SUM(D23:G23) | I23: Forecast Formula | J23: Forecast Formula | K23: Forecast Formula | L23: Forecast Formula | M23: =SUM(I23:L23)
B24: EBIT | D24: =D20+D23 | E24: =E20+E23 | F24: =F20+F23 | G24: =G20+G23 | H24: =H20+H23 | I24: =I20+I23 | J24: =J20+J23 | K24: =K20+K23 | ... M24: =M20+M23
B25: EBIT Margin (%) | D25: =D24/D17 | E25: =E24/E17 | F25: =F24/F17 | G25: =G24/G17 | H25: =H23/H17 | I25: =I23/I17 | J25: =J23/J17 | K25: =K23/K17 | L25: =L23/L17 | M25: =M23/M17
B27: NOPAT | D27: =D24*(1-$E$13) | E27: =E24*(1-$E$13) | F27: =F24*(1-$E$13) | G27: =G24*(1-$E$13) | H27: =H24*(1-$E$13) | I27: =I24*(1-$E$13) | J27: =J24*(1-$E$13) | K27: =K24*(1-$E$13) | ... M27: =M24*(1-$E$13)
B28: (+) D&A | D28: HIST | E28: HIST | F28: HIST | G28: HIST | H28: =SUM(D28:G28) | I28: Forecast Formula | J28: Forecast Formula | K28: Forecast Formula | L28: Forecast Formula | M28: =SUM(I28:L28)
B29: (-) CapEx | D29: HIST | E29: HIST | F29: HIST | G29: HIST | H29: =SUM(D29:G29) | I29: Forecast Formula | J29: Forecast Formula | K29: Forecast Formula | L29: Forecast Formula | M29: =SUM(I29:L29)
B30: (-) Changes in WC | D30: HIST | E30: HIST | F30: HIST | G30: HIST | H30: =SUM(D30:G30) | I30: Forecast Formula | J30: Forecast Formula | K30: Forecast Formula | L30: Forecast Formula | M30: =SUM(I30:L30)
B31: Unlevered Free Cash Flow | D31: =D27+D28+D29+D30 | E31: =E27+E28+E29+E30 | F31: =F27+F28+F29+F30 | G31: =G27+G28+G29+G30 | H31: =H27+H28+H29+H30 | I31: =I27+I28+I29+I30 | J31: =J27+J28+J29+J30 | K31: =K27+K28+K29+K30 | ... M31: =M27+M28+M29+M30
B33: DCF | I33: Year"E" | J33: Year"E" | K33: Year"E" | L33: Year"E" | M33: Year"E"
B34: Discount Period | I34: =YEARFRAC(TODAY(),$J$5) | J34: =I34+0.25 | K34: =J34+0.25 | L34: =K34+0.25
B35: Discount Factor | I35: =(1/(1+$E$14))^I34 | J35: =(1/(1+$E$14))^J34 | K35: =(1/(1+$E$14))^K34 | L35: =(1/(1+$E$14))^L34
B37: PV of UFCF | I37: =I31*I35 | J37: =J31*J35 | K37: =K31*K35 | L37: =L31*L35 | M37: =SUM(I37:L37)
B38: Total PV of UFCF | M38: =SUM(M37)
B40: Terminal Value | M40: =(M31*(1+J6))/(E14-F2)
B41: PV of TV | M41: =M40*M35
B43: Enterprise Value | M43: =M38+M41
B44: (-) Net Debt | M44: =-($J$11-$J$7)
B45: Equity Value | M45: =M43+M44
B47: (/) Shares Outstanding | M47: =J8
B48: Per Share Price Target | M48: =M45/M47
B49: Implied Upside/Downside | M49: =M48/J9-1

Sheet 3-STMT Q
B2: "Company Name" 3 Statement Model (UNITS)
B4: Income Statement
D5: Q1 "YEAR""A" | E5: Q2 "YEAR""A" | F5: Q3 "YEAR""A" | G5: Q4 "YEAR""A" | H5: "####"A | I5: Q1 "YEAR""E" | J5: Q2 "YEAR""E" | K5: Q3 "YEAR""E" | L5: Q4 "YEAR""E" | M5: "####"E | O5: Assumptions | P5: Type | Q5: Value
B6: Line Item | O6: Revenue | P6: Custom | Q6: 0.02 | R6: 0.04 | S6: 0.03
B7: Line Item | O7: Gross Margin | P7: Step | Q7: 0.005
B8: Gross Income | O8: Operating Costs | P8: Step | Q8: 0.0075
B9: Gross Margin % | O9: EBITDA Margin | P9: Custom | R9: **ford doesn’t report
B10: Line Item | O10: Tax Rate | P10: Constant | Q10: 0.21
B11: Line Item | O11: Interest Rate on Debt | P11: Custom | Q11: 0.06 | R11: 0.05 | S11: 0.04 | T11: 0.07
B12: Operating Income
B13: Operating Margin %
B14: Line Item
B15: Income before Taxes
B16: Income Tax Expense
B17: Net Income
B18: Net Income Margin %
B19: EPS
B21: Balance Sheet
B22: Assets | D22: Q1 "YEAR""A" | E22: Q2 "YEAR""A" | F22: Q3 "YEAR""A" | G22: Q4 "YEAR""A" | H22: "####"A | I22: Q1 "YEAR""E" | J22: Q2 "YEAR""E" | K22: Q3 "YEAR""E" | L22: Q4 "YEAR""E" | M22: "####"E
B23: Line Item
B24: Line Item
B25: Total Current Assets
B26: Line Item
B27: Line Item
B28: Line Item
B29: Line Item
B30: Total Assets
B32: Liabilties
B33: Line Item
B34: Line Item
B35: Line Item
... B51: Cash Flow Statement
B52: Cash Flows from Operating Activities | D52: Q1 "YEAR""A" | E52: Q2 "YEAR""A" | F52: Q3 "YEAR""A" | G52: Q4 "YEAR""A" | H52: "####"A | I52: Q1 "YEAR""E" | J52: Q2 "YEAR""E" | K52: Q3 "YEAR""E" | L52: Q4 "YEAR""E" | M52: "####"E
B53: Line Item
B54: Line Item
B55: Total Current Assets
B56: Line Item
B57: Line Item
B58: Line Item
B59: Line Item
B60: Net Cash Provided by/(used in) Operating Activities
B62: Cash Flows from Investing Activities
B63: Line Item
B64: Line Item
B65: Line Item
... B84: Cash, Cash Equivalents, and Restricted Cash at End of Period

Sheet 3-STMT Quarterly
B2: "Company Name" Balance Sheet (UNITS)
B4: Assets | D4: Q1 "YEAR""A" | E4: Q2 "YEAR""A" | F4: Q3 "YEAR""A" | G4: Q4 "YEAR""A" | H4: "####"A | I4: Q1 "YEAR""E" | J4: Q2 "YEAR""E" | K4: Q3 "YEAR""E" | L4: Q4 "YEAR""E" | M4: "####"E
B5: Line Item
B6: Line Item
B7: Total Current Assets
B8: Line Item
B9: Line Item
B10: Line Item
B11: Line Item
B12: Total Assets
B14: Liabilties
B15: Line Item
B16: Line Item
B17: Line Item
... B31: Total Liabilities and Equity

Sheet CF STMT Annual 
B2: "Company Name" Statements of Cash Flows (UNITS)
B4: Cash Flows from Operating Activities | D4: Year"A" | E4: Year"A" | F4: Year"A" | G4: Year"A" | H4: Year"A" | I4: Year"E" | J4: Year"E"
B5: Line Item
B6: Line Item
B7: Total Current Assets
B8: Line Item
B9: Line Item
B10: Line Item
B11: Line Item
B12: Net Cash Provided by/(used in) Operating Activities
B14: Cash Flows from Investing Activities
B15: Line Item
B16: Line Item
B17: Line Item
... B36: Cash, Cash Equivalents, and Restricted Cash at End of Period

Sheet CF STMT Quarterly
B2: "Company Name" Statements of Cash Flows (UNITS)
B4: Cash Flows from Operating Activities | D4: Q1 "YEAR""A" | E4: Q2 "YEAR""A" | F4: Q3 "YEAR""A" | G4: Q4 "YEAR""A" | H4: "####"A | I4: Q1 "YEAR""E" | J4: Q2 "YEAR""E" | K4: Q3 "YEAR""E" | L4: Q4 "YEAR""E" | M4: "####"E
B5: Line Item
B6: Line Item
B7: Total Current Assets
B8: Line Item
B9: Line Item
B10: Line Item
B11: Line Item
B12: Net Cash Provided by/(used in) Operating Activities
B14: Cash Flows from Investing Activities
B15: Line Item
B16: Line Item
B17: Line Item
... B36: Cash, Cash Equivalents, and Restricted Cash at End of Period
